Workbook
Name NextBookOptions: OFFSET(BookTracker!$O$119,0,0,COUNTA(BookTracker!$O$119:$O$100002),1)
Name TBRBookList: BookTracker!$O$1:$O$43
Name TBRBookTitles: #REF!

Sheet BookTracker
A1: 📚 Book Reading Tracker
A2: 📊 SUMMARY
A3: Metric | B3: Count | C3: Avg Words | D3: Avg Pages | E3: Avg Rating
A4: Total Books Read (All Time) | B4: =COUNTA(TotalRankings!D2:D9998)+COUNTA(TotalRankings!AJ2:AJ9998) -> 131 | C4: =AVERAGE(TotalRankings!H2:H9998) -> 198004.42 | D4: =IFERROR(ROUND(C4/350,0),"-") -> 566 | E4: =IFERROR(ROUND(AVERAGEIF(TotalRankings!$C:$C,">0"),2),"-") -> 7.59
A5: Books Read in 2026 | B5: =COUNTIF('2026BooksRead'!D2:D10000,"?*")+COUNTIF('2026BooksRead'!AJ2:AJ10000,"?*") -> 55 | C5: =AVERAGE('2026BooksRead'!H2:H10000) -> 187284.58 | D5: =IFERROR(ROUND(C5/350,0),"-") -> 535 | E5: =IFERROR(ROUND(AVERAGEIF('2026BooksRead'!$C:$C,">0"),2),"-") -> 7.7
A6: Books Read in 2025 | B6: =COUNTIF('2025BooksRead'!D2:D9999,"?*")+COUNTIF('2025BooksRead'!AJ2:AJ10000,"?*") -> 76 | C6: =AVERAGE('2025BooksRead'!H2:H9999) -> 205640.48 | D6: =IFERROR(ROUND(C6/350,0),"-") -> 588 | E6: =IFERROR(ROUND(AVERAGEIF('2025BooksRead'!$C:$C,">0"),2),"-") -> 7.51
A8: 📖 READING STATUS | B8: Book | C8: Author | D8: Genre | E8: Series | F8: Words | G8: Rank | H8: Score
A9: 📚 Last Read | B9: {=IFERROR(INDEX(TBRFinished!D:D,_xlfn.XMATCH("*",TBRFinished!D2:D10013,2,-1)+1),"None yet")} -> The Martian Chronicles | C9: {=IFERROR(INDEX(TBRFinished!F:F,_xlfn.XMATCH("*",TBRFinished!D2:D10013,2,-1)+1),"")} -> Ray Bradbury | D9: {=IFERROR(INDEX(TBRFinished!E:E,_xlfn.XMATCH("*",TBRFinished!D2:D10013,2,-1)+1),"")} -> Speculative Literary Fiction | E9: {=IFERROR(INDEX(TBRFinished!G:G,_xlfn.XMATCH("*",TBRFinished!D2:D10013,2,-1)+1),"")} -> Standalone | F9: =IF(B9="","",IFERROR(_xlfn.XLOOKUP(B9,TBRFinished!D:D,TBRFinished!H:H),"")) -> 64198 | G9: =COUNTIF(TotalRankings!$C$2:$C$401,">"&H9)+1 -> 93 | H9: =IFERROR(TEXT(_xlfn.XLOOKUP(B9,TotalRankings!D:D,TotalRankings!C:C),"0.00"),"") -> 7.11
A10: 📖 Currently Reading | B10: =ReadNext!B4 -> Endymion | C10: =IF(B10="","",IFERROR(_xlfn.XLOOKUP(B10,Recommendations!D:D,Recommendations!F:F),"")) -> Dan Simmons | D10: =IF(B10="","",IFERROR(_xlfn.XLOOKUP(B10,Recommendations!D:D,Recommendations!E:E),"")) -> Science Fiction (Hard) | E10: =IF(B10="","",IFERROR(_xlfn.XLOOKUP(B10,Recommendations!D:D,Recommendations!G:G),"")) -> Hyperion Cantos | F10: =IF(B10="","",IFERROR(_xlfn.XLOOKUP(B10,Recommendations!D:D,Recommendations!H:H),"")) -> 280000 | G10: =IF(B10="","",IFERROR(_xlfn.XLOOKUP(B10,Recommendations!D:D,Recommendations!A:A),"")) -> 63 | H10: =IF(B10="","",IFERROR(_xlfn.XLOOKUP(B10,Recommendations!D:D,Recommendations!C:C),"")) -> 7.7649269
A11: 📖🔜 Reading Next | B11: =ReadNext!B5 -> The Republic of Thieves | C11: =IF(B11="","",IFERROR(_xlfn.XLOOKUP(B11,Recommendations!D:D,Recommendations!F:F),"")) -> Scott Lynch | D11: =IF(B11="","",IFERROR(_xlfn.XLOOKUP(B11,Recommendations!D:D,Recommendations!E:E),"")) -> Epic Fantasy | E11: =IF(B11="","",IFERROR(_xlfn.XLOOKUP(B11,Recommendations!D:D,Recommendations!G:G),"")) -> Gentleman Bastards | F11: =IF(B11="","",IFERROR(_xlfn.XLOOKUP(B11,Recommendations!D:D,Recommendations!H:H),"")) -> 220000 | G11: =IF(B11="","",IFERROR(_xlfn.XLOOKUP(B11,Recommendations!D:D,Recommendations!A:A),"")) -> 74 | H11: =IF(B11="","",IFERROR(_xlfn.XLOOKUP(B11,Recommendations!D:D,Recommendations!C:C),"")) -> 7.5524151
A13: 🎭 BOOKS BY GENRE (FICTION) | B13: {=SUMPRODUCT((LEN(TotalRankings!E2:E498)>0)*1)} -> 125 | C13: =IFERROR(AVERAGE(TotalRankings!H2:H9998),"-") -> 198004.42 | D13: =IFERROR(ROUND(C13/350,0),"-") -> 566 | E13: =IFERROR(ROUND(AVERAGEIF(TotalRankings!$E:$E,">0""", TotalRankings!$C:$C),2),"-") -> 7.59 | F13: {=SUMPRODUCT((LEN('2025BooksRead'!E2:E499)>0)*1)} -> 73 | G13: =IFERROR(AVERAGE('2025BooksRead'!H2:H9999),"-") -> 205640.48 | H13: =IFERROR(ROUND(G13/350,0),"-") -> 588 | I13: =IFERROR(AVERAGEIF('2025BooksRead'!$E:$E,"<>"&"", '2025BooksRead'!$C:$C),"-") -> 4.6062218 | J13: {=SUMPRODUCT((LEN('2026BooksRead'!E2:E501)>0)*1)} -> 52 | K13: =IFERROR(AVERAGE('2026BooksRead'!H2:H10000),"-") -> 187284.58 | L13: =IFERROR(ROUND(K13/350,0),"-") -> 535 | M13: =IFERROR(ROUND(AVERAGEIF('2026BooksRead'!$C:$C,">0"),2),"-") -> 7.7
A14: Genre | B14: Books (Total) | C14: Avg Words (Total) | D14: Avg Pages (Total) | E14: Avg Rating (Total) | F14: Books (2025) | G14: Avg Words (2025) | H14: Avg Pages (2025) | I14: Avg Rating (2025) | J14: Books (2026) | K14: Avg Words (2026) | L14: Avg Pages (2026) | M14: Avg Rating (2026)
A15: {=_xlfn.SORTBY(_xlfn.UNIQUE(_xlfn._xlws.FILTER(TotalRankings!E2:E498,TotalRankings!E2:E498<>"")),COUNTIF(TotalRankings!E:E,_xlfn.UNIQUE(_xlfn._xlws.FILTER(TotalRankings!E2:E498,TotalRankings!E2:E498<>""))),-1)} -> Epic Fantasy | B15: =IF(A15="","",COUNTIF(TotalRankings!E:E,A15)) -> 53 | C15: =IF(A15="","",IFERROR(AVERAGEIF(TotalRankings!E:E,A15,TotalRankings!H:H),"-")) -> 280242.45 | D15: =IF(A15="","",IFERROR(ROUND(C15/350,0),"-")) -> 801 | E15: =IF(A15="","",IFERROR(ROUND(AVERAGEIF(TotalRankings!$E$2:$E$498,A15,TotalRankings!$C$2:$C$498),2),"-")) -> 8.06 | F15: =IF(A15="","",COUNTIF('2025BooksRead'!E:E,A15)) -> 27 | G15: =IF(A15="","",IFERROR(AVERAGEIF('2025BooksRead'!E:E,A15,'2025BooksRead'!H:H),"-")) -> 309324.07 | H15: =IF(A15="","",IFERROR(ROUND(G15/350,0),"-")) -> 884 | I15: =IF(A15="","",IFERROR(AVERAGEIF('2025BooksRead'!E:E,A15,'2025BooksRead'!C:C),"-")) -> 7.9511176 | J15: =IF(A15="","",COUNTIF('2026BooksRead'!E:E,A15)) -> 26 | K15: =IF(A15="","",IFERROR(AVERAGEIF('2026BooksRead'!E:E,A15,'2026BooksRead'!H:H),"-")) -> 250042.31 | L15: =IF(A15="","",IFERROR(ROUND(K15/350,0),"-")) -> 714 | M15: =IF(A15="","",IFERROR(AVERAGEIF('2026BooksRead'!E:E,A15,'2026BooksRead'!C:C),"-")) -> 8.1819255
A16: Science Fiction (Soft) | B16: =IF(A16="","",COUNTIF(TotalRankings!E:E,A16)) -> 16 | C16: =IF(A16="","",IFERROR(AVERAGEIF(TotalRankings!E:E,A16,TotalRankings!H:H),"-")) -> 211344.06 | D16: =IF(A16="","",IFERROR(ROUND(C16/350,0),"-")) -> 604 | E16: =IF(A16="","",IFERROR(ROUND(AVERAGEIF(TotalRankings!$E$2:$E$498,A16,TotalRankings!$C$2:$C$498),2),"-")) -> 7.46 | F16: =IF(A16="","",COUNTIF('2025BooksRead'!E:E,A16)) -> 13 | G16: =IF(A16="","",IFERROR(AVERAGEIF('2025BooksRead'!E:E,A16,'2025BooksRead'!H:H),"-")) -> 232538.85 | H16: =IF(A16="","",IFERROR(ROUND(G16/350,0),"-")) -> 664 | I16: =IF(A16="","",IFERROR(AVERAGEIF('2025BooksRead'!E:E,A16,'2025BooksRead'!C:C),"-")) -> 7.9801661 | J16: =IF(A16="","",COUNTIF('2026BooksRead'!E:E,A16)) -> 3 | K16: =IF(A16="","",IFERROR(AVERAGEIF('2026BooksRead'!E:E,A16,'2026BooksRead'!H:H),"-")) -> 119500 | L16: =IF(A16="","",IFERROR(ROUND(K16/350,0),"-")) -> 341 | M16: =IF(A16="","",IFERROR(AVERAGEIF('2026BooksRead'!E:E,A16,'2026BooksRead'!C:C),"-")) -> 5.2242853
A17: Science Fiction (Hard) | B17: =IF(A17="","",COUNTIF(TotalRankings!E:E,A17)) -> 14 | C17: =IF(A17="","",IFERROR(AVERAGEIF(TotalRankings!E:E,A17,TotalRankings!H:H),"-")) -> 126071.43 | D17: =IF(A17="","",IFERROR(ROUND(C17/350,0),"-")) -> 360 | E17: =IF(A17="","",IFERROR(ROUND(AVERAGEIF(TotalRankings!$E$2:$E$498,A17,TotalRankings!$C$2:$C$498),2),"-")) -> 7.36 | F17: =IF(A17="","",COUNTIF('2025BooksRead'!E:E,A17)) -> 8 | G17: =IF(A17="","",IFERROR(AVERAGEIF('2025BooksRead'!E:E,A17,'2025BooksRead'!H:H),"-")) -> 120000 | H17: =IF(A17="","",IFERROR(ROUND(G17/350,0),"-")) -> 343 | I17: =IF(A17="","",IFERROR(AVERAGEIF('2025BooksRead'!E:E,A17,'2025BooksRead'!C:C),"-")) -> 7.5175794 | J17: =IF(A17="","",COUNTIF('2026BooksRead'!E:E,A17)) -> 6 | K17: =IF(A17="","",IFERROR(AVERAGEIF('2026BooksRead'!E:E,A17,'2026BooksRead'!H:H),"-")) -> 134166.67 | L17: =IF(A17="","",IFERROR(ROUND(K17/350,0),"-")) -> 383 | M17: =IF(A17="","",IFERROR(AVERAGEIF('2026BooksRead'!E:E,A17,'2026BooksRead'!C:C),"-")) -> 7.1523103
A18: Literary Fantasy | B18: =IF(A18="","",COUNTIF(TotalRankings!E:E,A18)) -> 13 | C18: =IF(A18="","",IFERROR(AVERAGEIF(TotalRankings!E:E,A18,TotalRankings!H:H),"-")) -> 99923.077 | D18: =IF(A18="","",IFERROR(ROUND(C18/350,0),"-")) -> 285 | E18: =IF(A18="","",IFERROR(ROUND(AVERAGEIF(TotalRankings!$E$2:$E$498,A18,TotalRankings!$C$2:$C$498),2),"-")) -> 7.1 | F18: =IF(A18="","",COUNTIF('2025BooksRead'!E:E,A18)) -> 10 | G18: =IF(A18="","",IFERROR(AVERAGEIF('2025BooksRead'!E:E,A18,'2025BooksRead'!H:H),"-")) -> 98900 | H18: =IF(A18="","",IFERROR(ROUND(G18/350,0),"-")) -> 283 | I18: =IF(A18="","",IFERROR(AVERAGEIF('2025BooksRead'!E:E,A18,'2025BooksRead'!C:C),"-")) -> 6.7811056 | J18: =IF(A18="","",COUNTIF('2026BooksRead'!E:E,A18)) -> 3 | K18: =IF(A18="","",IFERROR(AVERAGEIF('2026BooksRead'!E:E,A18,'2026BooksRead'!H:H),"-")) -> 103333.33 | L18: =IF(A18="","",IFERROR(ROUND(K18/350,0),"-")) -> 295 | M18: =IF(A18="","",IFERROR(AVERAGEIF('2026BooksRead'!E:E,A18,'2026BooksRead'!C:C),"-")) -> 8.1419611
A19: Science Fantasy | B19: =IF(A19="","",COUNTIF(TotalRankings!E:E,A19)) -> 11 | C19: =IF(A19="","",IFERROR(AVERAGEIF(TotalRankings!E:E,A19,TotalRankings!H:H),"-")) -> 157727.27 | D19: =IF(A19="","",IFERROR(ROUND(C19/350,0),"-")) -> 451 | E19: =IF(A19="","",IFERROR(ROUND(AVERAGEIF(TotalRankings!$E$2:$E$498,A19,TotalRankings!$C$2:$C$498),2),"-")) -> 6.98 | F19: =IF(A19="","",COUNTIF('2025BooksRead'!E:E,A19)) -> 3 | G19: =IF(A19="","",IFERROR(AVERAGEIF('2025BooksRead'!E:E,A19,'2025BooksRead'!H:H),"-")) -> 120000 | H19: =IF(A19="","",IFERROR(ROUND(G19/350,0),"-")) -> 343 | I19: =IF(A19="","",IFERROR(AVERAGEIF('2025BooksRead'!E:E,A19,'2025BooksRead'!C:C),"-")) -> 5.9568403 | J19: =IF(A19="","",COUNTIF('2026BooksRead'!E:E,A19)) -> 8 | K19: =IF(A19="","",IFERROR(AVERAGEIF('2026BooksRead'!E:E,A19,'2026BooksRead'!H:H),"-")) -> 171875 | L19: =IF(A19="","",IFERROR(ROUND(K19/350,0),"-")) -> 491 | M19: =IF(A19="","",IFERROR(AVERAGEIF('2026BooksRead'!E:E,A19,'2026BooksRead'!C:C),"-")) -> 7.3618932
A20: Literary Fiction | B20: =IF(A20="","",COUNTIF(TotalRankings!E:E,A20)) -> 4 | C20: =IF(A20="","",IFERROR(AVERAGEIF(TotalRankings!E:E,A20,TotalRankings!H:H),"-")) -> 102500 | D20: =IF(A20="","",IFERROR(ROUND(C20/350,0),"-")) -> 293 | E20: =IF(A20="","",IFERROR(ROUND(AVERAGEIF(TotalRankings!$E$2:$E$498,A20,TotalRankings!$C$2:$C$498),2),"-")) -> 6 | F20: =IF(A20="","",COUNTIF('2025BooksRead'!E:E,A20)) -> 4 | G20: =IF(A20="","",IFERROR(AVERAGEIF('2025BooksRead'!E:E,A20,'2025BooksRead'!H:H),"-")) -> 102500 | H20: =IF(A20="","",IFERROR(ROUND(G20/350,0),"-")) -> 293 | I20: =IF(A20="","",IFERROR(AVERAGEIF('2025BooksRead'!E:E,A20,'2025BooksRead'!C:C),"-")) -> 5.99725 | J20: =IF(A20="","",COUNTIF('2026BooksRead'!E:E,A20)) -> 0 | K20: =IF(A20="","",IFERROR(AVERAGEIF('2026BooksRead'!E:E,A20,'2026BooksRead'!H:H),"-")) -> - | L20: =IF(A20="","",IFERROR(ROUND(K20/350,0),"-")) -> - | M20: =IF(A20="","",IFERROR(AVERAGEIF('2026BooksRead'!E:E,A20,'2026BooksRead'!C:C),"-")) -> -
A21: Russian Literature | B21: =IF(A21="","",COUNTIF(TotalRankings!E:E,A21)) -> 3 | C21: =IF(A21="","",IFERROR(AVERAGEIF(TotalRankings!E:E,A21,TotalRankings!H:H),"-")) -> 106000 | D21: =IF(A21="","",IFERROR(ROUND(C21/350,0),"-")) -> 303 | E21: =IF(A21="","",IFERROR(ROUND(AVERAGEIF(TotalRankings!$E$2:$E$498,A21,TotalRankings!$C$2:$C$498),2),"-")) -> 8.23 | F21: =IF(A21="","",COUNTIF('2025BooksRead'!E:E,A21)) -> 1 | G21: =IF(A21="","",IFERROR(AVERAGEIF('2025BooksRead'!E:E,A21,'2025BooksRead'!H:H),"-")) -> 164000 | H21: =IF(A21="","",IFERROR(ROUND(G21/350,0),"-")) -> 469 | I21: =IF(A21="","",IFERROR(AVERAGEIF('2025BooksRead'!E:E,A21,'2025BooksRead'!C:C),"-")) -> 8.5225405 | J21: =IF(A21="","",COUNTIF('2026BooksRead'!E:E,A21)) -> 2 | K21: =IF(A21="","",IFERROR(AVERAGEIF('2026BooksRead'!E:E,A21,'2026BooksRead'!H:H),"-")) -> 77000 | L21: =IF(A21="","",IFERROR(ROUND(K21/350,0),"-")) -> 220 | M21: =IF(A21="","",IFERROR(AVERAGEIF('2026BooksRead'!E:E,A21,'2026BooksRead'!C:C),"-")) -> 8.0847893
A22: Classical Epic | B22: =IF(A22="","",COUNTIF(TotalRankings!E:E,A22)) -> 3 | C22: =IF(A22="","",IFERROR(AVERAGEIF(TotalRankings!E:E,A22,TotalRankings!H:H),"-")) -> 166000 | D22: =IF(A22="","",IFERROR(ROUND(C22/350,0),"-")) -> 474 | E22: =IF(A22="","",IFERROR(ROUND(AVERAGEIF(TotalRankings!$E$2:$E$498,A22,TotalRankings!$C$2:$C$498),2),"-")) -> 7.85 | F22: =IF(A22="","",COUNTIF('2025BooksRead'!E:E,A22)) -> 3 | G22: =IF(A22="","",IFERROR(AVERAGEIF('2025BooksRead'!E:E,A22,'2025BooksRead'!H:H),"-")) -> 166000 | H22: =IF(A22="","",IFERROR(ROUND(G22/350,0),"-")) -> 474 | I22: =IF(A22="","",IFERROR(AVERAGEIF('2025BooksRead'!E:E,A22,'2025BooksRead'!C:C),"-")) -> 7.8485417 | J22: =IF(A22="","",COUNTIF('2026BooksRead'!E:E,A22)) -> 0 | K22: =IF(A22="","",IFERROR(AVERAGEIF('2026BooksRead'!E:E,A22,'2026BooksRead'!H:H),"-")) -> - | L22: =IF(A22="","",IFERROR(ROUND(K22/350,0),"-")) -> - | M22: =IF(A22="","",IFERROR(AVERAGEIF('2026BooksRead'!E:E,A22,'2026BooksRead'!C:C),"-")) -> -
A23: Speculative Literary Fiction | B23: =IF(A23="","",COUNTIF(TotalRankings!E:E,A23)) -> 3 | C23: =IF(A23="","",IFERROR(AVERAGEIF(TotalRankings!E:E,A23,TotalRankings!H:H),"-")) -> 67732.667 | D23: =IF(A23="","",IFERROR(ROUND(C23/350,0),"-")) -> 194 | E23: =IF(A23="","",IFERROR(ROUND(AVERAGEIF(TotalRankings!$E$2:$E$498,A23,TotalRankings!$C$2:$C$498),2),"-")) -> 6.06 | F23: =IF(A23="","",COUNTIF('2025BooksRead'!E:E,A23)) -> 1 | G23: =IF(A23="","",IFERROR(AVERAGEIF('2025BooksRead'!E:E,A23,'2025BooksRead'!H:H),"-")) -> 95000 | H23: =IF(A23="","",IFERROR(ROUND(G23/350,0),"-")) -> 271 | I23: =IF(A23="","",IFERROR(AVERAGEIF('2025BooksRead'!E:E,A23,'2025BooksRead'!C:C),"-")) -> 5.1551912 | J23: =IF(A23="","",COUNTIF('2026BooksRead'!E:E,A23)) -> 2 | K23: =IF(A23="","",IFERROR(AVERAGEIF('2026BooksRead'!E:E,A23,'2026BooksRead'!H:H),"-")) -> 54099 | L23: =IF(A23="","",IFERROR(ROUND(K23/350,0),"-")) -> 155 | M23: =IF(A23="","",IFERROR(AVERAGEIF('2026BooksRead'!E:E,A23,'2026BooksRead'!C:C),"-")) -> 6.5091544
A24: Gothic Fiction | B24: =IF(A24="","",COUNTIF(TotalRankings!E:E,A24)) -> 2 | C24: =IF(A24="","",IFERROR(AVERAGEIF(TotalRankings!E:E,A24,TotalRankings!H:H),"-")) -> 63500 | D24: =IF(A24="","",IFERROR(ROUND(C24/350,0),"-")) -> 181 | E24: =IF(A24="","",IFERROR(ROUND(AVERAGEIF(TotalRankings!$E$2:$E$498,A24,TotalRankings!$C$2:$C$498),2),"-")) -> 8.19 | F24: =IF(A24="","",COUNTIF('2025BooksRead'!E:E,A24)) -> 0 | G24: =IF(A24="","",IFERROR(AVERAGEIF('2025BooksRead'!E:E,A24,'2025BooksRead'!H:H),"-")) -> - | H24: =IF(A24="","",IFERROR(ROUND(G24/350,0),"-")) -> - | I24: =IF(A24="","",IFERROR(AVERAGEIF('2025BooksRead'!E:E,A24,'2025BooksRead'!C:C),"-")) -> - | J24: =IF(A24="","",COUNTIF('2026BooksRead'!E:E,A24)) -> 2 | K24: =IF(A24="","",IFERROR(AVERAGEIF('2026BooksRead'!E:E,A24,'2026BooksRead'!H:H),"-")) -> 63500 | L24: =IF(A24="","",IFERROR(ROUND(K24/350,0),"-")) -> 181 | M24: =IF(A24="","",IFERROR(AVERAGEIF('2026BooksRead'!E:E,A24,'2026BooksRead'!C:C),"-")) -> 8.1871099
A25: Classical Drama | B25: =IF(A25="","",COUNTIF(TotalRankings!E:E,A25)) -> 2 | C25: =IF(A25="","",IFERROR(AVERAGEIF(TotalRankings!E:E,A25,TotalRankings!H:H),"-")) -> 40500 | D25: =IF(A25="","",IFERROR(ROUND(C25/350,0),"-")) -> 116 | E25: =IF(A25="","",IFERROR(ROUND(AVERAGEIF(TotalRankings!$E$2:$E$498,A25,TotalRankings!$C$2:$C$498),2),"-")) -> 7.37 | F25: =IF(A25="","",COUNTIF('2025BooksRead'!E:E,A25)) -> 2 | G25: =IF(A25="","",IFERROR(AVERAGEIF('2025BooksRead'!E:E,A25,'2025BooksRead'!H:H),"-")) -> 40500 | H25: =IF(A25="","",IFERROR(ROUND(G25/350,0),"-")) -> 116 | I25: =IF(A25="","",IFERROR(AVERAGEIF('2025BooksRead'!E:E,A25,'2025BooksRead'!C:C),"-")) -> 7.3694333 | J25: =IF(A25="","",COUNTIF('2026BooksRead'!E:E,A25)) -> 0 | K25: =IF(A25="","",IFERROR(AVERAGEIF('2026BooksRead'!E:E,A25,'2026BooksRead'!H:H),"-")) -> - | L25: =IF(A25="","",IFERROR(ROUND(K25/350,0),"-")) -> - | M25: =IF(A25="","",IFERROR(AVERAGEIF('2026BooksRead'!E:E,A25,'2026BooksRead'!C:C),"-")) -> -
A26: Cyberpunk | B26: =IF(A26="","",COUNTIF(TotalRankings!E:E,A26)) -> 1 | C26: =IF(A26="","",IFERROR(AVERAGEIF(TotalRankings!E:E,A26,TotalRankings!H:H),"-")) -> 80000 | D26: =IF(A26="","",IFERROR(ROUND(C26/350,0),"-")) -> 229 | E26: =IF(A26="","",IFERROR(ROUND(AVERAGEIF(TotalRankings!$E$2:$E$498,A26,TotalRankings!$C$2:$C$498),2),"-")) -> 7.94 | F26: =IF(A26="","",COUNTIF('2025BooksRead'!E:E,A26)) -> 1 | G26: =IF(A26="","",IFERROR(AVERAGEIF('2025BooksRead'!E:E,A26,'2025BooksRead'!H:H),"-")) -> 80000 | H26: =IF(A26="","",IFERROR(ROUND(G26/350,0),"-")) -> 229 | I26: =IF(A26="","",IFERROR(AVERAGEIF('2025BooksRead'!E:E,A26,'2025BooksRead'!C:C),"-")) -> 7.9446272 | J26: =IF(A26="","",COUNTIF('2026BooksRead'!E:E,A26)) -> 0 | K26: =IF(A26="","",IFERROR(AVERAGEIF('2026BooksRead'!E:E,A26,'2026BooksRead'!H:H),"-")) -> - | L26: =IF(A26="","",IFERROR(ROUND(K26/350,0),"-")) -> - | M26: =IF(A26="","",IFERROR(AVERAGEIF('2026BooksRead'!E:E,A26,'2026BooksRead'!C:C),"-")) -> -
A28: ✍️ BOOKS BY AUTHOR (FICTION) | B28: {=SUMPRODUCT((LEN(TotalRankings!F2:F498)>0)*1)} -> 125 | C28: =AVERAGE(TotalRankings!H2:H113) -> 210268.33 | D28: =IFERROR(ROUND(C28/350,0),"-") -> 601 | E28: =IFERROR(ROUND(AVERAGEIF(TotalRankings!$E:$E,">0""", TotalRankings!$C:$C),2),"-") -> 7.59 | F28: {=SUMPRODUCT((LEN('2025BooksRead'!F2:F499)>0)*1)} -> 73 | G28: =AVERAGE('2025BooksRead'!H2:H120) -> 205640.48 | H28: =IFERROR(ROUND(G28/350,0),"-") -> 588 | I28: =IFERROR(ROUND(AVERAGE('2025BooksRead'!C2:C120),2),"-") -> 4.61 | J28: {=SUMPRODUCT((LEN('2026BooksRead'!F2:F501)>0)*1)} -> 52 | K28: =AVERAGE('2026BooksRead'!H2:H40) -> 198541.03 | L28: =IFERROR(ROUND(K28/350,0),"-") -> 567 | M28: =IFERROR(ROUND(AVERAGEIF('2026BooksRead'!$C:$C,">0"),2),"-") -> 7.7
A29: Authors | B29: Books (Total) | C29: Avg Words (Total) | D29: Avg Pages (Total) | E29: Avg Rating (Total) | F29: Books (2025) | G29: Avg Words (2025) | H29: Avg Pages (2025) | I29: Avg Rating (2025) | J29: Books (2026) | K29: Avg Words (2026) | L29: Avg Pages (2026) | M29: Avg Rating (2026)
A30: {=_xlfn.SORTBY(_xlfn.UNIQUE(_xlfn._xlws.FILTER(TotalRankings!F2:F498,TotalRankings!F2:F498<>"")),COUNTIF(TotalRankings!F:F,_xlfn.UNIQUE(_xlfn._xlws.FILTER(TotalRankings!F2:F498,TotalRankings!F2:F498<>""))),-1)} -> Brandon Sanderson | B30: =IF(A30="","",COUNTIF(TotalRankings!F:F,A30)) -> 18 | C30: =IF(A30="","",IFERROR(AVERAGEIF(TotalRankings!F:F,A30,TotalRankings!H:H),"-")) -> 246833.33 | D30: =IF(A30="","",IFERROR(ROUND(C30/350,0),"-")) -> 705 | E30: =IF(A30="","",IFERROR(ROUND(AVERAGEIF(TotalRankings!$F$2:$F$498,A30,TotalRankings!$C$2:$C$498),2),"-")) -> 7.32 | F30: =IF(A30="","",COUNTIF('2025BooksRead'!F:F,A30)) -> 18 | G30: =IF(A30="","",IFERROR(AVERAGEIF('2025BooksRead'!F:F,A30,'2025BooksRead'!H:H),"-")) -> 246833.33 | H30: =IF(A30="","",IFERROR(ROUND(G30/350,0),"-")) -> 705 | I30: =IF(A30="","",IFERROR(AVERAGEIF('2025BooksRead'!F:F,A30,'2025BooksRead'!C:C),"-")) -> 7.3179113 | J30: =IF(A30="","",COUNTIF('2026BooksRead'!F:F,A30)) -> 0 | K30: =IF(A30="","",IFERROR(AVERAGEIF('2026BooksRead'!F:F,A30,'2026BooksRead'!H:H),"-")) -> - | L30: =IF(A30="","",IFERROR(ROUND(K30/350,0),"-")) -> - | M30: =IF(A30="","",IFERROR(AVERAGEIF('2026BooksRead'!F:F,A30,'2026BooksRead'!C:C),"-")) -> -
A31: Robert Jordan | B31: =IF(A31="","",COUNTIF(TotalRankings!F:F,A31)) -> 12 | C31: =IF(A31="","",IFERROR(AVERAGEIF(TotalRankings!F:F,A31,TotalRankings!H:H),"-")) -> 280916.67 | D31: =IF(A31="","",IFERROR(ROUND(C31/350,0),"-")) -> 803 | E31: =IF(A31="","",IFERROR(ROUND(AVERAGEIF(TotalRankings!$F$2:$F$498,A31,TotalRankings!$C$2:$C$498),2),"-")) -> 8.13 | F31: =IF(A31="","",COUNTIF('2025BooksRead'!F:F,A31)) -> 12 | G31: =IF(A31="","",IFERROR(AVERAGEIF('2025BooksRead'!F:F,A31,'2025BooksRead'!H:H),"-")) -> 280916.67 | H31: =IF(A31="","",IFERROR(ROUND(G31/350,0),"-")) -> 803 | I31: =IF(A31="","",IFERROR(AVERAGEIF('2025BooksRead'!F:F,A31,'2025BooksRead'!C:C),"-")) -> 8.1250532 | J31: =IF(A31="","",COUNTIF('2026BooksRead'!F:F,A31)) -> 0 | K31: =IF(A31="","",IFERROR(AVERAGEIF('2026BooksRead'!F:F,A31,'2026BooksRead'!H:H),"-")) -> - | L31: =IF(A31="","",IFERROR(ROUND(K31/350,0),"-")) -> - | M31: =IF(A31="","",IFERROR(AVERAGEIF('2026BooksRead'!F:F,A31,'2026BooksRead'!C:C),"-")) -> -
A32: Steven Erikson | B32: =IF(A32="","",COUNTIF(TotalRankings!F:F,A32)) -> 10 | C32: =IF(A32="","",IFERROR(AVERAGEIF(TotalRankings!F:F,A32,TotalRankings!H:H),"-")) -> 329300 | D32: =IF(A32="","",IFERROR(ROUND(C32/350,0),"-")) -> 941 | E32: =IF(A32="","",IFERROR(ROUND(AVERAGEIF(TotalRankings!$F$2:$F$498,A32,TotalRankings!$C$2:$C$498),2),"-")) -> 9.01 | F32: =IF(A32="","",COUNTIF('2025BooksRead'!F:F,A32)) -> 0 | G32: =IF(A32="","",IFERROR(AVERAGEIF('2025BooksRead'!F:F,A32,'2025BooksRead'!H:H),"-")) -> - | H32: =IF(A32="","",IFERROR(ROUND(G32/350,0),"-")) -> - | I32: =IF(A32="","",IFERROR(AVERAGEIF('2025BooksRead'!F:F,A32,'2025BooksRead'!C:C),"-")) -> - | J32: =IF(A32="","",COUNTIF('2026BooksRead'!F:F,A32)) -> 10 | K32: =IF(A32="","",IFERROR(AVERAGEIF('2026BooksRead'!F:F,A32,'2026BooksRead'!H:H),"-")) -> 329300 | L32: =IF(A32="","",IFERROR(ROUND(K32/350,0),"-")) -> 941 | M32: =IF(A32="","",IFERROR(AVERAGEIF('2026BooksRead'!F:F,A32,'2026BooksRead'!C:C),"-")) -> 9.0081591
A33: Matt Dinniman | B33: =IF(A33="","",COUNTIF(TotalRankings!F:F,A33)) -> 8 | C33: =IF(A33="","",IFERROR(AVERAGEIF(TotalRankings!F:F,A33,TotalRankings!H:H),"-")) -> 171875 | D33: =IF(A33="","",IFERROR(ROUND(C33/350,0),"-")) -> 491 | E33: =IF(A33="","",IFERROR(ROUND(AVERAGEIF(TotalRankings!$F$2:$F$498,A33,TotalRankings!$C$2:$C$498),2),"-")) -> 7.36 | F33: =IF(A33="","",COUNTIF('2025BooksRead'!F:F,A33)) -> 0 | G33: =IF(A33="","",IFERROR(AVERAGEIF('2025BooksRead'!F:F,A33,'2025BooksRead'!H:H),"-")) -> - | H33: =IF(A33="","",IFERROR(ROUND(G33/350,0),"-")) -> - | I33: =IF(A33="","",IFERROR(AVERAGEIF('2025BooksRead'!F:F,A33,'2025BooksRead'!C:C),"-")) -> - | J33: =IF(A33="","",COUNTIF('2026BooksRead'!F:F,A33)) -> 8 | K33: =IF(A33="","",IFERROR(AVERAGEIF('2026BooksRead'!F:F,A33,'2026BooksRead'!H:H),"-")) -> 171875 | L33: =IF(A33="","",IFERROR(ROUND(K33/350,0),"-")) -> 491 | M33: =IF(A33="","",IFERROR(AVERAGEIF('2026BooksRead'!F:F,A33,'2026BooksRead'!C:C),"-")) -> 7.3618932
A34: Orson Scott Card | B34: =IF(A34="","",COUNTIF(TotalRankings!F:F,A34)) -> 7 | C34: =IF(A34="","",IFERROR(AVERAGEIF(TotalRankings!F:F,A34,TotalRankings!H:H),"-")) -> 121857.14 | D34: =IF(A34="","",IFERROR(ROUND(C34/350,0),"-")) -> 348 | E34: =IF(A34="","",IFERROR(ROUND(AVERAGEIF(TotalRankings!$F$2:$F$498,A34,TotalRankings!$C$2:$C$498),2),"-")) -> 6.88 | F34: =IF(A34="","",COUNTIF('2025BooksRead'!F:F,A34)) -> 6 | G34: =IF(A34="","",IFERROR(AVERAGEIF('2025BooksRead'!F:F,A34,'2025BooksRead'!H:H),"-")) -> 125500 | H34: =IF(A34="","",IFERROR(ROUND(G34/350,0),"-")) -> 359 | I34: =IF(A34="","",IFERROR(AVERAGEIF('2025BooksRead'!F:F,A34,'2025BooksRead'!C:C),"-")) -> 7.6445399 | J34: =IF(A34="","",COUNTIF('2026BooksRead'!F:F,A34)) -> 1 | K34: =IF(A34="","",IFERROR(AVERAGEIF('2026BooksRead'!F:F,A34,'2026BooksRead'!H:H),"-")) -> 100000 | L34: =IF(A34="","",IFERROR(ROUND(K34/350,0),"-")) -> 286 | M34: =IF(A34="","",IFERROR(AVERAGEIF('2026BooksRead'!F:F,A34,'2026BooksRead'!C:C),"-")) -> 2.2966095
A35: Christopher Ruocchio | B35: =IF(A35="","",COUNTIF(TotalRankings!F:F,A35)) -> 7 | C35: =IF(A35="","",IFERROR(AVERAGEIF(TotalRankings!F:F,A35,TotalRankings!H:H),"-")) -> 260571.43 | D35: =IF(A35="","",IFERROR(ROUND(C35/350,0),"-")) -> 744 | E35: =IF(A35="","",IFERROR(ROUND(AVERAGEIF(TotalRankings!$F$2:$F$498,A35,TotalRankings!$C$2:$C$498),2),"-")) -> 7.79 | F35: =IF(A35="","",COUNTIF('2025BooksRead'!F:F,A35)) -> 7 | G35: =IF(A35="","",IFERROR(AVERAGEIF('2025BooksRead'!F:F,A35,'2025BooksRead'!H:H),"-")) -> 260571.43 | H35: =IF(A35="","",IFERROR(ROUND(G35/350,0),"-")) -> 744 | I35: =IF(A35="","",IFERROR(AVERAGEIF('2025BooksRead'!F:F,A35,'2025BooksRead'!C:C),"-")) -> 7.794659 | J35: =IF(A35="","",COUNTIF('2026BooksRead'!F:F,A35)) -> 0 | K35: =IF(A35="","",IFERROR(AVERAGEIF('2026BooksRead'!F:F,A35,'2026BooksRead'!H:H),"-")) -> - | L35: =IF(A35="","",IFERROR(ROUND(K35/350,0),"-")) -> - | M35: =IF(A35="","",IFERROR(AVERAGEIF('2026BooksRead'!F:F,A35,'2026BooksRead'!C:C),"-")) -> -
A36: Joe Abercrombie | B36: =IF(A36="","",COUNTIF(TotalRankings!F:F,A36)) -> 6 | C36: =IF(A36="","",IFERROR(AVERAGEIF(TotalRankings!F:F,A36,TotalRankings!H:H),"-")) -> 204433.33 | D36: =IF(A36="","",IFERROR(ROUND(C36/350,0),"-")) -> 584 | E36: =IF(A36="","",IFERROR(ROUND(AVERAGEIF(TotalRankings!$F$2:$F$498,A36,TotalRankings!$C$2:$C$498),2),"-")) -> 8.05 | F36: =IF(A36="","",COUNTIF('2025BooksRead'!F:F,A36)) -> 0 | G36: =IF(A36="","",IFERROR(AVERAGEIF('2025BooksRead'!F:F,A36,'2025BooksRead'!H:H),"-")) -> - | H36: =IF(A36="","",IFERROR(ROUND(G36/350,0),"-")) -> - | I36: =IF(A36="","",IFERROR(AVERAGEIF('2025BooksRead'!F:F,A36,'2025BooksRead'!C:C),"-")) -> - | J36: =IF(A36="","",COUNTIF('2026BooksRead'!F:F,A36)) -> 6 | K36: =IF(A36="","",IFERROR(AVERAGEIF('2026BooksRead'!F:F,A36,'2026BooksRead'!H:H),"-")) -> 204433.33 | L36: =IF(A36="","",IFERROR(ROUND(K36/350,0),"-")) -> 584 | M36: =IF(A36="","",IFERROR(AVERAGEIF('2026BooksRead'!F:F,A36,'2026BooksRead'!C:C),"-")) -> 8.045503
A37: Pierce Brown | B37: =IF(A37="","",COUNTIF(TotalRankings!F:F,A37)) -> 6 | C37: =IF(A37="","",IFERROR(AVERAGEIF(TotalRankings!F:F,A37,TotalRankings!H:H),"-")) -> 199834.17 | D37: =IF(A37="","",IFERROR(ROUND(C37/350,0),"-")) -> 571 | E37: =IF(A37="","",IFERROR(ROUND(AVERAGEIF(TotalRankings!$F$2:$F$498,A37,TotalRankings!$C$2:$C$498),2),"-")) -> 8.2 | F37: =IF(A37="","",COUNTIF('2025BooksRead'!F:F,A37)) -> 6 | G37: =IF(A37="","",IFERROR(AVERAGEIF('2025BooksRead'!F:F,A37,'2025BooksRead'!H:H),"-")) -> 199834.17 | H37: =IF(A37="","",IFERROR(ROUND(G37/350,0),"-")) -> 571 | I37: =IF(A37="","",IFERROR(AVERAGEIF('2025BooksRead'!F:F,A37,'2025BooksRead'!C:C),"-")) -> 8.1965909 | J37: =IF(A37="","",COUNTIF('2026BooksRead'!F:F,A37)) -> 0 | K37: =IF(A37="","",IFERROR(AVERAGEIF('2026BooksRead'!F:F,A37,'2026BooksRead'!H:H),"-")) -> - | L37: =IF(A37="","",IFERROR(ROUND(K37/350,0),"-")) -> - | M37: =IF(A37="","",IFERROR(AVERAGEIF('2026BooksRead'!F:F,A37,'2026BooksRead'!C:C),"-")) -> -
A38: J.R.R. Tolkien | B38: =IF(A38="","",COUNTIF(TotalRankings!F:F,A38)) -> 4 | C38: =IF(A38="","",IFERROR(AVERAGEIF(TotalRankings!F:F,A38,TotalRankings!H:H),"-")) -> 138000 | D38: =IF(A38="","",IFERROR(ROUND(C38/350,0),"-")) -> 394 | E38: =IF(A38="","",IFERROR(ROUND(AVERAGEIF(TotalRankings!$F$2:$F$498,A38,TotalRankings!$C$2:$C$498),2),"-")) -> 8.26 | F38: =IF(A38="","",COUNTIF('2025BooksRead'!F:F,A38)) -> 0 | G38: =IF(A38="","",IFERROR(AVERAGEIF('2025BooksRead'!F:F,A38,'2025BooksRead'!H:H),"-")) -> - | H38: =IF(A38="","",IFERROR(ROUND(G38/350,0),"-")) -> - | I38: =IF(A38="","",IFERROR(AVERAGEIF('2025BooksRead'!F:F,A38,'2025BooksRead'!C:C),"-")) -> - | J38: =IF(A38="","",COUNTIF('2026BooksRead'!F:F,A38)) -> 4 | K38: =IF(A38="","",IFERROR(AVERAGEIF('2026BooksRead'!F:F,A38,'2026BooksRead'!H:H),"-")) -> 138000 | L38: =IF(A38="","",IFERROR(ROUND(K38/350,0),"-")) -> 394 | M38: =IF(A38="","",IFERROR(AVERAGEIF('2026BooksRead'!F:F,A38,'2026BooksRead'!C:C),"-")) -> 8.2589387
A39: Tad Williams | B39: =IF(A39="","",COUNTIF(TotalRankings!F:F,A39)) -> 3 | C39: =IF(A39="","",IFERROR(AVERAGEIF(TotalRankings!F:F,A39,TotalRankings!H:H),"-")) -> 296916.67 | D39: =IF(A39="","",IFERROR(ROUND(C39/350,0),"-")) -> 848 | E39: =IF(A39="","",IFERROR(ROUND(AVERAGEIF(TotalRankings!$F$2:$F$498,A39,TotalRankings!$C$2:$C$498),2),"-")) -> 5.81 | F39: =IF(A39="","",COUNTIF('2025BooksRead'!F:F,A39)) -> 2 | G39: =IF(A39="","",IFERROR(AVERAGEIF('2025BooksRead'!F:F,A39,'2025BooksRead'!H:H),"-")) -> 185375 | H39: =IF(A39="","",IFERROR(ROUND(G39/350,0),"-")) -> 530 | I39: =IF(A39="","",IFERROR(AVERAGEIF('2025BooksRead'!F:F,A39,'2025BooksRead'!C:C),"-")) -> 5.6161373 | J39: =IF(A39="","",COUNTIF('2026BooksRead'!F:F,A39)) -> 1 | K39: =IF(A39="","",IFERROR(AVERAGEIF('2026BooksRead'!F:F,A39,'2026BooksRead'!H:H),"-")) -> 520000 | L39: =IF(A39="","",IFERROR(ROUND(K39/350,0),"-")) -> 1486 | M39: =IF(A39="","",IFERROR(AVERAGEIF('2026BooksRead'!F:F,A39,'2026BooksRead'!C:C),"-")) -> 6.2030794
A40: Timothy Zahn | B40: =IF(A40="","",COUNTIF(TotalRankings!F:F,A40)) -> 3 | C40: =IF(A40="","",IFERROR(AVERAGEIF(TotalRankings!F:F,A40,TotalRankings!H:H),"-")) -> 120000 | D40: =IF(A40="","",IFERROR(ROUND(C40/350,0),"-")) -> 343 | E40: =IF(A40="","",IFERROR(ROUND(AVERAGEIF(TotalRankings!$F$2:$F$498,A40,TotalRankings!$C$2:$C$498),2),"-")) -> 5.96 | F40: =IF(A40="","",COUNTIF('2025BooksRead'!F:F,A40)) -> 3 | G40: =IF(A40="","",IFERROR(AVERAGEIF('2025BooksRead'!F:F,A40,'2025BooksRead'!H:H),"-")) -> 120000 | H40: =IF(A40="","",IFERROR(ROUND(G40/350,0),"-")) -> 343 | I40: =IF(A40="","",IFERROR(AVERAGEIF('2025BooksRead'!F:F,A40,'2025BooksRead'!C:C),"-")) -> 5.9568403 | J40: =IF(A40="","",COUNTIF('2026BooksRead'!F:F,A40)) -> 0 | K40: =IF(A40="","",IFERROR(AVERAGEIF('2026BooksRead'!F:F,A40,'2026BooksRead'!H:H),"-")) -> - | L40: =IF(A40="","",IFERROR(ROUND(K40/350,0),"-")) -> - | M40: =IF(A40="","",IFERROR(AVERAGEIF('2026BooksRead'!F:F,A40,'2026BooksRead'!C:C),"-")) -> -
A41: Dan Simmons | B41: =IF(A41="","",COUNTIF(TotalRankings!F:F,A41)) -> 2 | C41: =IF(A41="","",IFERROR(AVERAGEIF(TotalRankings!F:F,A41,TotalRankings!H:H),"-")) -> 235000 | D41: =IF(A41="","",IFERROR(ROUND(C41/350,0),"-")) -> 671 | E41: =IF(A41="","",IFERROR(ROUND(AVERAGEIF(TotalRankings!$F$2:$F$498,A41,TotalRankings!$C$2:$C$498),2),"-")) -> 9.26 | F41: =IF(A41="","",COUNTIF('2025BooksRead'!F:F,A41)) -> 0 | G41: =IF(A41="","",IFERROR(AVERAGEIF('2025BooksRead'!F:F,A41,'2025BooksRead'!H:H),"-")) -> - | H41: =IF(A41="","",IFERROR(ROUND(G41/350,0),"-")) -> - | I41: =IF(A41="","",IFERROR(AVERAGEIF('2025BooksRead'!F:F,A41,'2025BooksRead'!C:C),"-")) -> - | J41: =IF(A41="","",COUNTIF('2026BooksRead'!F:F,A41)) -> 2 | K41: =IF(A41="","",IFERROR(AVERAGEIF('2026BooksRead'!F:F,A41,'2026BooksRead'!H:H),"-")) -> 235000 | L41: =IF(A41="","",IFERROR(ROUND(K41/350,0),"-")) -> 671 | M41: =IF(A41="","",IFERROR(AVERAGEIF('2026BooksRead'!F:F,A41,'2026BooksRead'!C:C),"-")) -> 9.2649405
A42: Michael Ende | B42: =IF(A42="","",COUNTIF(TotalRankings!F:F,A42)) -> 2 | C42: =IF(A42="","",IFERROR(AVERAGEIF(TotalRankings!F:F,A42,TotalRankings!H:H),"-")) -> 105500 | D42: =IF(A42="","",IFERROR(ROUND(C42/350,0),"-")) -> 301 | E42: =IF(A42="","",IFERROR(ROUND(AVERAGEIF(TotalRankings!$F$2:$F$498,A42,TotalRankings!$C$2:$C$498),2),"-")) -> 8.66 | F42: =IF(A42="","",COUNTIF('2025BooksRead'!F:F,A42)) -> 1 | G42: =IF(A42="","",IFERROR(AVERAGEIF('2025BooksRead'!F:F,A42,'2025BooksRead'!H:H),"-")) -> 111000 | H42: =IF(A42="","",IFERROR(ROUND(G42/350,0),"-")) -> 317 | I42: =IF(A42="","",IFERROR(AVERAGEIF('2025BooksRead'!F:F,A42,'2025BooksRead'!C:C),"-")) -> 9.2712056 | J42: =IF(A42="","",COUNTIF('2026BooksRead'!F:F,A42)) -> 1 | K42: =IF(A42="","",IFERROR(AVERAGEIF('2026BooksRead'!F:F,A42,'2026BooksRead'!H:H),"-")) -> 100000 | L42: =IF(A42="","",IFERROR(ROUND(K42/350,0),"-")) -> 286 | M42: =IF(A42="","",IFERROR(AVERAGEIF('2026BooksRead'!F:F,A42,'2026BooksRead'!C:C),"-")) -> 8.04125
... A73: William Kennedy | B73: =IF(A73="","",COUNTIF(TotalRankings!F:F,A73)) -> 1 | C73: =IF(A73="","",IFERROR(AVERAGEIF(TotalRankings!F:F,A73,TotalRankings!H:H),"-")) -> 57000 | D73: =IF(A73="","",IFERROR(ROUND(C73/350,0),"-")) -> 163 | E73: =IF(A73="","",IFERROR(ROUND(AVERAGEIF(TotalRankings!$F$2:$F$498,A73,TotalRankings!$C$2:$C$498),2),"-")) -> 4.78 | F73: =IF(A73="","",COUNTIF('2025BooksRead'!F:F,A73)) -> 1 | G73: =IF(A73="","",IFERROR(AVERAGEIF('2025BooksRead'!F:F,A73,'2025BooksRead'!H:H),"-")) -> 57000 | H73: =IF(A73="","",IFERROR(ROUND(G73/350,0),"-")) -> 163 | I73: =IF(A73="","",IFERROR(AVERAGEIF('2025BooksRead'!F:F,A73,'2025BooksRead'!C:C),"-")) -> 4.7791 | J73: =IF(A73="","",COUNTIF('2026BooksRead'!F:F,A73)) -> 0 | K73: =IF(A73="","",IFERROR(AVERAGEIF('2026BooksRead'!F:F,A73,'2026BooksRead'!H:H),"-")) -> - | L73: =IF(A73="","",IFERROR(ROUND(K73/350,0),"-")) -> - | M73: =IF(A73="","",IFERROR(AVERAGEIF('2026BooksRead'!F:F,A73,'2026BooksRead'!C:C),"-")) -> -
B74: =IF(A74="","",COUNTIF(TotalRankings!F:F,A74)) | C74: =IF(A74="","",IFERROR(AVERAGEIF(TotalRankings!F:F,A74,TotalRankings!H:H),"-")) | D74: =IF(A74="","",IFERROR(ROUND(C74/350,0),"-")) | E74: =IF(A74="","",IFERROR(ROUND(AVERAGEIF(TotalRankings!$F$2:$F$498,A74,TotalRankings!$C$2:$C$498),2),"-")) | F74: =IF(A74="","",COUNTIF('2025BooksRead'!F:F,A74)) | G74: =IF(A74="","",IFERROR(AVERAGEIF('2025BooksRead'!F:F,A74,'2025BooksRead'!H:H),"-")) | H74: =IF(A74="","",IFERROR(ROUND(G74/350,0),"-")) | I74: =IF(A74="","",IFERROR(AVERAGEIF('2025BooksRead'!F:F,A74,'2025BooksRead'!C:C),"-")) | J74: =IF(A74="","",COUNTIF('2026BooksRead'!F:F,A74)) | K74: =IF(A74="","",IFERROR(AVERAGEIF('2026BooksRead'!F:F,A74,'2026BooksRead'!H:H),"-")) | L74: =IF(A74="","",IFERROR(ROUND(K74/350,0),"-")) | M74: =IF(A74="","",IFERROR(AVERAGEIF('2026BooksRead'!F:F,A74,'2026BooksRead'!C:C),"-"))
A76: ✍️ BOOKS BY AUTHOR (NON-FICTION) | B76: =COUNTA(TotalRankings!$AK$2:$AK$498) -> 6 | C76: =IFERROR(ROUND((SUM('2025BooksRead'!$AL$2:$AL$100)+SUM('2026BooksRead'!$AL$2:$AL$100))/(COUNT('2025BooksRead'!$AL$2:$AL$100)+COUNT('2026BooksRead'!$AL$2:$AL$100)),0),"-") -> 61417 | D76: =IFERROR(ROUND(C76/350,0),"-") -> 175 | E76: =IFERROR(AVERAGE(TotalRankings!$AI$2:$AI$498),"-") -> 7.337963 | F76: =COUNTIF('2025BooksRead'!$AK$2:$AK$100,"<>") -> 3 | G76: =IFERROR(ROUND(AVERAGE('2025BooksRead'!$AL$2:$AL$100),0),"-") -> 97167 | H76: =IFERROR(ROUND(G76/350,0),"-") -> 278 | I76: =IFERROR(AVERAGE('2025BooksRead'!$AI$2:$AI$100),"-") -> 7.3481481 | J76: =COUNTIF('2026BooksRead'!$AK$2:$AK$100,"<>") -> 3 | K76: =IFERROR(ROUND(AVERAGE('2026BooksRead'!$AL$2:$AL$100),0),"-") -> 25667 | L76: =IFERROR(ROUND(K76/350,0),"-") -> 73 | M76: =IFERROR(AVERAGE('2026BooksRead'!$AI$2:$AI$100),"-") -> 7.3277778
A77: Authors | B77: Books (Total) | C77: Avg Words (Total) | D77: Avg Pages (Total) | E77: Avg Rating (Total) | F77: Books (2025) | G77: Avg Words (2025) | H77: Avg Pages (2025) | I77: Avg Rating (2025) | J77: Books (2026) | K77: Avg Words (2026) | L77: Avg Pages (2026) | M77: Avg Rating (2026)
A78: {=IFERROR(_xlfn.SORTBY(_xlfn.UNIQUE(_xlfn._xlws.FILTER(TotalRankings!$AK$2:$AK$498,TotalRankings!$AK$2:$AK$498<>"")),AVERAGEIF(TotalRankings!$AK$2:$AK$498,_xlfn.UNIQUE(_xlfn._xlws.FILTER(TotalRankings!$AK$2:$AK$498,TotalRankings!$AK$2:$AK$498<>"")),TotalRankings!$AI$2:$AI$498),-1),"")} -> Sigmund Freud | B78: =IF(A78="","",COUNTIF(TotalRankings!AK:AK,A78)) -> 1 | C78: =IF(A78="","",IFERROR(ROUND((SUMIF('2025BooksRead'!$AK:$AK,A78,'2025BooksRead'!$AL:$AL)+SUMIF('2026BooksRead'!$AK:$AK,A78,'2026BooksRead'!$AL:$AL))/(COUNTIF('2025BooksRead'!$AK:$AK,A78)+COUNTIF('2026BooksRead'!$AK:$AK,A78)),0),"-")) -> 20000 | D78: =IF(A78="","",IFERROR(ROUND(C78/350,0),"-")) -> 57 | E78: =IF(A78="","",IFERROR(ROUND(AVERAGEIF(TotalRankings!$AK$2:$AK$498,A78,TotalRankings!$AI$2:$AI$498),2),"-")) -> 8.11 | F78: =IF(A78="","",COUNTIF('2025BooksRead'!AK:AK,A78)) -> 0 | G78: =IF(A78="","",IFERROR(AVERAGEIF('2025BooksRead'!$AK:$AK,A78,'2025BooksRead'!$AL:$AL),"-")) -> - | H78: =IF(A78="","",IFERROR(ROUND(G78/350,0),"-")) -> - | I78: =IF(A78="","",IFERROR(AVERAGEIF('2025BooksRead'!AK:AK,A78,'2025BooksRead'!AI:AI),"-")) -> - | J78: =IF(A78="","",COUNTIF('2026BooksRead'!AK:AK,A78)) -> 1 | K78: =IF(A78="","",IFERROR(AVERAGEIF('2026BooksRead'!$AK:$AK,A78,'2026BooksRead'!$AL:$AL),"-")) -> 20000 | L78: =IF(A78="","",IFERROR(ROUND(K78/350,0),"-")) -> 57 | M78: =IF(A78="","",IFERROR(AVERAGEIF('2026BooksRead'!AK:AK,A78,'2026BooksRead'!AI:AI),"-")) -> 8.1111111
A79: Jonathan Haidt | B79: =IF(A79="","",COUNTIF(TotalRankings!AK:AK,A79)) -> 1 | C79: =IF(A79="","",IFERROR(ROUND((SUMIF('2025BooksRead'!$AK:$AK,A79,'2025BooksRead'!$AL:$AL)+SUMIF('2026BooksRead'!$AK:$AK,A79,'2026BooksRead'!$AL:$AL))/(COUNTIF('2025BooksRead'!$AK:$AK,A79)+COUNTIF('2026BooksRead'!$AK:$AK,A79)),0),"-")) -> 115000 | D79: =IF(A79="","",IFERROR(ROUND(C79/350,0),"-")) -> 329 | E79: =IF(A79="","",IFERROR(ROUND(AVERAGEIF(TotalRankings!$AK$2:$AK$498,A79,TotalRankings!$AI$2:$AI$498),2),"-")) -> 8.08 | F79: =IF(A79="","",COUNTIF('2025BooksRead'!AK:AK,A79)) -> 1 | G79: =IF(A79="","",IFERROR(AVERAGEIF('2025BooksRead'!$AK:$AK,A79,'2025BooksRead'!$AL:$AL),"-")) -> 115000 | H79: =IF(A79="","",IFERROR(ROUND(G79/350,0),"-")) -> 329 | I79: =IF(A79="","",IFERROR(AVERAGEIF('2025BooksRead'!AK:AK,A79,'2025BooksRead'!AI:AI),"-")) -> 8.0833333 | J79: =IF(A79="","",COUNTIF('2026BooksRead'!AK:AK,A79)) -> 0 | K79: =IF(A79="","",IFERROR(AVERAGEIF('2026BooksRead'!$AK:$AK,A79,'2026BooksRead'!$AL:$AL),"-")) -> - | L79: =IF(A79="","",IFERROR(ROUND(K79/350,0),"-")) -> - | M79: =IF(A79="","",IFERROR(AVERAGEIF('2026BooksRead'!AK:AK,A79,'2026BooksRead'!AI:AI),"-")) -> -
A80: Nicolo Machiavelli | B80: =IF(A80="","",COUNTIF(TotalRankings!AK:AK,A80)) -> 1 | C80: =IF(A80="","",IFERROR(ROUND((SUMIF('2025BooksRead'!$AK:$AK,A80,'2025BooksRead'!$AL:$AL)+SUMIF('2026BooksRead'!$AK:$AK,A80,'2026BooksRead'!$AL:$AL))/(COUNTIF('2025BooksRead'!$AK:$AK,A80)+COUNTIF('2026BooksRead'!$AK:$AK,A80)),0),"-")) -> 31000 | D80: =IF(A80="","",IFERROR(ROUND(C80/350,0),"-")) -> 89 | E80: =IF(A80="","",IFERROR(ROUND(AVERAGEIF(TotalRankings!$AK$2:$AK$498,A80,TotalRankings!$AI$2:$AI$498),2),"-")) -> 7.86 | F80: =IF(A80="","",COUNTIF('2025BooksRead'!AK:AK,A80)) -> 0 | G80: =IF(A80="","",IFERROR(AVERAGEIF('2025BooksRead'!$AK:$AK,A80,'2025BooksRead'!$AL:$AL),"-")) -> - | H80: =IF(A80="","",IFERROR(ROUND(G80/350,0),"-")) -> - | I80: =IF(A80="","",IFERROR(AVERAGEIF('2025BooksRead'!AK:AK,A80,'2025BooksRead'!AI:AI),"-")) -> - | J80: =IF(A80="","",COUNTIF('2026BooksRead'!AK:AK,A80)) -> 1 | K80: =IF(A80="","",IFERROR(AVERAGEIF('2026BooksRead'!$AK:$AK,A80,'2026BooksRead'!$AL:$AL),"-")) -> 31000 | L80: =IF(A80="","",IFERROR(ROUND(K80/350,0),"-")) -> 89 | M80: =IF(A80="","",IFERROR(AVERAGEIF('2026BooksRead'!AK:AK,A80,'2026BooksRead'!AI:AI),"-")) -> 7.8555556
A81: Augustine | B81: =IF(A81="","",COUNTIF(TotalRankings!AK:AK,A81)) -> 1 | C81: =IF(A81="","",IFERROR(ROUND((SUMIF('2025BooksRead'!$AK:$AK,A81,'2025BooksRead'!$AL:$AL)+SUMIF('2026BooksRead'!$AK:$AK,A81,'2026BooksRead'!$AL:$AL))/(COUNTIF('2025BooksRead'!$AK:$AK,A81)+COUNTIF('2026BooksRead'!$AK:$AK,A81)),0),"-")) -> 100000 | D81: =IF(A81="","",IFERROR(ROUND(C81/350,0),"-")) -> 286 | E81: =IF(A81="","",IFERROR(ROUND(AVERAGEIF(TotalRankings!$AK$2:$AK$498,A81,TotalRankings!$AI$2:$AI$498),2),"-")) -> 7.57 | F81: =IF(A81="","",COUNTIF('2025BooksRead'!AK:AK,A81)) -> 1 | G81: =IF(A81="","",IFERROR(AVERAGEIF('2025BooksRead'!$AK:$AK,A81,'2025BooksRead'!$AL:$AL),"-")) -> 100000 | H81: =IF(A81="","",IFERROR(ROUND(G81/350,0),"-")) -> 286 | I81: =IF(A81="","",IFERROR(AVERAGEIF('2025BooksRead'!AK:AK,A81,'2025BooksRead'!AI:AI),"-")) -> 7.5722222 | J81: =IF(A81="","",COUNTIF('2026BooksRead'!AK:AK,A81)) -> 0 | K81: =IF(A81="","",IFERROR(AVERAGEIF('2026BooksRead'!$AK:$AK,A81,'2026BooksRead'!$AL:$AL),"-")) -> - | L81: =IF(A81="","",IFERROR(ROUND(K81/350,0),"-")) -> - | M81: =IF(A81="","",IFERROR(AVERAGEIF('2026BooksRead'!AK:AK,A81,'2026BooksRead'!AI:AI),"-")) -> -
A82: Ben Mezrich | B82: =IF(A82="","",COUNTIF(TotalRankings!AK:AK,A82)) -> 1 | C82: =IF(A82="","",IFERROR(ROUND((SUMIF('2025BooksRead'!$AK:$AK,A82,'2025BooksRead'!$AL:$AL)+SUMIF('2026BooksRead'!$AK:$AK,A82,'2026BooksRead'!$AL:$AL))/(COUNTIF('2025BooksRead'!$AK:$AK,A82)+COUNTIF('2026BooksRead'!$AK:$AK,A82)),0),"-")) -> 76500 | D82: =IF(A82="","",IFERROR(ROUND(C82/350,0),"-")) -> 219 | E82: =IF(A82="","",IFERROR(ROUND(AVERAGEIF(TotalRankings!$AK$2:$AK$498,A82,TotalRankings!$AI$2:$AI$498),2),"-")) -> 6.39 | F82: =IF(A82="","",COUNTIF('2025BooksRead'!AK:AK,A82)) -> 1 | G82: =IF(A82="","",IFERROR(AVERAGEIF('2025BooksRead'!$AK:$AK,A82,'2025BooksRead'!$AL:$AL),"-")) -> 76500 | H82: =IF(A82="","",IFERROR(ROUND(G82/350,0),"-")) -> 219 | I82: =IF(A82="","",IFERROR(AVERAGEIF('2025BooksRead'!AK:AK,A82,'2025BooksRead'!AI:AI),"-")) -> 6.3888889 | J82: =IF(A82="","",COUNTIF('2026BooksRead'!AK:AK,A82)) -> 0 | K82: =IF(A82="","",IFERROR(AVERAGEIF('2026BooksRead'!$AK:$AK,A82,'2026BooksRead'!$AL:$AL),"-")) -> - | L82: =IF(A82="","",IFERROR(ROUND(K82/350,0),"-")) -> - | M82: =IF(A82="","",IFERROR(AVERAGEIF('2026BooksRead'!AK:AK,A82,'2026BooksRead'!AI:AI),"-")) -> -
A83: Friedrich Nietzsche | B83: =IF(A83="","",COUNTIF(TotalRankings!AK:AK,A83)) -> 1 | C83: =IF(A83="","",IFERROR(ROUND((SUMIF('2025BooksRead'!$AK:$AK,A83,'2025BooksRead'!$AL:$AL)+SUMIF('2026BooksRead'!$AK:$AK,A83,'2026BooksRead'!$AL:$AL))/(COUNTIF('2025BooksRead'!$AK:$AK,A83)+COUNTIF('2026BooksRead'!$AK:$AK,A83)),0),"-")) -> 26000 | D83: =IF(A83="","",IFERROR(ROUND(C83/350,0),"-")) -> 74 | E83: =IF(A83="","",IFERROR(ROUND(AVERAGEIF(TotalRankings!$AK$2:$AK$498,A83,TotalRankings!$AI$2:$AI$498),2),"-")) -> 6.02 | F83: =IF(A83="","",COUNTIF('2025BooksRead'!AK:AK,A83)) -> 0 | G83: =IF(A83="","",IFERROR(AVERAGEIF('2025BooksRead'!$AK:$AK,A83,'2025BooksRead'!$AL:$AL),"-")) -> - | H83: =IF(A83="","",IFERROR(ROUND(G83/350,0),"-")) -> - | I83: =IF(A83="","",IFERROR(AVERAGEIF('2025BooksRead'!AK:AK,A83,'2025BooksRead'!AI:AI),"-")) -> - | J83: =IF(A83="","",COUNTIF('2026BooksRead'!AK:AK,A83)) -> 1 | K83: =IF(A83="","",IFERROR(AVERAGEIF('2026BooksRead'!$AK:$AK,A83,'2026BooksRead'!$AL:$AL),"-")) -> 26000 | L83: =IF(A83="","",IFERROR(ROUND(K83/350,0),"-")) -> 74 | M83: =IF(A83="","",IFERROR(AVERAGEIF('2026BooksRead'!AK:AK,A83,'2026BooksRead'!AI:AI),"-")) -> 6.0166667
B84: =IF(A84="","",COUNTIF(TotalRankings!F:F,A84)) | C84: =IF(A84="","",IFERROR(ROUND((SUMIF('2025BooksRead'!$AK:$AK,A84,'2025BooksRead'!$AL:$AL)+SUMIF('2026BooksRead'!$AK:$AK,A84,'2026BooksRead'!$AL:$AL))/(COUNTIF('2025BooksRead'!$AK:$AK,A84)+COUNTIF('2026BooksRead'!$AK:$AK,A84)),0),"-")) | D84: =IF(A84="","",IFERROR(ROUND(C84/350,0),"-")) | E84: =IF(A84="","",IFERROR(ROUND(AVERAGEIF(TotalRankings!$F$2:$F$498,A84,TotalRankings!$C$2:$C$498),2),"-")) | F84: =IF(A84="","",COUNTIF('2025BooksRead'!F:F,A84)) | G84: =IF(A84="","",IFERROR(AVERAGEIF('2025BooksRead'!$AK:$AK,A84,'2025BooksRead'!$AL:$AL),"-")) | H84: =IF(A84="","",IFERROR(ROUND(G84/350,0),"-")) | I84: =IF(A84="","",IFERROR(AVERAGEIF('2025BooksRead'!F:F,A84,'2025BooksRead'!C:C),"-")) | J84: =IF(A84="","",COUNTIF('2026BooksRead'!F:F,A84)) | K84: =IF(A84="","",IFERROR(AVERAGEIF('2026BooksRead'!$AK:$AK,A84,'2026BooksRead'!$AL:$AL),"-")) | L84: =IF(A84="","",IFERROR(ROUND(K84/350,0),"-")) | M84: =IF(A84="","",IFERROR(AVERAGEIF('2026BooksRead'!F:F,A84,'2026BooksRead'!C:C),"-"))
B85: =IF(A85="","",COUNTIF(TotalRankings!F:F,A85)) | C85: =IF(A85="","",IFERROR(ROUND((SUMIF('2025BooksRead'!$AK:$AK,A85,'2025BooksRead'!$AL:$AL)+SUMIF('2026BooksRead'!$AK:$AK,A85,'2026BooksRead'!$AL:$AL))/(COUNTIF('2025BooksRead'!$AK:$AK,A85)+COUNTIF('2026BooksRead'!$AK:$AK,A85)),0),"-")) | D85: =IF(A85="","",IFERROR(ROUND(C85/350,0),"-")) | E85: =IF(A85="","",IFERROR(ROUND(AVERAGEIF(TotalRankings!$F$2:$F$498,A85,TotalRankings!$C$2:$C$498),2),"-")) | F85: =IF(A85="","",COUNTIF('2025BooksRead'!F:F,A85)) | G85: =IF(A85="","",IFERROR(AVERAGEIF('2025BooksRead'!$AK:$AK,A85,'2025BooksRead'!$AL:$AL),"-")) | H85: =IF(A85="","",IFERROR(ROUND(G85/350,0),"-")) | I85: =IF(A85="","",IFERROR(AVERAGEIF('2025BooksRead'!F:F,A85,'2025BooksRead'!C:C),"-")) | J85: =IF(A85="","",COUNTIF('2026BooksRead'!F:F,A85)) | K85: =IF(A85="","",IFERROR(AVERAGEIF('2026BooksRead'!$AK:$AK,A85,'2026BooksRead'!$AL:$AL),"-")) | L85: =IF(A85="","",IFERROR(ROUND(K85/350,0),"-")) | M85: =IF(A85="","",IFERROR(AVERAGEIF('2026BooksRead'!F:F,A85,'2026BooksRead'!C:C),"-"))
B86: =IF(A86="","",COUNTIF(TotalRankings!F:F,A86)) | C86: =IF(A86="","",IFERROR(ROUND((SUMIF('2025BooksRead'!$AK:$AK,A86,'2025BooksRead'!$AL:$AL)+SUMIF('2026BooksRead'!$AK:$AK,A86,'2026BooksRead'!$AL:$AL))/(COUNTIF('2025BooksRead'!$AK:$AK,A86)+COUNTIF('2026BooksRead'!$AK:$AK,A86)),0),"-")) | D86: =IF(A86="","",IFERROR(ROUND(C86/350,0),"-")) | E86: =IF(A86="","",IFERROR(ROUND(AVERAGEIF(TotalRankings!$F$2:$F$498,A86,TotalRankings!$C$2:$C$498),2),"-")) | F86: =IF(A86="","",COUNTIF('2025BooksRead'!F:F,A86)) | G86: =IF(A86="","",IFERROR(AVERAGEIF('2025BooksRead'!$AK:$AK,A86,'2025BooksRead'!$AL:$AL),"-")) | H86: =IF(A86="","",IFERROR(ROUND(G86/350,0),"-")) | I86: =IF(A86="","",IFERROR(AVERAGEIF('2025BooksRead'!F:F,A86,'2025BooksRead'!C:C),"-")) | J86: =IF(A86="","",COUNTIF('2026BooksRead'!F:F,A86)) | K86: =IF(A87="","",IFERROR(AVERAGEIF('2026BooksRead'!$AK:$AK,A87,'2026BooksRead'!$AL:$AL),"-")) | L86: =IF(A86="","",IFERROR(ROUND(#REF!/350,0),"-")) | M86: =IF(A86="","",IFERROR(AVERAGEIF('2026BooksRead'!F:F,A86,'2026BooksRead'!C:C),"-"))
B87: =IF($A87="","",COUNTIF(TotalRankings!$AK$2:$AK$498,$A87)) | C87: =IF(A87="","",IFERROR(ROUND((SUMIF('2025BooksRead'!$AK:$AK,A87,'2025BooksRead'!$AL:$AL)+SUMIF('2026BooksRead'!$AK:$AK,A87,'2026BooksRead'!$AL:$AL))/(COUNTIF('2025BooksRead'!$AK:$AK,A87)+COUNTIF('2026BooksRead'!$AK:$AK,A87)),0),"-")) | E87: =IF($A87="","",IFERROR(AVERAGEIF(TotalRankings!$AK$2:$AK$498,$A87,TotalRankings!$AI$2:$AI$498),"-")) | F87: =IF($A87="","",COUNTIF('2025BooksRead'!$AK$2:$AK$100,$A87)) | G87: =IF(A87="","",IFERROR(AVERAGEIF('2025BooksRead'!$AK:$AK,A87,'2025BooksRead'!$AL:$AL),"-")) | I87: =IF($A87="","",IFERROR(AVERAGEIF('2025BooksRead'!$AK$2:$AK$100,$A87,'2025BooksRead'!$AI$2:$AI$100),"-")) | J87: =IF($A87="","",COUNTIF('2026BooksRead'!$AK$2:$AK$100,$A87)) | M87: =IF($A87="","",IFERROR(AVERAGEIF('2026BooksRead'!$AK$2:$AK$100,$A87,'2026BooksRead'!$AI$2:$AI$100),"-"))
B88: =IF($A88="","",COUNTIF(TotalRankings!$AK$2:$AK$498,$A88)) | C88: =IF(A88="","",IFERROR(ROUND((SUMIF('2025BooksRead'!$AK:$AK,A88,'2025BooksRead'!$AL:$AL)+SUMIF('2026BooksRead'!$AK:$AK,A88,'2026BooksRead'!$AL:$AL))/(COUNTIF('2025BooksRead'!$AK:$AK,A88)+COUNTIF('2026BooksRead'!$AK:$AK,A88)),0),"-")) | E88: =IF($A88="","",IFERROR(AVERAGEIF(TotalRankings!$AK$2:$AK$498,$A88,TotalRankings!$AI$2:$AI$498),"-")) | F88: =IF($A88="","",COUNTIF('2025BooksRead'!$AK$2:$AK$100,$A88)) | G88: =IF(A88="","",IFERROR(AVERAGEIF('2025BooksRead'!$AK:$AK,A88,'2025BooksRead'!$AL:$AL),"-")) | I88: =IF($A88="","",IFERROR(AVERAGEIF('2025BooksRead'!$AK$2:$AK$100,$A88,'2025BooksRead'!$AI$2:$AI$100),"-")) | J88: =IF($A88="","",COUNTIF('2026BooksRead'!$AK$2:$AK$100,$A88)) | K88: =IF(A88="","",IFERROR(AVERAGEIF('2026BooksRead'!$AK:$AK,A88,'2026BooksRead'!$AL:$AL),"-")) | M88: =IF($A88="","",IFERROR(AVERAGEIF('2026BooksRead'!$AK$2:$AK$100,$A88,'2026BooksRead'!$AI$2:$AI$100),"-"))
B89: =IF($A89="","",COUNTIF(TotalRankings!$AK$2:$AK$498,$A89)) | C89: =IF(A89="","",IFERROR(ROUND((SUMIF('2025BooksRead'!$AK:$AK,A89,'2025BooksRead'!$AL:$AL)+SUMIF('2026BooksRead'!$AK:$AK,A89,'2026BooksRead'!$AL:$AL))/(COUNTIF('2025BooksRead'!$AK:$AK,A89)+COUNTIF('2026BooksRead'!$AK:$AK,A89)),0),"-")) | E89: =IF($A89="","",IFERROR(AVERAGEIF(TotalRankings!$AK$2:$AK$498,$A89,TotalRankings!$AI$2:$AI$498),"-")) | F89: =IF($A89="","",COUNTIF('2025BooksRead'!$AK$2:$AK$100,$A89)) | G89: =IF(A89="","",IFERROR(AVERAGEIF('2025BooksRead'!$AK:$AK,A89,'2025BooksRead'!$AL:$AL),"-")) | I89: =IF($A89="","",IFERROR(AVERAGEIF('2025BooksRead'!$AK$2:$AK$100,$A89,'2025BooksRead'!$AI$2:$AI$100),"-")) | J89: =IF($A89="","",COUNTIF('2026BooksRead'!$AK$2:$AK$100,$A89)) | K89: =IF(A89="","",IFERROR(AVERAGEIF('2026BooksRead'!$AK:$AK,A89,'2026BooksRead'!$AL:$AL),"-")) | M89: =IF($A89="","",IFERROR(AVERAGEIF('2026BooksRead'!$AK$2:$AK$100,$A89,'2026BooksRead'!$AI$2:$AI$100),"-"))
B90: =IF($A90="","",COUNTIF(TotalRankings!$AK$2:$AK$498,$A90)) | C90: =IF(A90="","",IFERROR(ROUND((SUMIF('2025BooksRead'!$AK:$AK,A90,'2025BooksRead'!$AL:$AL)+SUMIF('2026BooksRead'!$AK:$AK,A90,'2026BooksRead'!$AL:$AL))/(COUNTIF('2025BooksRead'!$AK:$AK,A90)+COUNTIF('2026BooksRead'!$AK:$AK,A90)),0),"-")) | E90: =IF($A90="","",IFERROR(AVERAGEIF(TotalRankings!$AK$2:$AK$498,$A90,TotalRankings!$AI$2:$AI$498),"-")) | F90: =IF($A90="","",COUNTIF('2025BooksRead'!$AK$2:$AK$100,$A90)) | G90: =IF(A90="","",IFERROR(AVERAGEIF('2025BooksRead'!$AK:$AK,A90,'2025BooksRead'!$AL:$AL),"-")) | I90: =IF($A90="","",IFERROR(AVERAGEIF('2025BooksRead'!$AK$2:$AK$100,$A90,'2025BooksRead'!$AI$2:$AI$100),"-")) | J90: =IF($A90="","",COUNTIF('2026BooksRead'!$AK$2:$AK$100,$A90)) | K90: =IF(A90="","",IFERROR(AVERAGEIF('2026BooksRead'!$AK:$AK,A90,'2026BooksRead'!$AL:$AL),"-")) | M90: =IF($A90="","",IFERROR(AVERAGEIF('2026BooksRead'!$AK$2:$AK$100,$A90,'2026BooksRead'!$AI$2:$AI$100),"-"))
B91: =IF($A91="","",COUNTIF(TotalRankings!$AK$2:$AK$498,$A91)) | E91: =IF($A91="","",IFERROR(AVERAGEIF(TotalRankings!$AK$2:$AK$498,$A91,TotalRankings!$AI$2:$AI$498),"-")) | F91: =IF($A91="","",COUNTIF('2025BooksRead'!$AK$2:$AK$100,$A91)) | I91: =IF($A91="","",IFERROR(AVERAGEIF('2025BooksRead'!$AK$2:$AK$100,$A91,'2025BooksRead'!$AI$2:$AI$100),"-")) | J91: =IF($A91="","",COUNTIF('2026BooksRead'!$AK$2:$AK$100,$A91)) | M91: =IF($A91="","",IFERROR(AVERAGEIF('2026BooksRead'!$AK$2:$AK$100,$A91,'2026BooksRead'!$AI$2:$AI$100),"-"))
B92: =IF($A92="","",COUNTIF(TotalRankings!$AK$2:$AK$498,$A92)) | E92: =IF($A92="","",IFERROR(AVERAGEIF(TotalRankings!$AK$2:$AK$498,$A92,TotalRankings!$AI$2:$AI$498),"-")) | F92: =IF($A92="","",COUNTIF('2025BooksRead'!$AK$2:$AK$100,$A92)) | I92: =IF($A92="","",IFERROR(AVERAGEIF('2025BooksRead'!$AK$2:$AK$100,$A92,'2025BooksRead'!$AI$2:$AI$100),"-")) | J92: =IF($A92="","",COUNTIF('2026BooksRead'!$AK$2:$AK$100,$A92)) | M92: =IF($A92="","",IFERROR(AVERAGEIF('2026BooksRead'!$AK$2:$AK$100,$A92,'2026BooksRead'!$AI$2:$AI$100),"-"))
B93: =IF($A93="","",COUNTIF(TotalRankings!$AK$2:$AK$498,$A93)) | E93: =IF($A93="","",IFERROR(AVERAGEIF(TotalRankings!$AK$2:$AK$498,$A93,TotalRankings!$AI$2:$AI$498),"-")) | F93: =IF($A93="","",COUNTIF('2025BooksRead'!$AK$2:$AK$100,$A93)) | I93: =IF($A93="","",IFERROR(AVERAGEIF('2025BooksRead'!$AK$2:$AK$100,$A93,'2025BooksRead'!$AI$2:$AI$100),"-")) | J93: =IF($A93="","",COUNTIF('2026BooksRead'!$AK$2:$AK$100,$A93)) | M93: =IF($A93="","",IFERROR(AVERAGEIF('2026BooksRead'!$AK$2:$AK$100,$A93,'2026BooksRead'!$AI$2:$AI$100),"-"))
B94: =IF($A94="","",COUNTIF(TotalRankings!$AK$2:$AK$498,$A94)) | E94: =IF($A94="","",IFERROR(AVERAGEIF(TotalRankings!$AK$2:$AK$498,$A94,TotalRankings!$AI$2:$AI$498),"-")) | F94: =IF($A94="","",COUNTIF('2025BooksRead'!$AK$2:$AK$100,$A94)) | I94: =IF($A94="","",IFERROR(AVERAGEIF('2025BooksRead'!$AK$2:$AK$100,$A94,'2025BooksRead'!$AI$2:$AI$100),"-")) | J94: =IF($A94="","",COUNTIF('2026BooksRead'!$AK$2:$AK$100,$A94)) | M94: =IF($A94="","",IFERROR(AVERAGEIF('2026BooksRead'!$AK$2:$AK$100,$A94,'2026BooksRead'!$AI$2:$AI$100),"-"))
B95: =IF($A95="","",COUNTIF(TotalRankings!$AK$2:$AK$498,$A95)) | E95: =IF($A95="","",IFERROR(AVERAGEIF(TotalRankings!$AK$2:$AK$498,$A95,TotalRankings!$AI$2:$AI$498),"-")) | F95: =IF($A95="","",COUNTIF('2025BooksRead'!$AK$2:$AK$100,$A95)) | I95: =IF($A95="","",IFERROR(AVERAGEIF('2025BooksRead'!$AK$2:$AK$100,$A95,'2025BooksRead'!$AI$2:$AI$100),"-")) | J95: =IF($A95="","",COUNTIF('2026BooksRead'!$AK$2:$AK$100,$A95)) | M95: =IF($A95="","",IFERROR(AVERAGEIF('2026BooksRead'!$AK$2:$AK$100,$A95,'2026BooksRead'!$AI$2:$AI$100),"-"))
B96: =IF($A96="","",COUNTIF(TotalRankings!$AK$2:$AK$498,$A96)) | E96: =IF($A96="","",IFERROR(AVERAGEIF(TotalRankings!$AK$2:$AK$498,$A96,TotalRankings!$AI$2:$AI$498),"-")) | F96: =IF($A96="","",COUNTIF('2025BooksRead'!$AK$2:$AK$100,$A96)) | I96: =IF($A96="","",IFERROR(AVERAGEIF('2025BooksRead'!$AK$2:$AK$100,$A96,'2025BooksRead'!$AI$2:$AI$100),"-")) | J96: =IF($A96="","",COUNTIF('2026BooksRead'!$AK$2:$AK$100,$A96)) | M96: =IF($A96="","",IFERROR(AVERAGEIF('2026BooksRead'!$AK$2:$AK$100,$A96,'2026BooksRead'!$AI$2:$AI$100),"-"))
B97: =IF($A97="","",COUNTIF(TotalRankings!$AK$2:$AK$498,$A97)) | E97: =IF($A97="","",IFERROR(AVERAGEIF(TotalRankings!$AK$2:$AK$498,$A97,TotalRankings!$AI$2:$AI$498),"-")) | F97: =IF($A97="","",COUNTIF('2025BooksRead'!$AK$2:$AK$100,$A97)) | I97: =IF($A97="","",IFERROR(AVERAGEIF('2025BooksRead'!$AK$2:$AK$100,$A97,'2025BooksRead'!$AI$2:$AI$100),"-")) | J97: =IF($A97="","",COUNTIF('2026BooksRead'!$AK$2:$AK$100,$A97)) | M97: =IF($A97="","",IFERROR(AVERAGEIF('2026BooksRead'!$AK$2:$AK$100,$A97,'2026BooksRead'!$AI$2:$AI$100),"-"))
A100: 🔧 HOW TO ADD A NEW YEAR (e.g. 2027)
A101: 1. Create a new sheet named '2027BooksRead' following the same column structure (Book=D, Genre=E, Author=F)
A102: 2. In SUMMARY: add a new row for 2027 with formula =COUNTA('2027BooksRead'!D2:D10000)+COUNTA('2027BooksRead'!AJ2:AJ10000)
A103: 3. In BOOKS BY YEAR: insert a row and add formula =COUNTA('2027BooksRead'!D2:D10000)+COUNTA('2027BooksRead'!AJ2:AJ10000)
A104: 4. In BOOKS BY GENRE: add columns for 2027 with =COUNTIF and =AVERAGEIF referencing '2027BooksRead'
A105: 5. In BOOKS BY AUTHOR: add columns for 2027 with =COUNTIF and =AVERAGEIF referencing '2027BooksRead'
A106: 6. Add any new authors or genres as new rows in those tables
N118: ⚙ Currently Reading Options (auto)
N119: {=IFERROR(_xlfn._xlws.FILTER(TotalRankings!D2:D401,TotalRankings!D2:D401<>""),"")} -> Toll the Hounds
N120: The Crippled God
N121: Speaker For The Dead
N122: Deadhouse Gates
N123: The Fall of Hyperion
N124: The Neverending Story
N125: Memories of Ice
N126: Hyperion
N127: A Memory of Light
N128: The Bonehunters
N129: The Gathering Storm
N130: The Heroes
N131: Dust of Dreams
... N243: The Last Shadow

Sheet ReadNext
A1: MY TO-READ QUEUE | P1: Master Queue (edit here) | AL1: notDoneRecRow (helper)
A2: Series: | N2: notDoneRow (helper) | O2: seriesList (helper) | P2: Red Seas Under Red Skies | AL2: {=IF(INDEX(Recommendations!$D:$D,ROW())="","",IF(INDEX(Recommendations!$AJ:$AJ,ROW())=TRUE,"",ROW()))} -> 2
A3: # | B3: Book (pick from dropdown) | C3: Pred. Score | D3: Rank | E3: Genre | F3: Series | G3: Words | H3: Done? | I3: Auto-Done | N3: {=IF(INDEX($P:$P,ROW()-1)="","",IF(OR(IFERROR(_xlfn.XLOOKUP(INDEX($P:$P,ROW()-1),Recommendations!$D:$D,Recommendations!$AJ:$AJ),FALSE)=TRUE,INDEX($P:$P,ROW()-1)=BookTracker!$B$9),"",ROW()-1))} | O3: {=IFERROR(_xlfn._xlws.SORT(_xlfn.UNIQUE(_xlfn._xlws.FILTER(Recommendations!$G$2:$G$1086,(Recommendations!$G$2:$G$1086<>"")*(Recommendations!$G$2:$G$1086<>"Standalone")*(Recommendations!$AJ$2:$AJ$1086<>TRUE)))),"")} -> A Song of Ice and Fire | P3: Endymion | AL3: {=IF(INDEX(Recommendations!$D:$D,ROW())="","",IF(INDEX(Recommendations!$AJ:$AJ,ROW())=TRUE,"",ROW()))} -> 3
A4: Reading 1 | B4: {=IF(TRIM($B$2)<>"",IFERROR(INDEX(_xlfn._xlws.FILTER(Recommendations!$D$2:$D$1086,(Recommendations!$G$2:$G$1086=TRIM($B$2))*(Recommendations!$AJ$2:$AJ$1086<>TRUE)*(Recommendations!$D$2:$D$1086<>BookTracker!$B$9)),ROW()-3),""),IFERROR(INDEX($P:$P,SMALL($N$3:$N$102,ROW()-3)),""))} -> Endymion | C4: =IF($B4="","",IFERROR(_xlfn.XLOOKUP($B4,Recommendations!$D:$D,Recommendations!$C:$C),"")) -> 7.7649269 | D4: =IF($B4="","",IFERROR(_xlfn.XLOOKUP($B4,Recommendations!$D:$D,Recommendations!$A:$A),"")) -> 63 | E4: =IF($B4="","",IFERROR(_xlfn.XLOOKUP($B4,Recommendations!$D:$D,Recommendations!$E:$E),"")) -> Science Fiction (Hard) | F4: =IF($B4="","",IFERROR(_xlfn.XLOOKUP($B4,Recommendations!$D:$D,Recommendations!$G:$G),"")) -> Hyperion Cantos | G4: =IF($B4="","",IFERROR(_xlfn.XLOOKUP($B4,Recommendations!$D:$D,Recommendations!$H:$H),"")) -> 280000 | H4: =IF($B4="","",IFERROR(_xlfn.XLOOKUP($B4,Recommendations!$D:$D,Recommendations!$AJ:$AJ),FALSE)) -> FALSE | I4: =IF($B4="",FALSE,OR($H4=TRUE,$B4=BookTracker!$B$9)) -> FALSE | N4: {=IF(INDEX($P:$P,ROW()-1)="","",IF(OR(IFERROR(_xlfn.XLOOKUP(INDEX($P:$P,ROW()-1),Recommendations!$D:$D,Recommendations!$AJ:$AJ),FALSE)=TRUE,INDEX($P:$P,ROW()-1)=BookTracker!$B$9),"",ROW()-1))} -> 3 | O4: Aubrey-Maturin | P4: The Republic of Thieves | AL4: {=IF(INDEX(Recommendations!$D:$D,ROW())="","",IF(INDEX(Recommendations!$AJ:$AJ,ROW())=TRUE,"",ROW()))} -> 4
A5: =1 -> 1 | B5: {=IF(TRIM($B$2)<>"",IFERROR(INDEX(_xlfn._xlws.FILTER(Recommendations!$D$2:$D$1086,(Recommendations!$G$2:$G$1086=TRIM($B$2))*(Recommendations!$AJ$2:$AJ$1086<>TRUE)*(Recommendations!$D$2:$D$1086<>BookTracker!$B$9)),ROW()-3),""),IFERROR(INDEX($P:$P,SMALL($N$3:$N$102,ROW()-3)),""))} -> The Republic of Thieves | C5: =IF($B5="","",IFERROR(_xlfn.XLOOKUP($B5,Recommendations!$D:$D,Recommendations!$C:$C),"")) -> 7.5524151 | D5: =IF($B5="","",IFERROR(_xlfn.XLOOKUP($B5,Recommendations!$D:$D,Recommendations!$A:$A),"")) -> 74 | E5: =IF($B5="","",IFERROR(_xlfn.XLOOKUP($B5,Recommendations!$D:$D,Recommendations!$E:$E),"")) -> Epic Fantasy | F5: =IF($B5="","",IFERROR(_xlfn.XLOOKUP($B5,Recommendations!$D:$D,Recommendations!$G:$G),"")) -> Gentleman Bastards | G5: =IF($B5="","",IFERROR(_xlfn.XLOOKUP($B5,Recommendations!$D:$D,Recommendations!$H:$H),"")) -> 220000 | H5: =IF($B5="","",IFERROR(_xlfn.XLOOKUP($B5,Recommendations!$D:$D,Recommendations!$AJ:$AJ),FALSE)) -> FALSE | I5: =IF($B5="",FALSE,OR($H5=TRUE,$B5=BookTracker!$B$9)) -> FALSE | N5: {=IF(INDEX($P:$P,ROW()-1)="","",IF(OR(IFERROR(_xlfn.XLOOKUP(INDEX($P:$P,ROW()-1),Recommendations!$D:$D,Recommendations!$AJ:$AJ),FALSE)=TRUE,INDEX($P:$P,ROW()-1)=BookTracker!$B$9),"",ROW()-1))} -> 4 | O5: Blacktongue | P5: The Rise of Endymion | AL5: {=IF(INDEX(Recommendations!$D:$D,ROW())="","",IF(INDEX(Recommendations!$AJ:$AJ,ROW())=TRUE,"",ROW()))} -> 5
A6: =2 -> 2 | B6: {=IF(TRIM($B$2)<>"",IFERROR(INDEX(_xlfn._xlws.FILTER(Recommendations!$D$2:$D$1086,(Recommendations!$G$2:$G$1086=TRIM($B$2))*(Recommendations!$AJ$2:$AJ$1086<>TRUE)*(Recommendations!$D$2:$D$1086<>BookTracker!$B$9)),ROW()-3),""),IFERROR(INDEX($P:$P,SMALL($N$3:$N$102,ROW()-3)),""))} -> The Rise of Endymion | C6: =IF($B6="","",IFERROR(_xlfn.XLOOKUP($B6,Recommendations!$D:$D,Recommendations!$C:$C),"")) -> 7.9320563 | D6: =IF($B6="","",IFERROR(_xlfn.XLOOKUP($B6,Recommendations!$D:$D,Recommendations!$A:$A),"")) -> 52 | E6: =IF($B6="","",IFERROR(_xlfn.XLOOKUP($B6,Recommendations!$D:$D,Recommendations!$E:$E),"")) -> Science Fiction (Hard) | F6: =IF($B6="","",IFERROR(_xlfn.XLOOKUP($B6,Recommendations!$D:$D,Recommendations!$G:$G),"")) -> Hyperion Cantos | G6: =IF($B6="","",IFERROR(_xlfn.XLOOKUP($B6,Recommendations!$D:$D,Recommendations!$H:$H),"")) -> 420000 | H6: =IF($B6="","",IFERROR(_xlfn.XLOOKUP($B6,Recommendations!$D:$D,Recommendations!$AJ:$AJ),FALSE)) -> FALSE | I6: =IF($B6="",FALSE,OR($H6=TRUE,$B6=BookTracker!$B$9)) -> FALSE | N6: {=IF(INDEX($P:$P,ROW()-1)="","",IF(OR(IFERROR(_xlfn.XLOOKUP(INDEX($P:$P,ROW()-1),Recommendations!$D:$D,Recommendations!$AJ:$AJ),FALSE)=TRUE,INDEX($P:$P,ROW()-1)=BookTracker!$B$9),"",ROW()-1))} -> 5 | O6: Broken Earth | P6: Lord of Emperors | AL6: {=IF(INDEX(Recommendations!$D:$D,ROW())="","",IF(INDEX(Recommendations!$AJ:$AJ,ROW())=TRUE,"",ROW()))} -> 6
A7: =3 -> 3 | B7: {=IF(TRIM($B$2)<>"",IFERROR(INDEX(_xlfn._xlws.FILTER(Recommendations!$D$2:$D$1086,(Recommendations!$G$2:$G$1086=TRIM($B$2))*(Recommendations!$AJ$2:$AJ$1086<>TRUE)*(Recommendations!$D$2:$D$1086<>BookTracker!$B$9)),ROW()-3),""),IFERROR(INDEX($P:$P,SMALL($N$3:$N$102,ROW()-3)),""))} -> Lord of Emperors | C7: =IF($B7="","",IFERROR(_xlfn.XLOOKUP($B7,Recommendations!$D:$D,Recommendations!$C:$C),"")) -> 8.1486847 | D7: =IF($B7="","",IFERROR(_xlfn.XLOOKUP($B7,Recommendations!$D:$D,Recommendations!$A:$A),"")) -> 44 | E7: =IF($B7="","",IFERROR(_xlfn.XLOOKUP($B7,Recommendations!$D:$D,Recommendations!$E:$E),"")) -> Literary Fantasy | F7: =IF($B7="","",IFERROR(_xlfn.XLOOKUP($B7,Recommendations!$D:$D,Recommendations!$G:$G),"")) -> The Sarantine Mosaic | G7: =IF($B7="","",IFERROR(_xlfn.XLOOKUP($B7,Recommendations!$D:$D,Recommendations!$H:$H),"")) -> 175000 | H7: =IF($B7="","",IFERROR(_xlfn.XLOOKUP($B7,Recommendations!$D:$D,Recommendations!$AJ:$AJ),FALSE)) -> FALSE | I7: =IF($B7="",FALSE,OR($H7=TRUE,$B7=BookTracker!$B$9)) -> FALSE | N7: {=IF(INDEX($P:$P,ROW()-1)="","",IF(OR(IFERROR(_xlfn.XLOOKUP(INDEX($P:$P,ROW()-1),Recommendations!$D:$D,Recommendations!$AJ:$AJ),FALSE)=TRUE,INDEX($P:$P,ROW()-1)=BookTracker!$B$9),"",ROW()-1))} -> 6 | O7: Children of Time | P7: Shadow of the Hegemon | AL7: {=IF(INDEX(Recommendations!$D:$D,ROW())="","",IF(INDEX(Recommendations!$AJ:$AJ,ROW())=TRUE,"",ROW()))} -> 7
A8: =4 -> 4 | B8: {=IF(TRIM($B$2)<>"",IFERROR(INDEX(_xlfn._xlws.FILTER(Recommendations!$D$2:$D$1086,(Recommendations!$G$2:$G$1086=TRIM($B$2))*(Recommendations!$AJ$2:$AJ$1086<>TRUE)*(Recommendations!$D$2:$D$1086<>BookTracker!$B$9)),ROW()-3),""),IFERROR(INDEX($P:$P,SMALL($N$3:$N$102,ROW()-3)),""))} -> Shadow of the Hegemon | C8: =IF($B8="","",IFERROR(_xlfn.XLOOKUP($B8,Recommendations!$D:$D,Recommendations!$C:$C),"")) -> 7.2532681 | D8: =IF($B8="","",IFERROR(_xlfn.XLOOKUP($B8,Recommendations!$D:$D,Recommendations!$A:$A),"")) -> 85 | E8: =IF($B8="","",IFERROR(_xlfn.XLOOKUP($B8,Recommendations!$D:$D,Recommendations!$E:$E),"")) -> Science Fiction (Hard) | F8: =IF($B8="","",IFERROR(_xlfn.XLOOKUP($B8,Recommendations!$D:$D,Recommendations!$G:$G),"")) -> Ender's Shadow | G8: =IF($B8="","",IFERROR(_xlfn.XLOOKUP($B8,Recommendations!$D:$D,Recommendations!$H:$H),"")) -> 95000 | H8: =IF($B8="","",IFERROR(_xlfn.XLOOKUP($B8,Recommendations!$D:$D,Recommendations!$AJ:$AJ),FALSE)) -> FALSE | I8: =IF($B8="",FALSE,OR($H8=TRUE,$B8=BookTracker!$B$9)) -> FALSE | N8: {=IF(INDEX($P:$P,ROW()-1)="","",IF(OR(IFERROR(_xlfn.XLOOKUP(INDEX($P:$P,ROW()-1),Recommendations!$D:$D,Recommendations!$AJ:$AJ),FALSE)=TRUE,INDEX($P:$P,ROW()-1)=BookTracker!$B$9),"",ROW()-1))} -> 7 | O8: Chronicle of the Unhewn Throne | P8: Shadow Puppets | AL8: {=IF(INDEX(Recommendations!$D:$D,ROW())="","",IF(INDEX(Recommendations!$AJ:$AJ,ROW())=TRUE,"",ROW()))} -> 8
A9: =5 -> 5 | B9: {=IF(TRIM($B$2)<>"",IFERROR(INDEX(_xlfn._xlws.FILTER(Recommendations!$D$2:$D$1086,(Recommendations!$G$2:$G$1086=TRIM($B$2))*(Recommendations!$AJ$2:$AJ$1086<>TRUE)*(Recommendations!$D$2:$D$1086<>BookTracker!$B$9)),ROW()-3),""),IFERROR(INDEX($P:$P,SMALL($N$3:$N$102,ROW()-3)),""))} -> Shadow Puppets | C9: =IF($B9="","",IFERROR(_xlfn.XLOOKUP($B9,Recommendations!$D:$D,Recommendations!$C:$C),"")) -> 6.6294837 | D9: =IF($B9="","",IFERROR(_xlfn.XLOOKUP($B9,Recommendations!$D:$D,Recommendations!$A:$A),"")) -> 107 | E9: =IF($B9="","",IFERROR(_xlfn.XLOOKUP($B9,Recommendations!$D:$D,Recommendations!$E:$E),"")) -> Science Fiction (Hard) | F9: =IF($B9="","",IFERROR(_xlfn.XLOOKUP($B9,Recommendations!$D:$D,Recommendations!$G:$G),"")) -> Ender's Shadow | G9: =IF($B9="","",IFERROR(_xlfn.XLOOKUP($B9,Recommendations!$D:$D,Recommendations!$H:$H),"")) -> 99000 | H9: =IF($B9="","",IFERROR(_xlfn.XLOOKUP($B9,Recommendations!$D:$D,Recommendations!$AJ:$AJ),FALSE)) -> FALSE | I9: =IF($B9="",FALSE,OR($H9=TRUE,$B9=BookTracker!$B$9)) -> FALSE | N9: {=IF(INDEX($P:$P,ROW()-1)="","",IF(OR(IFERROR(_xlfn.XLOOKUP(INDEX($P:$P,ROW()-1),Recommendations!$D:$D,Recommendations!$AJ:$AJ),FALSE)=TRUE,INDEX($P:$P,ROW()-1)=BookTracker!$B$9),"",ROW()-1))} -> 8 | O9: Codex Alera | P9: Shadow of the Giant | AL9: {=IF(INDEX(Recommendations!$D:$D,ROW())="","",IF(INDEX(Recommendations!$AJ:$AJ,ROW())=TRUE,"",ROW()))} -> 9
A10: =6 -> 6 | B10: {=IF(TRIM($B$2)<>"",IFERROR(INDEX(_xlfn._xlws.FILTER(Recommendations!$D$2:$D$1086,(Recommendations!$G$2:$G$1086=TRIM($B$2))*(Recommendations!$AJ$2:$AJ$1086<>TRUE)*(Recommendations!$D$2:$D$1086<>BookTracker!$B$9)),ROW()-3),""),IFERROR(INDEX($P:$P,SMALL($N$3:$N$102,ROW()-3)),""))} -> Shadow of the Giant | C10: =IF($B10="","",IFERROR(_xlfn.XLOOKUP($B10,Recommendations!$D:$D,Recommendations!$C:$C),"")) -> 7.2193395 | D10: =IF($B10="","",IFERROR(_xlfn.XLOOKUP($B10,Recommendations!$D:$D,Recommendations!$A:$A),"")) -> 88 | E10: =IF($B10="","",IFERROR(_xlfn.XLOOKUP($B10,Recommendations!$D:$D,Recommendations!$E:$E),"")) -> Science Fiction (Hard) | F10: =IF($B10="","",IFERROR(_xlfn.XLOOKUP($B10,Recommendations!$D:$D,Recommendations!$G:$G),"")) -> Ender's Shadow | G10: =IF($B10="","",IFERROR(_xlfn.XLOOKUP($B10,Recommendations!$D:$D,Recommendations!$H:$H),"")) -> 107000 | H10: =IF($B10="","",IFERROR(_xlfn.XLOOKUP($B10,Recommendations!$D:$D,Recommendations!$AJ:$AJ),FALSE)) -> FALSE | I10: =IF($B10="",FALSE,OR($H10=TRUE,$B10=BookTracker!$B$9)) -> FALSE | N10: {=IF(INDEX($P:$P,ROW()-1)="","",IF(OR(IFERROR(_xlfn.XLOOKUP(INDEX($P:$P,ROW()-1),Recommendations!$D:$D,Recommendations!$AJ:$AJ),FALSE)=TRUE,INDEX($P:$P,ROW()-1)=BookTracker!$B$9),"",ROW()-1))} -> 9 | O10: Conclave of Shadows | P10: The Wise Man's Fear | AL10: {=IF(INDEX(Recommendations!$D:$D,ROW())="","",IF(INDEX(Recommendations!$AJ:$AJ,ROW())=TRUE,"",ROW()))} -> 10
A11: =7 -> 7 | B11: {=IF(TRIM($B$2)<>"",IFERROR(INDEX(_xlfn._xlws.FILTER(Recommendations!$D$2:$D$1086,(Recommendations!$G$2:$G$1086=TRIM($B$2))*(Recommendations!$AJ$2:$AJ$1086<>TRUE)*(Recommendations!$D$2:$D$1086<>BookTracker!$B$9)),ROW()-3),""),IFERROR(INDEX($P:$P,SMALL($N$3:$N$102,ROW()-3)),""))} -> The Wise Man's Fear | C11: =IF($B11="","",IFERROR(_xlfn.XLOOKUP($B11,Recommendations!$D:$D,Recommendations!$C:$C),"")) -> 6.7662303 | D11: =IF($B11="","",IFERROR(_xlfn.XLOOKUP($B11,Recommendations!$D:$D,Recommendations!$A:$A),"")) -> 104 | E11: =IF($B11="","",IFERROR(_xlfn.XLOOKUP($B11,Recommendations!$D:$D,Recommendations!$E:$E),"")) -> Epic Fantasy | F11: =IF($B11="","",IFERROR(_xlfn.XLOOKUP($B11,Recommendations!$D:$D,Recommendations!$G:$G),"")) -> The Kingkiller Chronicle | G11: =IF($B11="","",IFERROR(_xlfn.XLOOKUP($B11,Recommendations!$D:$D,Recommendations!$H:$H),"")) -> 395000 | H11: =IF($B11="","",IFERROR(_xlfn.XLOOKUP($B11,Recommendations!$D:$D,Recommendations!$AJ:$AJ),FALSE)) -> FALSE | I11: =IF($B11="",FALSE,OR($H11=TRUE,$B11=BookTracker!$B$9)) -> FALSE | N11: {=IF(INDEX($P:$P,ROW()-1)="","",IF(OR(IFERROR(_xlfn.XLOOKUP(INDEX($P:$P,ROW()-1),Recommendations!$D:$D,Recommendations!$AJ:$AJ),FALSE)=TRUE,INDEX($P:$P,ROW()-1)=BookTracker!$B$9),"",ROW()-1))} -> 10 | O11: Conqueror | P11: The Obelisk Gate | AL11: {=IF(INDEX(Recommendations!$D:$D,ROW())="","",IF(INDEX(Recommendations!$AJ:$AJ,ROW())=TRUE,"",ROW()))} -> 11
A12: =8 -> 8 | B12: {=IF(TRIM($B$2)<>"",IFERROR(INDEX(_xlfn._xlws.FILTER(Recommendations!$D$2:$D$1086,(Recommendations!$G$2:$G$1086=TRIM($B$2))*(Recommendations!$AJ$2:$AJ$1086<>TRUE)*(Recommendations!$D$2:$D$1086<>BookTracker!$B$9)),ROW()-3),""),IFERROR(INDEX($P:$P,SMALL($N$3:$N$102,ROW()-3)),""))} -> The Obelisk Gate | C12: =IF($B12="","",IFERROR(_xlfn.XLOOKUP($B12,Recommendations!$D:$D,Recommendations!$C:$C),"")) -> 6.9422599 | D12: =IF($B12="","",IFERROR(_xlfn.XLOOKUP($B12,Recommendations!$D:$D,Recommendations!$A:$A),"")) -> 99 | E12: =IF($B12="","",IFERROR(_xlfn.XLOOKUP($B12,Recommendations!$D:$D,Recommendations!$E:$E),"")) -> Science Fiction (Soft) | F12: =IF($B12="","",IFERROR(_xlfn.XLOOKUP($B12,Recommendations!$D:$D,Recommendations!$G:$G),"")) -> Broken Earth | G12: =IF($B12="","",IFERROR(_xlfn.XLOOKUP($B12,Recommendations!$D:$D,Recommendations!$H:$H),"")) -> 110000 | H12: =IF($B12="","",IFERROR(_xlfn.XLOOKUP($B12,Recommendations!$D:$D,Recommendations!$AJ:$AJ),FALSE)) -> FALSE | I12: =IF($B12="",FALSE,OR($H12=TRUE,$B12=BookTracker!$B$9)) -> FALSE | N12: {=IF(INDEX($P:$P,ROW()-1)="","",IF(OR(IFERROR(_xlfn.XLOOKUP(INDEX($P:$P,ROW()-1),Recommendations!$D:$D,Recommendations!$AJ:$AJ),FALSE)=TRUE,INDEX($P:$P,ROW()-1)=BookTracker!$B$9),"",ROW()-1))} -> 11 | O12: Cradle | P12: The Stone Sky | AL12: {=IF(INDEX(Recommendations!$D:$D,ROW())="","",IF(INDEX(Recommendations!$AJ:$AJ,ROW())=TRUE,"",ROW()))} -> 12
A13: =9 -> 9 | B13: {=IF(TRIM($B$2)<>"",IFERROR(INDEX(_xlfn._xlws.FILTER(Recommendations!$D$2:$D$1086,(Recommendations!$G$2:$G$1086=TRIM($B$2))*(Recommendations!$AJ$2:$AJ$1086<>TRUE)*(Recommendations!$D$2:$D$1086<>BookTracker!$B$9)),ROW()-3),""),IFERROR(INDEX($P:$P,SMALL($N$3:$N$102,ROW()-3)),""))} -> The Stone Sky | C13: =IF($B13="","",IFERROR(_xlfn.XLOOKUP($B13,Recommendations!$D:$D,Recommendations!$C:$C),"")) -> 7.4748158 | D13: =IF($B13="","",IFERROR(_xlfn.XLOOKUP($B13,Recommendations!$D:$D,Recommendations!$A:$A),"")) -> 76 | E13: =IF($B13="","",IFERROR(_xlfn.XLOOKUP($B13,Recommendations!$D:$D,Recommendations!$E:$E),"")) -> Science Fiction (Soft) | F13: =IF($B13="","",IFERROR(_xlfn.XLOOKUP($B13,Recommendations!$D:$D,Recommendations!$G:$G),"")) -> Broken Earth | G13: =IF($B13="","",IFERROR(_xlfn.XLOOKUP($B13,Recommendations!$D:$D,Recommendations!$H:$H),"")) -> 110000 | H13: =IF($B13="","",IFERROR(_xlfn.XLOOKUP($B13,Recommendations!$D:$D,Recommendations!$AJ:$AJ),FALSE)) -> FALSE | I13: =IF($B13="",FALSE,OR($H13=TRUE,$B13=BookTracker!$B$9)) -> FALSE | N13: {=IF(INDEX($P:$P,ROW()-1)="","",IF(OR(IFERROR(_xlfn.XLOOKUP(INDEX($P:$P,ROW()-1),Recommendations!$D:$D,Recommendations!$AJ:$AJ),FALSE)=TRUE,INDEX($P:$P,ROW()-1)=BookTracker!$B$9),"",ROW()-1))} -> 12 | O13: Discworld: City Watch | AL13: {=IF(INDEX(Recommendations!$D:$D,ROW())="","",IF(INDEX(Recommendations!$AJ:$AJ,ROW())=TRUE,"",ROW()))} -> 13
A14: =10 -> 10 | B14: {=IF(TRIM($B$2)<>"",IFERROR(INDEX(_xlfn._xlws.FILTER(Recommendations!$D$2:$D$1086,(Recommendations!$G$2:$G$1086=TRIM($B$2))*(Recommendations!$AJ$2:$AJ$1086<>TRUE)*(Recommendations!$D$2:$D$1086<>BookTracker!$B$9)),ROW()-3),""),IFERROR(INDEX($P:$P,SMALL($N$3:$N$102,ROW()-3)),""))} | C14: =IF($B14="","",IFERROR(_xlfn.XLOOKUP($B14,Recommendations!$D:$D,Recommendations!$C:$C),"")) | D14: =IF($B14="","",IFERROR(_xlfn.XLOOKUP($B14,Recommendations!$D:$D,Recommendations!$A:$A),"")) | E14: =IF($B14="","",IFERROR(_xlfn.XLOOKUP($B14,Recommendations!$D:$D,Recommendations!$E:$E),"")) | F14: =IF($B14="","",IFERROR(_xlfn.XLOOKUP($B14,Recommendations!$D:$D,Recommendations!$G:$G),"")) | G14: =IF($B14="","",IFERROR(_xlfn.XLOOKUP($B14,Recommendations!$D:$D,Recommendations!$H:$H),"")) | H14: =IF($B14="","",IFERROR(_xlfn.XLOOKUP($B14,Recommendations!$D:$D,Recommendations!$AJ:$AJ),FALSE)) | I14: =IF($B14="",FALSE,OR($H14=TRUE,$B14=BookTracker!$B$9)) -> FALSE | N14: {=IF(INDEX($P:$P,ROW()-1)="","",IF(OR(IFERROR(_xlfn.XLOOKUP(INDEX($P:$P,ROW()-1),Recommendations!$D:$D,Recommendations!$AJ:$AJ),FALSE)=TRUE,INDEX($P:$P,ROW()-1)=BookTracker!$B$9),"",ROW()-1))} | O14: Discworld: Death | AL14: {=IF(INDEX(Recommendations!$D:$D,ROW())="","",IF(INDEX(Recommendations!$AJ:$AJ,ROW())=TRUE,"",ROW()))} -> 14
A15: =11 -> 11 | B15: {=IF(TRIM($B$2)<>"",IFERROR(INDEX(_xlfn._xlws.FILTER(Recommendations!$D$2:$D$1086,(Recommendations!$G$2:$G$1086=TRIM($B$2))*(Recommendations!$AJ$2:$AJ$1086<>TRUE)*(Recommendations!$D$2:$D$1086<>BookTracker!$B$9)),ROW()-3),""),IFERROR(INDEX($P:$P,SMALL($N$3:$N$102,ROW()-3)),""))} | C15: =IF($B15="","",IFERROR(_xlfn.XLOOKUP($B15,Recommendations!$D:$D,Recommendations!$C:$C),"")) | D15: =IF($B15="","",IFERROR(_xlfn.XLOOKUP($B15,Recommendations!$D:$D,Recommendations!$A:$A),"")) | E15: =IF($B15="","",IFERROR(_xlfn.XLOOKUP($B15,Recommendations!$D:$D,Recommendations!$E:$E),"")) | F15: =IF($B15="","",IFERROR(_xlfn.XLOOKUP($B15,Recommendations!$D:$D,Recommendations!$G:$G),"")) | G15: =IF($B15="","",IFERROR(_xlfn.XLOOKUP($B15,Recommendations!$D:$D,Recommendations!$H:$H),"")) | H15: =IF($B15="","",IFERROR(_xlfn.XLOOKUP($B15,Recommendations!$D:$D,Recommendations!$AJ:$AJ),FALSE)) | I15: =IF($B15="",FALSE,OR($H15=TRUE,$B15=BookTracker!$B$9)) -> FALSE | N15: {=IF(INDEX($P:$P,ROW()-1)="","",IF(OR(IFERROR(_xlfn.XLOOKUP(INDEX($P:$P,ROW()-1),Recommendations!$D:$D,Recommendations!$AJ:$AJ),FALSE)=TRUE,INDEX($P:$P,ROW()-1)=BookTracker!$B$9),"",ROW()-1))} | O15: Discworld: Moist von Lipwig | AL15: {=IF(INDEX(Recommendations!$D:$D,ROW())="","",IF(INDEX(Recommendations!$AJ:$AJ,ROW())=TRUE,"",ROW()))} -> 15
A16: =12 -> 12 | B16: {=IF(TRIM($B$2)<>"",IFERROR(INDEX(_xlfn._xlws.FILTER(Recommendations!$D$2:$D$1086,(Recommendations!$G$2:$G$1086=TRIM($B$2))*(Recommendations!$AJ$2:$AJ$1086<>TRUE)*(Recommendations!$D$2:$D$1086<>BookTracker!$B$9)),ROW()-3),""),IFERROR(INDEX($P:$P,SMALL($N$3:$N$102,ROW()-3)),""))} | C16: =IF($B16="","",IFERROR(_xlfn.XLOOKUP($B16,Recommendations!$D:$D,Recommendations!$C:$C),"")) | D16: =IF($B16="","",IFERROR(_xlfn.XLOOKUP($B16,Recommendations!$D:$D,Recommendations!$A:$A),"")) | E16: =IF($B16="","",IFERROR(_xlfn.XLOOKUP($B16,Recommendations!$D:$D,Recommendations!$E:$E),"")) | F16: =IF($B16="","",IFERROR(_xlfn.XLOOKUP($B16,Recommendations!$D:$D,Recommendations!$G:$G),"")) | G16: =IF($B16="","",IFERROR(_xlfn.XLOOKUP($B16,Recommendations!$D:$D,Recommendations!$H:$H),"")) | H16: =IF($B16="","",IFERROR(_xlfn.XLOOKUP($B16,Recommendations!$D:$D,Recommendations!$AJ:$AJ),FALSE)) | I16: =IF($B16="",FALSE,OR($H16=TRUE,$B16=BookTracker!$B$9)) -> FALSE | N16: {=IF(INDEX($P:$P,ROW()-1)="","",IF(OR(IFERROR(_xlfn.XLOOKUP(INDEX($P:$P,ROW()-1),Recommendations!$D:$D,Recommendations!$AJ:$AJ),FALSE)=TRUE,INDEX($P:$P,ROW()-1)=BookTracker!$B$9),"",ROW()-1))} | O16: Discworld: Rincewind | AL16: {=IF(INDEX(Recommendations!$D:$D,ROW())="","",IF(INDEX(Recommendations!$AJ:$AJ,ROW())=TRUE,"",ROW()))} -> 16
A17: =13 -> 13 | B17: {=IF(TRIM($B$2)<>"",IFERROR(INDEX(_xlfn._xlws.FILTER(Recommendations!$D$2:$D$1086,(Recommendations!$G$2:$G$1086=TRIM($B$2))*(Recommendations!$AJ$2:$AJ$1086<>TRUE)*(Recommendations!$D$2:$D$1086<>BookTracker!$B$9)),ROW()-3),""),IFERROR(INDEX($P:$P,SMALL($N$3:$N$102,ROW()-3)),""))} | C17: =IF($B17="","",IFERROR(_xlfn.XLOOKUP($B17,Recommendations!$D:$D,Recommendations!$C:$C),"")) | D17: =IF($B17="","",IFERROR(_xlfn.XLOOKUP($B17,Recommendations!$D:$D,Recommendations!$A:$A),"")) | E17: =IF($B17="","",IFERROR(_xlfn.XLOOKUP($B17,Recommendations!$D:$D,Recommendations!$E:$E),"")) | F17: =IF($B17="","",IFERROR(_xlfn.XLOOKUP($B17,Recommendations!$D:$D,Recommendations!$G:$G),"")) | G17: =IF($B17="","",IFERROR(_xlfn.XLOOKUP($B17,Recommendations!$D:$D,Recommendations!$H:$H),"")) | H17: =IF($B17="","",IFERROR(_xlfn.XLOOKUP($B17,Recommendations!$D:$D,Recommendations!$AJ:$AJ),FALSE)) | I17: =IF($B17="",FALSE,OR($H17=TRUE,$B17=BookTracker!$B$9)) -> FALSE | N17: {=IF(INDEX($P:$P,ROW()-1)="","",IF(OR(IFERROR(_xlfn.XLOOKUP(INDEX($P:$P,ROW()-1),Recommendations!$D:$D,Recommendations!$AJ:$AJ),FALSE)=TRUE,INDEX($P:$P,ROW()-1)=BookTracker!$B$9),"",ROW()-1))} | O17: Discworld: Standalone | AL17: {=IF(INDEX(Recommendations!$D:$D,ROW())="","",IF(INDEX(Recommendations!$AJ:$AJ,ROW())=TRUE,"",ROW()))} -> 17
A18: =14 -> 14 | B18: {=IF(TRIM($B$2)<>"",IFERROR(INDEX(_xlfn._xlws.FILTER(Recommendations!$D$2:$D$1086,(Recommendations!$G$2:$G$1086=TRIM($B$2))*(Recommendations!$AJ$2:$AJ$1086<>TRUE)*(Recommendations!$D$2:$D$1086<>BookTracker!$B$9)),ROW()-3),""),IFERROR(INDEX($P:$P,SMALL($N$3:$N$102,ROW()-3)),""))} | C18: =IF($B18="","",IFERROR(_xlfn.XLOOKUP($B18,Recommendations!$D:$D,Recommendations!$C:$C),"")) | D18: =IF($B18="","",IFERROR(_xlfn.XLOOKUP($B18,Recommendations!$D:$D,Recommendations!$A:$A),"")) | E18: =IF($B18="","",IFERROR(_xlfn.XLOOKUP($B18,Recommendations!$D:$D,Recommendations!$E:$E),"")) | F18: =IF($B18="","",IFERROR(_xlfn.XLOOKUP($B18,Recommendations!$D:$D,Recommendations!$G:$G),"")) | G18: =IF($B18="","",IFERROR(_xlfn.XLOOKUP($B18,Recommendations!$D:$D,Recommendations!$H:$H),"")) | H18: =IF($B18="","",IFERROR(_xlfn.XLOOKUP($B18,Recommendations!$D:$D,Recommendations!$AJ:$AJ),FALSE)) | I18: =IF($B18="",FALSE,OR($H18=TRUE,$B18=BookTracker!$B$9)) -> FALSE | N18: {=IF(INDEX($P:$P,ROW()-1)="","",IF(OR(IFERROR(_xlfn.XLOOKUP(INDEX($P:$P,ROW()-1),Recommendations!$D:$D,Recommendations!$AJ:$AJ),FALSE)=TRUE,INDEX($P:$P,ROW()-1)=BookTracker!$B$9),"",ROW()-1))} | O18: Discworld: Tiffany Aching | AL18: {=IF(INDEX(Recommendations!$D:$D,ROW())="","",IF(INDEX(Recommendations!$AJ:$AJ,ROW())=TRUE,"",ROW()))} -> 18
A19: =15 -> 15 | B19: {=IF(TRIM($B$2)<>"",IFERROR(INDEX(_xlfn._xlws.FILTER(Recommendations!$D$2:$D$1086,(Recommendations!$G$2:$G$1086=TRIM($B$2))*(Recommendations!$AJ$2:$AJ$1086<>TRUE)*(Recommendations!$D$2:$D$1086<>BookTracker!$B$9)),ROW()-3),""),IFERROR(INDEX($P:$P,SMALL($N$3:$N$102,ROW()-3)),""))} | C19: =IF($B19="","",IFERROR(_xlfn.XLOOKUP($B19,Recommendations!$D:$D,Recommendations!$C:$C),"")) | D19: =IF($B19="","",IFERROR(_xlfn.XLOOKUP($B19,Recommendations!$D:$D,Recommendations!$A:$A),"")) | E19: =IF($B19="","",IFERROR(_xlfn.XLOOKUP($B19,Recommendations!$D:$D,Recommendations!$E:$E),"")) | F19: =IF($B19="","",IFERROR(_xlfn.XLOOKUP($B19,Recommendations!$D:$D,Recommendations!$G:$G),"")) | G19: =IF($B19="","",IFERROR(_xlfn.XLOOKUP($B19,Recommendations!$D:$D,Recommendations!$H:$H),"")) | H19: =IF($B19="","",IFERROR(_xlfn.XLOOKUP($B19,Recommendations!$D:$D,Recommendations!$AJ:$AJ),FALSE)) | I19: =IF($B19="",FALSE,OR($H19=TRUE,$B19=BookTracker!$B$9)) -> FALSE | N19: {=IF(INDEX($P:$P,ROW()-1)="","",IF(OR(IFERROR(_xlfn.XLOOKUP(INDEX($P:$P,ROW()-1),Recommendations!$D:$D,Recommendations!$AJ:$AJ),FALSE)=TRUE,INDEX($P:$P,ROW()-1)=BookTracker!$B$9),"",ROW()-1))} | O19: Discworld: Witches | AL19: {=IF(INDEX(Recommendations!$D:$D,ROW())="","",IF(INDEX(Recommendations!$AJ:$AJ,ROW())=TRUE,"",ROW()))} -> 19
A20: =16 -> 16 | B20: {=IF(TRIM($B$2)<>"",IFERROR(INDEX(_xlfn._xlws.FILTER(Recommendations!$D$2:$D$1086,(Recommendations!$G$2:$G$1086=TRIM($B$2))*(Recommendations!$AJ$2:$AJ$1086<>TRUE)*(Recommendations!$D$2:$D$1086<>BookTracker!$B$9)),ROW()-3),""),IFERROR(INDEX($P:$P,SMALL($N$3:$N$102,ROW()-3)),""))} | C20: =IF($B20="","",IFERROR(_xlfn.XLOOKUP($B20,Recommendations!$D:$D,Recommendations!$C:$C),"")) | D20: =IF($B20="","",IFERROR(_xlfn.XLOOKUP($B20,Recommendations!$D:$D,Recommendations!$A:$A),"")) | E20: =IF($B20="","",IFERROR(_xlfn.XLOOKUP($B20,Recommendations!$D:$D,Recommendations!$E:$E),"")) | F20: =IF($B20="","",IFERROR(_xlfn.XLOOKUP($B20,Recommendations!$D:$D,Recommendations!$G:$G),"")) | G20: =IF($B20="","",IFERROR(_xlfn.XLOOKUP($B20,Recommendations!$D:$D,Recommendations!$H:$H),"")) | H20: =IF($B20="","",IFERROR(_xlfn.XLOOKUP($B20,Recommendations!$D:$D,Recommendations!$AJ:$AJ),FALSE)) | I20: =IF($B20="",FALSE,OR($H20=TRUE,$B20=BookTracker!$B$9)) -> FALSE | N20: {=IF(INDEX($P:$P,ROW()-1)="","",IF(OR(IFERROR(_xlfn.XLOOKUP(INDEX($P:$P,ROW()-1),Recommendations!$D:$D,Recommendations!$AJ:$AJ),FALSE)=TRUE,INDEX($P:$P,ROW()-1)=BookTracker!$B$9),"",ROW()-1))} | O20: Drenai Saga | AL20: {=IF(INDEX(Recommendations!$D:$D,ROW())="","",IF(INDEX(Recommendations!$AJ:$AJ,ROW())=TRUE,"",ROW()))} -> 20
N21: {=IF(INDEX($P:$P,ROW()-1)="","",IF(OR(IFERROR(_xlfn.XLOOKUP(INDEX($P:$P,ROW()-1),Recommendations!$D:$D,Recommendations!$AJ:$AJ),FALSE)=TRUE,INDEX($P:$P,ROW()-1)=BookTracker!$B$9),"",ROW()-1))} | O21: Dune | AL21: {=IF(INDEX(Recommendations!$D:$D,ROW())="","",IF(INDEX(Recommendations!$AJ:$AJ,ROW())=TRUE,"",ROW()))} -> 21
B22: 🎭 MOOD WEIGHTS (0-5 Scale, Combinable) | N22: {=IF(INDEX($P:$P,ROW()-1)="","",IF(OR(IFERROR(_xlfn.XLOOKUP(INDEX($P:$P,ROW()-1),Recommendations!$D:$D,Recommendations!$AJ:$AJ),FALSE)=TRUE,INDEX($P:$P,ROW()-1)=BookTracker!$B$9),"",ROW()-1))} | O22: Earthsea Cycle | AL22: {=IF(INDEX(Recommendations!$D:$D,ROW())="","",IF(INDEX(Recommendations!$AJ:$AJ,ROW())=TRUE,"",ROW()))} -> 22
A23: Mood | B23: Weight (0-5) | C23: Components Weighted | N23: {=IF(INDEX($P:$P,ROW()-1)="","",IF(OR(IFERROR(_xlfn.XLOOKUP(INDEX($P:$P,ROW()-1),Recommendations!$D:$D,Recommendations!$AJ:$AJ),FALSE)=TRUE,INDEX($P:$P,ROW()-1)=BookTracker!$B$9),"",ROW()-1))} | O23: Eisenhorn | AL23: {=IF(INDEX(Recommendations!$D:$D,ROW())="","",IF(INDEX(Recommendations!$AJ:$AJ,ROW())=TRUE,"",ROW()))} -> 23
A24: Action-Heavy | B24: 0 | C24: Action, Plot, Entertainment | N24: {=IF(INDEX($P:$P,ROW()-1)="","",IF(OR(IFERROR(_xlfn.XLOOKUP(INDEX($P:$P,ROW()-1),Recommendations!$D:$D,Recommendations!$AJ:$AJ),FALSE)=TRUE,INDEX($P:$P,ROW()-1)=BookTracker!$B$9),"",ROW()-1))} | O24: Ender's Shadow | AL24: {=IF(INDEX(Recommendations!$D:$D,ROW())="","",IF(INDEX(Recommendations!$AJ:$AJ,ROW())=TRUE,"",ROW()))} -> 24
A25: Theme-Heavy | B25: 0 | C25: Insights, Philosophizing, Thought-Provokingness | N25: {=IF(INDEX($P:$P,ROW()-1)="","",IF(OR(IFERROR(_xlfn.XLOOKUP(INDEX($P:$P,ROW()-1),Recommendations!$D:$D,Recommendations!$AJ:$AJ),FALSE)=TRUE,INDEX($P:$P,ROW()-1)=BookTracker!$B$9),"",ROW()-1))} | O25: Firefall | AL25: {=IF(INDEX(Recommendations!$D:$D,ROW())="","",IF(INDEX(Recommendations!$AJ:$AJ,ROW())=TRUE,"",ROW()))} -> 25
A26: Emotion-Heavy | B26: 0 | C26: Emotional Impact, Depth, Character Avg | N26: {=IF(INDEX($P:$P,ROW()-1)="","",IF(OR(IFERROR(_xlfn.XLOOKUP(INDEX($P:$P,ROW()-1),Recommendations!$D:$D,Recommendations!$AJ:$AJ),FALSE)=TRUE,INDEX($P:$P,ROW()-1)=BookTracker!$B$9),"",ROW()-1))} | O26: Foundation | AL26: {=IF(INDEX(Recommendations!$D:$D,ROW())="","",IF(INDEX(Recommendations!$AJ:$AJ,ROW())=TRUE,"",ROW()))} -> 26
A27: Immersion-Heavy | B27: 0 | C27: WB Depth, WB Originality, Prose, Phraseology | N27: {=IF(INDEX($P:$P,ROW()-1)="","",IF(OR(IFERROR(_xlfn.XLOOKUP(INDEX($P:$P,ROW()-1),Recommendations!$D:$D,Recommendations!$AJ:$AJ),FALSE)=TRUE,INDEX($P:$P,ROW()-1)=BookTracker!$B$9),"",ROW()-1))} | O27: Gentleman Bastards | AL27: {=IF(INDEX(Recommendations!$D:$D,ROW())="","",IF(INDEX(Recommendations!$AJ:$AJ,ROW())=TRUE,"",ROW()))} -> 27
A28: Story-Heavy | B28: 0 | C28: Plot, Ending, Entertainment, Pacing | N28: {=IF(INDEX($P:$P,ROW()-1)="","",IF(OR(IFERROR(_xlfn.XLOOKUP(INDEX($P:$P,ROW()-1),Recommendations!$D:$D,Recommendations!$AJ:$AJ),FALSE)=TRUE,INDEX($P:$P,ROW()-1)=BookTracker!$B$9),"",ROW()-1))} | O28: Gilead | AL28: {=IF(INDEX(Recommendations!$D:$D,ROW())="","",IF(INDEX(Recommendations!$AJ:$AJ,ROW())=TRUE,"",ROW()))} -> 28
A29: Character-Heavy | B29: 0 | C29: Depth, Motivations, Multi-Dimensionality | N29: {=IF(INDEX($P:$P,ROW()-1)="","",IF(OR(IFERROR(_xlfn.XLOOKUP(INDEX($P:$P,ROW()-1),Recommendations!$D:$D,Recommendations!$AJ:$AJ),FALSE)=TRUE,INDEX($P:$P,ROW()-1)=BookTracker!$B$9),"",ROW()-1))} | O29: Gormenghast | AL29: {=IF(INDEX(Recommendations!$D:$D,ROW())="","",IF(INDEX(Recommendations!$AJ:$AJ,ROW())=TRUE,"",ROW()))} -> 29
N30: {=IF(INDEX($P:$P,ROW()-1)="","",IF(OR(IFERROR(_xlfn.XLOOKUP(INDEX($P:$P,ROW()-1),Recommendations!$D:$D,Recommendations!$AJ:$AJ),FALSE)=TRUE,INDEX($P:$P,ROW()-1)=BookTracker!$B$9),"",ROW()-1))} | O30: Green Bone Saga | AL30: {=IF(INDEX(Recommendations!$D:$D,ROW())="","",IF(INDEX(Recommendations!$AJ:$AJ,ROW())=TRUE,"",ROW()))} -> 30
B31: 📋 ATTRIBUTE FILTERS | N31: {=IF(INDEX($P:$P,ROW()-1)="","",IF(OR(IFERROR(_xlfn.XLOOKUP(INDEX($P:$P,ROW()-1),Recommendations!$D:$D,Recommendations!$AJ:$AJ),FALSE)=TRUE,INDEX($P:$P,ROW()-1)=BookTracker!$B$9),"",ROW()-1))} | O31: Gunmetal Gods | AL31: {=IF(INDEX(Recommendations!$D:$D,ROW())="","",IF(INDEX(Recommendations!$AJ:$AJ,ROW())=TRUE,"",ROW()))} -> 31
A32: Filter | B32: Selection | C32: Options Available | N32: {=IF(INDEX($P:$P,ROW()-1)="","",IF(OR(IFERROR(_xlfn.XLOOKUP(INDEX($P:$P,ROW()-1),Recommendations!$D:$D,Recommendations!$AJ:$AJ),FALSE)=TRUE,INDEX($P:$P,ROW()-1)=BookTracker!$B$9),"",ROW()-1))} | O32: Hainish Cycle | AL32: {=IF(INDEX(Recommendations!$D:$D,ROW())="","",IF(INDEX(Recommendations!$AJ:$AJ,ROW())=TRUE,"",ROW()))} -> 32
A33: Genre: | B33: Any | C33: Epic Fantasy, Sci-Fi, Literary Fantasy, etc. | N33: {=IF(INDEX($P:$P,ROW()-1)="","",IF(OR(IFERROR(_xlfn.XLOOKUP(INDEX($P:$P,ROW()-1),Recommendations!$D:$D,Recommendations!$AJ:$AJ),FALSE)=TRUE,INDEX($P:$P,ROW()-1)=BookTracker!$B$9),"",ROW()-1))} | O33: Hyperion Cantos | AL33: {=IF(INDEX(Recommendations!$D:$D,ROW())="","",IF(INDEX(Recommendations!$AJ:$AJ,ROW())=TRUE,"",ROW()))} -> 33
A34: Length: | B34: Any | C34: Short (<150K), Medium (150-300K), Long (>300K) | N34: {=IF(INDEX($P:$P,ROW()-1)="","",IF(OR(IFERROR(_xlfn.XLOOKUP(INDEX($P:$P,ROW()-1),Recommendations!$D:$D,Recommendations!$AJ:$AJ),FALSE)=TRUE,INDEX($P:$P,ROW()-1)=BookTracker!$B$9),"",ROW()-1))} | O34: Kharkanas | AL34: {=IF(INDEX(Recommendations!$D:$D,ROW())="","",IF(INDEX(Recommendations!$AJ:$AJ,ROW())=TRUE,"",ROW()))} -> 34
A35: Type: | B35: Any | C35: Series or Standalone | N35: {=IF(INDEX($P:$P,ROW()-1)="","",IF(OR(IFERROR(_xlfn.XLOOKUP(INDEX($P:$P,ROW()-1),Recommendations!$D:$D,Recommendations!$AJ:$AJ),FALSE)=TRUE,INDEX($P:$P,ROW()-1)=BookTracker!$B$9),"",ROW()-1))} | O35: Lightbringer | AL35: {=IF(INDEX(Recommendations!$D:$D,ROW())="","",IF(INDEX(Recommendations!$AJ:$AJ,ROW())=TRUE,"",ROW()))} -> 35
A36: Author: | B36: Any | C36: Type author name or leave as 'Any' | N36: {=IF(INDEX($P:$P,ROW()-1)="","",IF(OR(IFERROR(_xlfn.XLOOKUP(INDEX($P:$P,ROW()-1),Recommendations!$D:$D,Recommendations!$AJ:$AJ),FALSE)=TRUE,INDEX($P:$P,ROW()-1)=BookTracker!$B$9),"",ROW()-1))} | O36: Lord of the Mysteries | AL36: {=IF(INDEX(Recommendations!$D:$D,ROW())="","",IF(INDEX(Recommendations!$AJ:$AJ,ROW())=TRUE,"",ROW()))} -> 36
A37: Keyword: | N37: {=IF(INDEX($P:$P,ROW()-1)="","",IF(OR(IFERROR(_xlfn.XLOOKUP(INDEX($P:$P,ROW()-1),Recommendations!$D:$D,Recommendations!$AJ:$AJ),FALSE)=TRUE,INDEX($P:$P,ROW()-1)=BookTracker!$B$9),"",ROW()-1))} | O37: Masters of Rome | AL37: {=IF(INDEX(Recommendations!$D:$D,ROW())="","",IF(INDEX(Recommendations!$AJ:$AJ,ROW())=TRUE,"",ROW()))} -> 37
N38: {=IF(INDEX($P:$P,ROW()-1)="","",IF(OR(IFERROR(_xlfn.XLOOKUP(INDEX($P:$P,ROW()-1),Recommendations!$D:$D,Recommendations!$AJ:$AJ),FALSE)=TRUE,INDEX($P:$P,ROW()-1)=BookTracker!$B$9),"",ROW()-1))} | O38: Middle-earth (Legendarium) | AL38: {=IF(INDEX(Recommendations!$D:$D,ROW())="","",IF(INDEX(Recommendations!$AJ:$AJ,ROW())=TRUE,"",ROW()))} -> 38
A39: 📊 FILTERED RESULTS - Best Matches For Your Mood | N39: {=IF(INDEX($P:$P,ROW()-1)="","",IF(OR(IFERROR(_xlfn.XLOOKUP(INDEX($P:$P,ROW()-1),Recommendations!$D:$D,Recommendations!$AJ:$AJ),FALSE)=TRUE,INDEX($P:$P,ROW()-1)=BookTracker!$B$9),"",ROW()-1))} | O39: Mistborn Era 2 | AL39: {=IF(INDEX(Recommendations!$D:$D,ROW())="","",IF(INDEX(Recommendations!$AJ:$AJ,ROW())=TRUE,"",ROW()))} -> 39
A40: # | B40: Book | C40: Author | D40: Genre | E40: Words | F40: Mood Score | G40: Pred. Rank | H40: Series | I40: Blurb | J40: Keywords | K40: Done? | L40: IsDone | N40: {=IF(INDEX($P:$P,ROW()-1)="","",IF(OR(IFERROR(_xlfn.XLOOKUP(INDEX($P:$P,ROW()-1),Recommendations!$D:$D,Recommendations!$AJ:$AJ),FALSE)=TRUE,INDEX($P:$P,ROW()-1)=BookTracker!$B$9),"",ROW()-1))} | O40: Novels of the Malazan Empire | AL40: {=IF(INDEX(Recommendations!$D:$D,ROW())="","",IF(INDEX(Recommendations!$AJ:$AJ,ROW())=TRUE,"",ROW()))} -> 40
A41: =1 -> 1 | B41: =IFERROR(INDEX($U$55:$U$542, MATCH(LARGE($AK$55:$AK$542,A41), $AK$55:$AK$542, 0)), "") -> Night Watch | C41: =IFERROR(INDEX($V$55:$V$542, MATCH(LARGE($AK$55:$AK$542,A41), $AK$55:$AK$542, 0)), "") -> Terry Pratchett | D41: =IFERROR(INDEX($W$55:$W$542, MATCH(LARGE($AK$55:$AK$542,A41), $AK$55:$AK$542, 0)), "") -> Literary Fantasy | E41: =IFERROR(INDEX($Y$55:$Y$542, MATCH(LARGE($AK$55:$AK$542,A41), $AK$55:$AK$542, 0)), "") -> 110000 | F41: =IFERROR(ROUND(INDEX($AF$55:$AF$542, MATCH(LARGE($AK$55:$AK$542,A41), $AK$55:$AK$542, 0)),2), "") -> 9.16 | G41: =IFERROR(INDEX($T$55:$T$542, MATCH(LARGE($AK$55:$AK$542,A41), $AK$55:$AK$542, 0)), "") -> 8 | H41: =IFERROR(INDEX($X$55:$X$542, MATCH(LARGE($AK$55:$AK$542,A41), $AK$55:$AK$542, 0)), "") -> Discworld: City Watch | I41: =IFERROR(_xlfn.XLOOKUP(B41,$U$55:$U$542,$AH$55:$AH$542),"") -> Pratchett's masterpiece and the consensus #1 Discworld novel — Vimes thrown back in time to mentor his own younger self through a revolution. Closest analog: The Neverending Story for thematic ambition + Lions of Al-Rassan for the moral weight of historical inevitability. A meditation on justice, duty, and what it means to be a good man under impossible conditions. Confidence caveat: Plot (predicted 9.3) is highest-risk — the time-travel mechanic is unusually rigorous for Pratchett and could land 9.0–9.6 depending on tolerance for the John Keel framing. | J41: =IFERROR(_xlfn.XLOOKUP(B41,$U$55:$U$542,$AI$55:$AI$542),"") -> comic fantasy, satire, war, anti-war, witty, biting, clever | K41: =IF($B41="",FALSE,IFERROR(_xlfn.XLOOKUP($B41,Recommendations!$D:$D,Recommendations!$AJ:$AJ),FALSE)) -> FALSE | L41: =IF($B41="",FALSE,OR($K41=TRUE,$B41=BookTracker!$B$9)) -> FALSE | N41: {=IF(INDEX($P:$P,ROW()-1)="","",IF(OR(IFERROR(_xlfn.XLOOKUP(INDEX($P:$P,ROW()-1),Recommendations!$D:$D,Recommendations!$AJ:$AJ),FALSE)=TRUE,INDEX($P:$P,ROW()-1)=BookTracker!$B$9),"",ROW()-1))} | O41: Path to Ascendancy | AL41: {=IF(INDEX(Recommendations!$D:$D,ROW())="","",IF(INDEX(Recommendations!$AJ:$AJ,ROW())=TRUE,"",ROW()))} -> 41
A42: =2 -> 2 | B42: =IFERROR(INDEX($U$55:$U$542, MATCH(LARGE($AK$55:$AK$542,A42), $AK$55:$AK$542, 0)), "") -> Les Misérables | C42: =IFERROR(INDEX($V$55:$V$542, MATCH(LARGE($AK$55:$AK$542,A42), $AK$55:$AK$542, 0)), "") -> Victor Hugo | D42: =IFERROR(INDEX($W$55:$W$542, MATCH(LARGE($AK$55:$AK$542,A42), $AK$55:$AK$542, 0)), "") -> Literary Fiction | E42: =IFERROR(INDEX($Y$55:$Y$542, MATCH(LARGE($AK$55:$AK$542,A42), $AK$55:$AK$542, 0)), "") -> 530000 | F42: =IFERROR(ROUND(INDEX($AF$55:$AF$542, MATCH(LARGE($AK$55:$AK$542,A42), $AK$55:$AK$542, 0)),2), "") -> 9.09 | G42: =IFERROR(INDEX($T$55:$T$542, MATCH(LARGE($AK$55:$AK$542,A42), $AK$55:$AK$542, 0)), "") -> 8 | H42: =IFERROR(INDEX($X$55:$X$542, MATCH(LARGE($AK$55:$AK$542,A42), $AK$55:$AK$542, 0)), "") -> Standalone | I42: =IFERROR(_xlfn.XLOOKUP(B42,$U$55:$U$542,$AH$55:$AH$542),"") -> Hugo's colossal novel of justice, redemption, and revolution — Jean Valjean's decades-long flight from Inspector Javert set against the upheavals of 19th-century France. One of literature's greatest achievements in moral imagination and narrative scope. | J42: =IFERROR(_xlfn.XLOOKUP(B42,$U$55:$U$542,$AI$55:$AI$542),"") -> India, Emergency, caste, suffering, found-family, sweeping, devastating, resilience | K42: =IF($B42="",FALSE,IFERROR(_xlfn.XLOOKUP($B42,Recommendations!$D:$D,Recommendations!$AJ:$AJ),FALSE)) -> FALSE | L42: =IF($B42="",FALSE,OR($K42=TRUE,$B42=BookTracker!$B$9)) -> FALSE | N42: {=IF(INDEX($P:$P,ROW()-1)="","",IF(OR(IFERROR(_xlfn.XLOOKUP(INDEX($P:$P,ROW()-1),Recommendations!$D:$D,Recommendations!$AJ:$AJ),FALSE)=TRUE,INDEX($P:$P,ROW()-1)=BookTracker!$B$9),"",ROW()-1))} | O42: Powder Mage Trilogy | AL42: {=IF(INDEX(Recommendations!$D:$D,ROW())="","",IF(INDEX(Recommendations!$AJ:$AJ,ROW())=TRUE,"",ROW()))} -> 42
A43: =3 -> 3 | B43: =IFERROR(INDEX($U$55:$U$542, MATCH(LARGE($AK$55:$AK$542,A43), $AK$55:$AK$542, 0)), "") -> The Warrior Prophet | C43: =IFERROR(INDEX($V$55:$V$542, MATCH(LARGE($AK$55:$AK$542,A43), $AK$55:$AK$542, 0)), "") -> R. Scott Bakker | D43: =IFERROR(INDEX($W$55:$W$542, MATCH(LARGE($AK$55:$AK$542,A43), $AK$55:$AK$542, 0)), "") -> Epic Fantasy | E43: =IFERROR(INDEX($Y$55:$Y$542, MATCH(LARGE($AK$55:$AK$542,A43), $AK$55:$AK$542, 0)), "") -> 195000 | F43: =IFERROR(ROUND(INDEX($AF$55:$AF$542, MATCH(LARGE($AK$55:$AK$542,A43), $AK$55:$AK$542, 0)),2), "") -> 9.06 | G43: =IFERROR(INDEX($T$55:$T$542, MATCH(LARGE($AK$55:$AK$542,A43), $AK$55:$AK$542, 0)), "") -> 15 | H43: =IFERROR(INDEX($X$55:$X$542, MATCH(LARGE($AK$55:$AK$542,A43), $AK$55:$AK$542, 0)), "") -> The Second Apocalypse | I43: =IFERROR(_xlfn.XLOOKUP(B43,$U$55:$U$542,$AH$55:$AH$542),"") -> The Holy War on the march — Bakker's mid-trilogy peak with three massive battles, Cnaiür at full intensity, and a circumfixion sequence widely cited among fantasy's most devastating. Action/Ending profile rivals top-tier EF (Erikson, Sanderson) while keeping LF-tier prose. Confidence caveat: Emotional Impact (predicted 8.9) is highest-risk — one character arc's handling is a known divisive area; could land 7.5–9.4. | J43: =IFERROR(_xlfn.XLOOKUP(B43,$U$55:$U$542,$AI$55:$AI$542),"") -> dark fantasy, philosophical, dense, political-intrigue, holy-war, cerebral, grimdark, slow-burn | K43: =IF($B43="",FALSE,IFERROR(_xlfn.XLOOKUP($B43,Recommendations!$D:$D,Recommendations!$AJ:$AJ),FALSE)) -> FALSE | L43: =IF($B43="",FALSE,OR($K43=TRUE,$B43=BookTracker!$B$9)) -> FALSE | N43: {=IF(INDEX($P:$P,ROW()-1)="","",IF(OR(IFERROR(_xlfn.XLOOKUP(INDEX($P:$P,ROW()-1),Recommendations!$D:$D,Recommendations!$AJ:$AJ),FALSE)=TRUE,INDEX($P:$P,ROW()-1)=BookTracker!$B$9),"",ROW()-1))} | O43: Realm of the Elderlings | AL43: {=IF(INDEX(Recommendations!$D:$D,ROW())="","",IF(INDEX(Recommendations!$AJ:$AJ,ROW())=TRUE,"",ROW()))} -> 43
A44: =4 -> 4 | B44: =IFERROR(INDEX($U$55:$U$542, MATCH(LARGE($AK$55:$AK$542,A44), $AK$55:$AK$542, 0)), "") -> The Leopard | C44: =IFERROR(INDEX($V$55:$V$542, MATCH(LARGE($AK$55:$AK$542,A44), $AK$55:$AK$542, 0)), "") -> Giuseppe Tomasi di Lampedusa | D44: =IFERROR(INDEX($W$55:$W$542, MATCH(LARGE($AK$55:$AK$542,A44), $AK$55:$AK$542, 0)), "") -> Literary Fiction | E44: =IFERROR(INDEX($Y$55:$Y$542, MATCH(LARGE($AK$55:$AK$542,A44), $AK$55:$AK$542, 0)), "") -> 100000 | F44: =IFERROR(ROUND(INDEX($AF$55:$AF$542, MATCH(LARGE($AK$55:$AK$542,A44), $AK$55:$AK$542, 0)),2), "") -> 9.03 | G44: =IFERROR(INDEX($T$55:$T$542, MATCH(LARGE($AK$55:$AK$542,A44), $AK$55:$AK$542, 0)), "") -> 14 | H44: =IFERROR(INDEX($X$55:$X$542, MATCH(LARGE($AK$55:$AK$542,A44), $AK$55:$AK$542, 0)), "") -> Standalone | I44: =IFERROR(_xlfn.XLOOKUP(B44,$U$55:$U$542,$AH$55:$AH$542),"") -> Don Fabrizio's twilight as Sicilian prince during the Risorgimento — single-novel masterpiece, compact at ~250 pages, ending with one of the most revered closing movements in literature ('Things must change so that they can stay the same'). Tonally closer to Middlemarch's autumnal wisdom (your pred 8.83) than to War and Peace's sweep. Predicted Total Avg 8.92 → ~Rank 11, with Aesthetics (9.37) tying with Theme (9.37) as the highest paired scores I've assigned in this turn; Lampedusa's prose is the structural standout. Highest-confidence pick of this set — if any one of these matches the Les Misérables (9.02) emotional ceiling for you, it's this one. | J44: =IFERROR(_xlfn.XLOOKUP(B44,$U$55:$U$542,$AI$55:$AI$542),"") -> literary, classic, provincial, marriage, ambition, psychological, dense, humane | K44: =IF($B44="",FALSE,IFERROR(_xlfn.XLOOKUP($B44,Recommendations!$D:$D,Recommendations!$AJ:$AJ),FALSE)) -> FALSE | L44: =IF($B44="",FALSE,OR($K44=TRUE,$B44=BookTracker!$B$9)) -> FALSE | N44: {=IF(INDEX($P:$P,ROW()-1)="","",IF(OR(IFERROR(_xlfn.XLOOKUP(INDEX($P:$P,ROW()-1),Recommendations!$D:$D,Recommendations!$AJ:$AJ),FALSE)=TRUE,INDEX($P:$P,ROW()-1)=BookTracker!$B$9),"",ROW()-1))} | O44: Remembrance of Earth's Past | AL44: {=IF(INDEX(Recommendations!$D:$D,ROW())="","",IF(INDEX(Recommendations!$AJ:$AJ,ROW())=TRUE,"",ROW()))} -> 44
A45: =5 -> 5 | B45: =IFERROR(INDEX($U$55:$U$542, MATCH(LARGE($AK$55:$AK$542,A45), $AK$55:$AK$542, 0)), "") -> Speaking Bones | C45: =IFERROR(INDEX($V$55:$V$542, MATCH(LARGE($AK$55:$AK$542,A45), $AK$55:$AK$542, 0)), "") -> Ken Liu | D45: =IFERROR(INDEX($W$55:$W$542, MATCH(LARGE($AK$55:$AK$542,A45), $AK$55:$AK$542, 0)), "") -> Epic Fantasy | E45: =IFERROR(INDEX($Y$55:$Y$542, MATCH(LARGE($AK$55:$AK$542,A45), $AK$55:$AK$542, 0)), "") -> 370000 | F45: =IFERROR(ROUND(INDEX($AF$55:$AF$542, MATCH(LARGE($AK$55:$AK$542,A45), $AK$55:$AK$542, 0)),2), "") -> 9.01 | G45: =IFERROR(INDEX($T$55:$T$542, MATCH(LARGE($AK$55:$AK$542,A45), $AK$55:$AK$542, 0)), "") -> 12 | H45: =IFERROR(INDEX($X$55:$X$542, MATCH(LARGE($AK$55:$AK$542,A45), $AK$55:$AK$542, 0)), "") -> The Dandelion Dynasty | I45: =IFERROR(_xlfn.XLOOKUP(B45,$U$55:$U$542,$AH$55:$AH$542),"") -> The triumphant finale — multiple reviewers gave it 9.7/10 and called it a 'perfect ending,' with Liu's prose at its 'spectacular' peak and a generational epilogue (Part V) that pays off a decade of setup. Closest analog: The Unholy Consult-level series catharsis. Confidence caveat: Pacing (predicted 7.5) is highest-risk — Part 3's meditative middle and the 5-part epilogue structure could read as either profound or sprawling (could land 6.5–8.5). | J45: =IFERROR(_xlfn.XLOOKUP(B45,$U$55:$U$542,$AI$55:$AI$542),"") -> silkpunk, naval, inventive, political, expansive, war, ambitious | K45: =IF($B45="",FALSE,IFERROR(_xlfn.XLOOKUP($B45,Recommendations!$D:$D,Recommendations!$AJ:$AJ),FALSE)) -> FALSE | L45: =IF($B45="",FALSE,OR($K45=TRUE,$B45=BookTracker!$B$9)) -> FALSE | N45: {=IF(INDEX($P:$P,ROW()-1)="","",IF(OR(IFERROR(_xlfn.XLOOKUP(INDEX($P:$P,ROW()-1),Recommendations!$D:$D,Recommendations!$AJ:$AJ),FALSE)=TRUE,INDEX($P:$P,ROW()-1)=BookTracker!$B$9),"",ROW()-1))} | O45: Secret Projects | AL45: {=IF(INDEX(Recommendations!$D:$D,ROW())="","",IF(INDEX(Recommendations!$AJ:$AJ,ROW())=TRUE,"",ROW()))} -> 45
A46: =6 -> 6 | B46: =IFERROR(INDEX($U$55:$U$542, MATCH(LARGE($AK$55:$AK$542,A46), $AK$55:$AK$542, 0)), "") -> Crime and Punishment | C46: =IFERROR(INDEX($V$55:$V$542, MATCH(LARGE($AK$55:$AK$542,A46), $AK$55:$AK$542, 0)), "") -> Fyodor Dostoevsky | D46: =IFERROR(INDEX($W$55:$W$542, MATCH(LARGE($AK$55:$AK$542,A46), $AK$55:$AK$542, 0)), "") -> Russian Literature | E46: =IFERROR(INDEX($Y$55:$Y$542, MATCH(LARGE($AK$55:$AK$542,A46), $AK$55:$AK$542, 0)), "") -> 211000 | F46: =IFERROR(ROUND(INDEX($AF$55:$AF$542, MATCH(LARGE($AK$55:$AK$542,A46), $AK$55:$AK$542, 0)),2), "") -> 8.99 | G46: =IFERROR(INDEX($T$55:$T$542, MATCH(LARGE($AK$55:$AK$542,A46), $AK$55:$AK$542, 0)), "") -> 10 | H46: =IFERROR(INDEX($X$55:$X$542, MATCH(LARGE($AK$55:$AK$542,A46), $AK$55:$AK$542, 0)), "") -> Standalone | I46: =IFERROR(_xlfn.XLOOKUP(B46,$U$55:$U$542,$AH$55:$AH$542),"") -> Dostoevsky's tightest masterpiece — Raskolnikov's axe murder and the psychological pursuit by Porfiry Petrovich, with Sonya as the moral counterweight. Leaner than Karamazov but more intense; closest analog on your shelf is The Brothers Karamazov (pred 8.84). Predicted Total Avg 8.83 → ~Rank 13, with Theme (9.50) and Character (9.15) peaking — the entire Raskolnikov interiority is in the highest moral-philosophy tier of anything on your shelf. Confidence caveat: Pacing (8.3) is the modest risk — the middle act with Marmeladov can feel digressive, and Action (7.8) is the lowest single score (this is a novel of internal action). Likely your second-highest Dostoevsky behind Karamazov. | J46: =IFERROR(_xlfn.XLOOKUP(B46,$U$55:$U$542,$AI$55:$AI$542),"") -> labyrinthine, metaphysical, short-stories, cerebral, playful, philosophical, mind-bending | K46: =IF($B46="",FALSE,IFERROR(_xlfn.XLOOKUP($B46,Recommendations!$D:$D,Recommendations!$AJ:$AJ),FALSE)) -> FALSE | L46: =IF($B46="",FALSE,OR($K46=TRUE,$B46=BookTracker!$B$9)) -> FALSE | N46: {=IF(INDEX($P:$P,ROW()-1)="","",IF(OR(IFERROR(_xlfn.XLOOKUP(INDEX($P:$P,ROW()-1),Recommendations!$D:$D,Recommendations!$AJ:$AJ),FALSE)=TRUE,INDEX($P:$P,ROW()-1)=BookTracker!$B$9),"",ROW()-1))} | O46: Sharpe | AL46: {=IF(INDEX(Recommendations!$D:$D,ROW())="","",IF(INDEX(Recommendations!$AJ:$AJ,ROW())=TRUE,"",ROW()))} -> 46
A47: =7 -> 7 | B47: =IFERROR(INDEX($U$55:$U$542, MATCH(LARGE($AK$55:$AK$542,A47), $AK$55:$AK$542, 0)), "") -> The Burning God | C47: =IFERROR(INDEX($V$55:$V$542, MATCH(LARGE($AK$55:$AK$542,A47), $AK$55:$AK$542, 0)), "") -> R.F. Kuang | D47: =IFERROR(INDEX($W$55:$W$542, MATCH(LARGE($AK$55:$AK$542,A47), $AK$55:$AK$542, 0)), "") -> Epic Fantasy | E47: =IFERROR(INDEX($Y$55:$Y$542, MATCH(LARGE($AK$55:$AK$542,A47), $AK$55:$AK$542, 0)), "") -> 160000 | F47: =IFERROR(ROUND(INDEX($AF$55:$AF$542, MATCH(LARGE($AK$55:$AK$542,A47), $AK$55:$AK$542, 0)),2), "") -> 8.96 | G47: =IFERROR(INDEX($T$55:$T$542, MATCH(LARGE($AK$55:$AK$542,A47), $AK$55:$AK$542, 0)), "") -> 13 | H47: =IFERROR(INDEX($X$55:$X$542, MATCH(LARGE($AK$55:$AK$542,A47), $AK$55:$AK$542, 0)), "") -> The Poppy War | I47: =IFERROR(_xlfn.XLOOKUP(B47,$U$55:$U$542,$AH$55:$AH$542),"") -> The trilogy's devastating capstone, widely cited as Kuang's best-written book — Rin as fantastical Mao Zedong, postcolonial revolution, and a tragic finale critics call 'the only logical/perfect ending' (Ending 9.4 lands in Transcendent +1.4 WA band; one reviewer: 'George R.R. Martin, eat your heart out'). Stylistic analog is ASoS for the front-to-back tragic-payoff structure, though Kuang's thematic payload (Insights 9.2, Mao parallel, postcolonial framing) goes deeper than Martin attempts. Confidence caveat: Emotional Impact (9.5) is the highest-risk component — if the tragic ending lands as 'inevitable' rather than 'earned' for you, this drops to ~8.5 and the WA loses ~0.3. | J47: =IFERROR(_xlfn.XLOOKUP(B47,$U$55:$U$542,$AI$55:$AI$542),"") -> military, grimdark, war-atrocity, dark, intense, historical-inspired, harrowing | K47: =IF($B47="",FALSE,IFERROR(_xlfn.XLOOKUP($B47,Recommendations!$D:$D,Recommendations!$AJ:$AJ),FALSE)) -> FALSE | L47: =IF($B47="",FALSE,OR($K47=TRUE,$B47=BookTracker!$B$9)) -> FALSE | N47: {=IF(INDEX($P:$P,ROW()-1)="","",IF(OR(IFERROR(_xlfn.XLOOKUP(INDEX($P:$P,ROW()-1),Recommendations!$D:$D,Recommendations!$AJ:$AJ),FALSE)=TRUE,INDEX($P:$P,ROW()-1)=BookTracker!$B$9),"",ROW()-1))} | O47: The Acts of Caine | AL47: {=IF(INDEX(Recommendations!$D:$D,ROW())="","",IF(INDEX(Recommendations!$AJ:$AJ,ROW())=TRUE,"",ROW()))} -> 47
A48: =8 -> 8 | B48: =IFERROR(INDEX($U$55:$U$542, MATCH(LARGE($AK$55:$AK$542,A48), $AK$55:$AK$542, 0)), "") -> The Count of Monte Cristo | C48: =IFERROR(INDEX($V$55:$V$542, MATCH(LARGE($AK$55:$AK$542,A48), $AK$55:$AK$542, 0)), "") -> Alexandre Dumas | D48: =IFERROR(INDEX($W$55:$W$542, MATCH(LARGE($AK$55:$AK$542,A48), $AK$55:$AK$542, 0)), "") -> Literary Fiction | E48: =IFERROR(INDEX($Y$55:$Y$542, MATCH(LARGE($AK$55:$AK$542,A48), $AK$55:$AK$542, 0)), "") -> 464234 | F48: =IFERROR(ROUND(INDEX($AF$55:$AF$542, MATCH(LARGE($AK$55:$AK$542,A48), $AK$55:$AK$542, 0)),2), "") -> 8.92 | G48: =IFERROR(INDEX($T$55:$T$542, MATCH(LARGE($AK$55:$AK$542,A48), $AK$55:$AK$542, 0)), "") -> 11 | H48: =IFERROR(INDEX($X$55:$X$542, MATCH(LARGE($AK$55:$AK$542,A48), $AK$55:$AK$542, 0)), "") -> Standalone | I48: =IFERROR(_xlfn.XLOOKUP(B48,$U$55:$U$542,$AH$55:$AH$542),"") -> Dumas' swashbuckling epic of elaborate revenge — Edmond Dantès, wrongly imprisoned, escapes to become the mysterious Count and dismantle his betrayers' lives with surgical precision. Endlessly entertaining, structurally magnificent, and impossible to put down. | J48: =IFERROR(_xlfn.XLOOKUP(B48,$U$55:$U$542,$AI$55:$AI$542),"") -> literary, classic, redemption, justice, sweeping, moral, emotional, french | K48: =IF($B48="",FALSE,IFERROR(_xlfn.XLOOKUP($B48,Recommendations!$D:$D,Recommendations!$AJ:$AJ),FALSE)) -> FALSE | L48: =IF($B48="",FALSE,OR($K48=TRUE,$B48=BookTracker!$B$9)) -> FALSE | N48: {=IF(INDEX($P:$P,ROW()-1)="","",IF(OR(IFERROR(_xlfn.XLOOKUP(INDEX($P:$P,ROW()-1),Recommendations!$D:$D,Recommendations!$AJ:$AJ),FALSE)=TRUE,INDEX($P:$P,ROW()-1)=BookTracker!$B$9),"",ROW()-1))} | O48: The Age of Madness | AL48: {=IF(INDEX(Recommendations!$D:$D,ROW())="","",IF(INDEX(Recommendations!$AJ:$AJ,ROW())=TRUE,"",ROW()))} -> 48
A49: =9 -> 9 | B49: =IFERROR(INDEX($U$55:$U$542, MATCH(LARGE($AK$55:$AK$542,A49), $AK$55:$AK$542, 0)), "") -> Fall of Light | C49: =IFERROR(INDEX($V$55:$V$542, MATCH(LARGE($AK$55:$AK$542,A49), $AK$55:$AK$542, 0)), "") -> Steven Erikson | D49: =IFERROR(INDEX($W$55:$W$542, MATCH(LARGE($AK$55:$AK$542,A49), $AK$55:$AK$542, 0)), "") -> Epic Fantasy | E49: =IFERROR(INDEX($Y$55:$Y$542, MATCH(LARGE($AK$55:$AK$542,A49), $AK$55:$AK$542, 0)), "") -> 388700 | F49: =IFERROR(ROUND(INDEX($AF$55:$AF$542, MATCH(LARGE($AK$55:$AK$542,A49), $AK$55:$AK$542, 0)),2), "") -> 8.92 | G49: =IFERROR(INDEX($T$55:$T$542, MATCH(LARGE($AK$55:$AK$542,A49), $AK$55:$AK$542, 0)), "") -> 26 | H49: =IFERROR(INDEX($X$55:$X$542, MATCH(LARGE($AK$55:$AK$542,A49), $AK$55:$AK$542, 0)), "") -> Kharkanas | I49: =IFERROR(_xlfn.XLOOKUP(B49,$U$55:$U$542,$AH$55:$AH$542),"") -> Widely considered superior to Forge — deeper tragedy, more emotional payoff, Erikson's most sorrowful prose. Reads in the Toll the Hounds / Memories of Ice band: Prose (9.4), Emotional Impact (9.3), Themes (9.4). Closest analog: Toll the Hounds — same patient, philosophical depth applied to civilizational collapse. Confidence caveat: Pacing (7.0) is the biggest risk — readers exhausted by Forge often DNF Fall of Light (could land 5.5–8.0). | J49: =IFERROR(_xlfn.XLOOKUP(B49,$U$55:$U$542,$AI$55:$AI$542),"") -> grimdark, war, dark, brutal, political, mythic, gritty, intense | K49: =IF($B49="",FALSE,IFERROR(_xlfn.XLOOKUP($B49,Recommendations!$D:$D,Recommendations!$AJ:$AJ),FALSE)) -> FALSE | L49: =IF($B49="",FALSE,OR($K49=TRUE,$B49=BookTracker!$B$9)) -> FALSE | N49: {=IF(INDEX($P:$P,ROW()-1)="","",IF(OR(IFERROR(_xlfn.XLOOKUP(INDEX($P:$P,ROW()-1),Recommendations!$D:$D,Recommendations!$AJ:$AJ),FALSE)=TRUE,INDEX($P:$P,ROW()-1)=BookTracker!$B$9),"",ROW()-1))} | O49: The Bloodsworn Saga | AL49: {=IF(INDEX(Recommendations!$D:$D,ROW())="","",IF(INDEX(Recommendations!$AJ:$AJ,ROW())=TRUE,"",ROW()))} -> 49
A50: =10 -> 10 | B50: =IFERROR(INDEX($U$55:$U$542, MATCH(LARGE($AK$55:$AK$542,A50), $AK$55:$AK$542, 0)), "") -> The White-Luck Warrior | C50: =IFERROR(INDEX($V$55:$V$542, MATCH(LARGE($AK$55:$AK$542,A50), $AK$55:$AK$542, 0)), "") -> R. Scott Bakker | D50: =IFERROR(INDEX($W$55:$W$542, MATCH(LARGE($AK$55:$AK$542,A50), $AK$55:$AK$542, 0)), "") -> Epic Fantasy | E50: =IFERROR(INDEX($Y$55:$Y$542, MATCH(LARGE($AK$55:$AK$542,A50), $AK$55:$AK$542, 0)), "") -> 195000 | F50: =IFERROR(ROUND(INDEX($AF$55:$AF$542, MATCH(LARGE($AK$55:$AK$542,A50), $AK$55:$AK$542, 0)),2), "") -> 8.88 | G50: =IFERROR(INDEX($T$55:$T$542, MATCH(LARGE($AK$55:$AK$542,A50), $AK$55:$AK$542, 0)), "") -> 20 | H50: =IFERROR(INDEX($X$55:$X$542, MATCH(LARGE($AK$55:$AK$542,A50), $AK$55:$AK$542, 0)), "") -> The Second Apocalypse | I50: =IFERROR(_xlfn.XLOOKUP(B50,$U$55:$U$542,$AH$55:$AH$542),"") -> Aspect-Emperor middle volume that escalates well — massive battle sequences, deepening metaphysics, and damnation deployed as a literal narrative device. Cohesive thematic unity holds the sprawling cast together. Confidence caveat: Pacing (predicted 7.6) is highest-risk — extended travel chapters and recursive philosophical riffs slow chunks of the middle; could land 6.0–8.0. | J50: =IFERROR(_xlfn.XLOOKUP(B50,$U$55:$U$542,$AI$55:$AI$542),"") -> dark fantasy, philosophical, war, apocalyptic, dense, cerebral, intense | K50: =IF($B50="",FALSE,IFERROR(_xlfn.XLOOKUP($B50,Recommendations!$D:$D,Recommendations!$AJ:$AJ),FALSE)) -> FALSE | L50: =IF($B50="",FALSE,OR($K50=TRUE,$B50=BookTracker!$B$9)) -> FALSE | N50: {=IF(INDEX($P:$P,ROW()-1)="","",IF(OR(IFERROR(_xlfn.XLOOKUP(INDEX($P:$P,ROW()-1),Recommendations!$D:$D,Recommendations!$AJ:$AJ),FALSE)=TRUE,INDEX($P:$P,ROW()-1)=BookTracker!$B$9),"",ROW()-1))} | O50: The Book of the Long Sun | AL50: {=IF(INDEX(Recommendations!$D:$D,ROW())="","",IF(INDEX(Recommendations!$AJ:$AJ,ROW())=TRUE,"",ROW()))} -> 50
A51: =11 -> 11 | B51: =IFERROR(INDEX($U$55:$U$542, MATCH(LARGE($AK$55:$AK$542,A51), $AK$55:$AK$542, 0)), "") -> The Brothers Karamazov | C51: =IFERROR(INDEX($V$55:$V$542, MATCH(LARGE($AK$55:$AK$542,A51), $AK$55:$AK$542, 0)), "") -> Fyodor Dostoevsky | D51: =IFERROR(INDEX($W$55:$W$542, MATCH(LARGE($AK$55:$AK$542,A51), $AK$55:$AK$542, 0)), "") -> Russian Literature | E51: =IFERROR(INDEX($Y$55:$Y$542, MATCH(LARGE($AK$55:$AK$542,A51), $AK$55:$AK$542, 0)), "") -> 360000 | F51: =IFERROR(ROUND(INDEX($AF$55:$AF$542, MATCH(LARGE($AK$55:$AK$542,A51), $AK$55:$AK$542, 0)),2), "") -> 8.87 | G51: =IFERROR(INDEX($T$55:$T$542, MATCH(LARGE($AK$55:$AK$542,A51), $AK$55:$AK$542, 0)), "") -> 10 | H51: =IFERROR(INDEX($X$55:$X$542, MATCH(LARGE($AK$55:$AK$542,A51), $AK$55:$AK$542, 0)), "") -> Standalone | I51: =IFERROR(_xlfn.XLOOKUP(B51,$U$55:$U$542,$AH$55:$AH$542),"") -> Peak Dostoevsky — three brothers, a murdered father, and a trial that becomes a referendum on faith, doubt, love, and the existence of God. Grand Inquisitor, Devil chapter, and Ivan's rebellion are among the most ambitious passages in any novel. Theme (9.5 across) is the structural anchor, Char 9.25 right behind. Analog: The Idiot (8.39) for Dostoevsky baseline, lifted on scope and finale. Predicted WA 8.92 → Rank ~11. Confidence caveat: Pacing (6.0) and Action (5.5) reflect the philosophical-trial digressions; the middle Zosima section can stall readers. | J51: =IFERROR(_xlfn.XLOOKUP(B51,$U$55:$U$542,$AI$55:$AI$542),"") -> ghosts, Mexico, fragmented, haunting, lyrical, dreamlike, short, melancholic | K51: =IF($B51="",FALSE,IFERROR(_xlfn.XLOOKUP($B51,Recommendations!$D:$D,Recommendations!$AJ:$AJ),FALSE)) -> FALSE | L51: =IF($B51="",FALSE,OR($K51=TRUE,$B51=BookTracker!$B$9)) -> FALSE | N51: {=IF(INDEX($P:$P,ROW()-1)="","",IF(OR(IFERROR(_xlfn.XLOOKUP(INDEX($P:$P,ROW()-1),Recommendations!$D:$D,Recommendations!$AJ:$AJ),FALSE)=TRUE,INDEX($P:$P,ROW()-1)=BookTracker!$B$9),"",ROW()-1))} | O51: The Book of the New Sun | AL51: {=IF(INDEX(Recommendations!$D:$D,ROW())="","",IF(INDEX(Recommendations!$AJ:$AJ,ROW())=TRUE,"",ROW()))} -> 51
A52: =12 -> 12 | B52: =IFERROR(INDEX($U$55:$U$542, MATCH(LARGE($AK$55:$AK$542,A52), $AK$55:$AK$542, 0)), "") -> Middlemarch | C52: =IFERROR(INDEX($V$55:$V$542, MATCH(LARGE($AK$55:$AK$542,A52), $AK$55:$AK$542, 0)), "") -> George Eliot | D52: =IFERROR(INDEX($W$55:$W$542, MATCH(LARGE($AK$55:$AK$542,A52), $AK$55:$AK$542, 0)), "") -> Literary Fiction | E52: =IFERROR(INDEX($Y$55:$Y$542, MATCH(LARGE($AK$55:$AK$542,A52), $AK$55:$AK$542, 0)), "") -> 316000 | F52: =IFERROR(ROUND(INDEX($AF$55:$AF$542, MATCH(LARGE($AK$55:$AK$542,A52), $AK$55:$AK$542, 0)),2), "") -> 8.87 | G52: =IFERROR(INDEX($T$55:$T$542, MATCH(LARGE($AK$55:$AK$542,A52), $AK$55:$AK$542, 0)), "") -> 13 | H52: =IFERROR(INDEX($X$55:$X$542, MATCH(LARGE($AK$55:$AK$542,A52), $AK$55:$AK$542, 0)), "") -> Standalone | I52: =IFERROR(_xlfn.XLOOKUP(B52,$U$55:$U$542,$AH$55:$AH$542),"") -> Eliot's panoramic novel of Middlemarch, an English provincial town — following the idealistic Dorothea Brooke and the scholarly Dr. Lydgate as their ambitions collide with reality. Virginia Woolf called it one of the few English novels written for grown-up people. | J52: =IFERROR(_xlfn.XLOOKUP(B52,$U$55:$U$542,$AI$55:$AI$542),"") -> portal fantasy, sci-fi mashup, amnesia, humor, adventure, experimental, action | K52: =IF($B52="",FALSE,IFERROR(_xlfn.XLOOKUP($B52,Recommendations!$D:$D,Recommendations!$AJ:$AJ),FALSE)) -> FALSE | L52: =IF($B52="",FALSE,OR($K52=TRUE,$B52=BookTracker!$B$9)) -> FALSE | N52: {=IF(INDEX($P:$P,ROW()-1)="","",IF(OR(IFERROR(_xlfn.XLOOKUP(INDEX($P:$P,ROW()-1),Recommendations!$D:$D,Recommendations!$AJ:$AJ),FALSE)=TRUE,INDEX($P:$P,ROW()-1)=BookTracker!$B$9),"",ROW()-1))} | O52: The Books of Babel | AL52: {=IF(INDEX(Recommendations!$D:$D,ROW())="","",IF(INDEX(Recommendations!$AJ:$AJ,ROW())=TRUE,"",ROW()))} -> 52
A53: =13 -> 13 | B53: =IFERROR(INDEX($U$55:$U$542, MATCH(LARGE($AK$55:$AK$542,A53), $AK$55:$AK$542, 0)), "") -> Stormed Fortress | C53: =IFERROR(INDEX($V$55:$V$542, MATCH(LARGE($AK$55:$AK$542,A53), $AK$55:$AK$542, 0)), "") -> Janny Wurts | D53: =IFERROR(INDEX($W$55:$W$542, MATCH(LARGE($AK$55:$AK$542,A53), $AK$55:$AK$542, 0)), "") -> Epic Fantasy | E53: =IFERROR(INDEX($Y$55:$Y$542, MATCH(LARGE($AK$55:$AK$542,A53), $AK$55:$AK$542, 0)), "") -> 239000 | F53: =IFERROR(ROUND(INDEX($AF$55:$AF$542, MATCH(LARGE($AK$55:$AK$542,A53), $AK$55:$AK$542, 0)),2), "") -> 8.86 | G53: =IFERROR(INDEX($T$55:$T$542, MATCH(LARGE($AK$55:$AK$542,A53), $AK$55:$AK$542, 0)), "") -> 22 | H53: =IFERROR(INDEX($X$55:$X$542, MATCH(LARGE($AK$55:$AK$542,A53), $AK$55:$AK$542, 0)), "") -> Wars of Light and Shadow | I53: =IFERROR(_xlfn.XLOOKUP(B53,$U$55:$U$542,$AH$55:$AH$542),"") -> Arc 3's emotional and narrative payoff — siege of Alestron, Davien's arc, multiple character resolutions. Unanimously praised as the best of the Alliance of Light arc and a candidate for the series' best book. Closest analog: Erikson's The Crippled God in earned-conclusion energy. Confidence caveat: Emotional Impact (predicted 8.7) is highest-risk — could land 8.2–9.2 depending on arc investment. | J53: =IFERROR(_xlfn.XLOOKUP(B53,$U$55:$U$542,$AI$55:$AI$542),"") -> epic fantasy, conspiracy, intrigue, prose-heavy, slow-burn, sprawling, intricate | K53: =IF($B53="",FALSE,IFERROR(_xlfn.XLOOKUP($B53,Recommendations!$D:$D,Recommendations!$AJ:$AJ),FALSE)) -> FALSE | L53: =IF($B53="",FALSE,OR($K53=TRUE,$B53=BookTracker!$B$9)) -> FALSE | N53: {=IF(INDEX($P:$P,ROW()-1)="","",IF(OR(IFERROR(_xlfn.XLOOKUP(INDEX($P:$P,ROW()-1),Recommendations!$D:$D,Recommendations!$AJ:$AJ),FALSE)=TRUE,INDEX($P:$P,ROW()-1)=BookTracker!$B$9),"",ROW()-1))} | O53: The Broken Empire | T53: HELPER: Mood Score Calculation (All books from Recommendations, rows 3-400) | AL53: {=IF(INDEX(Recommendations!$D:$D,ROW())="","",IF(INDEX(Recommendations!$AJ:$AJ,ROW())=TRUE,"",ROW()))} -> 53
A54: =14 -> 14 | B54: =IFERROR(INDEX($U$55:$U$542, MATCH(LARGE($AK$55:$AK$542,A54), $AK$55:$AK$542, 0)), "") -> A Storm of Swords | C54: =IFERROR(INDEX($V$55:$V$542, MATCH(LARGE($AK$55:$AK$542,A54), $AK$55:$AK$542, 0)), "") -> George R.R. Martin | D54: =IFERROR(INDEX($W$55:$W$542, MATCH(LARGE($AK$55:$AK$542,A54), $AK$55:$AK$542, 0)), "") -> Epic Fantasy | E54: =IFERROR(INDEX($Y$55:$Y$542, MATCH(LARGE($AK$55:$AK$542,A54), $AK$55:$AK$542, 0)), "") -> 424000 | F54: =IFERROR(ROUND(INDEX($AF$55:$AF$542, MATCH(LARGE($AK$55:$AK$542,A54), $AK$55:$AK$542, 0)),2), "") -> 8.86 | G54: =IFERROR(INDEX($T$55:$T$542, MATCH(LARGE($AK$55:$AK$542,A54), $AK$55:$AK$542, 0)), "") -> 13 | H54: =IFERROR(INDEX($X$55:$X$542, MATCH(LARGE($AK$55:$AK$542,A54), $AK$55:$AK$542, 0)), "") -> A Song of Ice and Fire | I54: =IFERROR(_xlfn.XLOOKUP(B54,$U$55:$U$542,$AH$55:$AH$542),"") -> The series peak — more shocking, momentum-shifting set pieces per page than any other fantasy novel in this list. Ending at 9.5 is the highest in the series; prose and worldbuilding also hit series highs. Nearly 200k words longer than Book 1 but not a page feels wasted. The definitive case for ASOIAF as high literary fantasy. | J54: =IFERROR(_xlfn.XLOOKUP(B54,$U$55:$U$542,$AI$55:$AI$542),"") -> epic fantasy, political, brutal, multi-POV, shocking, war, morally-grey, gripping | K54: =IF($B54="",FALSE,IFERROR(_xlfn.XLOOKUP($B54,Recommendations!$D:$D,Recommendations!$AJ:$AJ),FALSE)) -> FALSE | L54: =IF($B54="",FALSE,OR($K54=TRUE,$B54=BookTracker!$B$9)) -> FALSE | N54: {=IF(INDEX($P:$P,ROW()-1)="","",IF(OR(IFERROR(_xlfn.XLOOKUP(INDEX($P:$P,ROW()-1),Recommendations!$D:$D,Recommendations!$AJ:$AJ),FALSE)=TRUE,INDEX($P:$P,ROW()-1)=BookTracker!$B$9),"",ROW()-1))} | O54: The Chronicles of the Black Company | T54: Rank | U54: Book | V54: Author | W54: Genre | X54: Series | Y54: Words | Z54: Action | AA54: Theme | AB54: Emotion | AC54: Immerse | AD54: Story | AE54: Chars | AF54: MoodScore | AG54: UniqueRank | AH54: Blurb | AI54: Keywords | AJ54: KwMatch | AK54: FilteredRank | AL54: {=IF(INDEX(Recommendations!$D:$D,ROW())="","",IF(INDEX(Recommendations!$AJ:$AJ,ROW())=TRUE,"",ROW()))} -> 54
A55: =15 -> 15 | B55: =IFERROR(INDEX($U$55:$U$542, MATCH(LARGE($AK$55:$AK$542,A55), $AK$55:$AK$542, 0)), "") -> The Unholy Consult | C55: =IFERROR(INDEX($V$55:$V$542, MATCH(LARGE($AK$55:$AK$542,A55), $AK$55:$AK$542, 0)), "") -> R. Scott Bakker | D55: =IFERROR(INDEX($W$55:$W$542, MATCH(LARGE($AK$55:$AK$542,A55), $AK$55:$AK$542, 0)), "") -> Epic Fantasy | E55: =IFERROR(INDEX($Y$55:$Y$542, MATCH(LARGE($AK$55:$AK$542,A55), $AK$55:$AK$542, 0)), "") -> 165000 | F55: =IFERROR(ROUND(INDEX($AF$55:$AF$542, MATCH(LARGE($AK$55:$AK$542,A55), $AK$55:$AK$542, 0)),2), "") -> 8.84 | G55: =IFERROR(INDEX($T$55:$T$542, MATCH(LARGE($AK$55:$AK$542,A55), $AK$55:$AK$542, 0)), "") -> 22 | H55: =IFERROR(INDEX($X$55:$X$542, MATCH(LARGE($AK$55:$AK$542,A55), $AK$55:$AK$542, 0)), "") -> The Second Apocalypse | I55: =IFERROR(_xlfn.XLOOKUP(B55,$U$55:$U$542,$AH$55:$AH$542),"") -> Series finale at Golgotterath — a climactic siege and the long-deferred central metaphysical question finally confronted; Bakker either sticks the landing spectacularly or fumbles it depending on the reader. Strong Plot/Depth/Worldbuilding with best-in-series battle action, but a deliberately abrupt close and a repetitive opening stretch. Confidence caveat: Ending (predicted 7.2) is the highest-risk component in any Bakker book — community reaction ranges from rapturous to 'profoundly disappointing.' Could land 5.0–9.0. | J55: =IFERROR(_xlfn.XLOOKUP(B55,$U$55:$U$542,$AI$55:$AI$542),"") -> dark fantasy, war, philosophical, grim, dense, harrowing, cerebral | K55: =IF($B55="",FALSE,IFERROR(_xlfn.XLOOKUP($B55,Recommendations!$D:$D,Recommendations!$AJ:$AJ),FALSE)) -> FALSE | L55: =IF($B55="",FALSE,OR($K55=TRUE,$B55=BookTracker!$B$9)) -> FALSE | N55: {=IF(INDEX($P:$P,ROW()-1)="","",IF(OR(IFERROR(_xlfn.XLOOKUP(INDEX($P:$P,ROW()-1),Recommendations!$D:$D,Recommendations!$AJ:$AJ),FALSE)=TRUE,INDEX($P:$P,ROW()-1)=BookTracker!$B$9),"",ROW()-1))} | O55: The Civil War Trilogy | AL55: {=IF(INDEX(Recommendations!$D:$D,ROW())="","",IF(INDEX(Recommendations!$AJ:$AJ,ROW())=TRUE,"",ROW()))} -> 55 | AM55: recRow (helper)
A56: =16 -> 16 | B56: =IFERROR(INDEX($U$55:$U$542, MATCH(LARGE($AK$55:$AK$542,A56), $AK$55:$AK$542, 0)), "") -> Song of the Mysteries | C56: =IFERROR(INDEX($V$55:$V$542, MATCH(LARGE($AK$55:$AK$542,A56), $AK$55:$AK$542, 0)), "") -> Janny Wurts | D56: =IFERROR(INDEX($W$55:$W$542, MATCH(LARGE($AK$55:$AK$542,A56), $AK$55:$AK$542, 0)), "") -> Epic Fantasy | E56: =IFERROR(INDEX($Y$55:$Y$542, MATCH(LARGE($AK$55:$AK$542,A56), $AK$55:$AK$542, 0)), "") -> 341000 | F56: =IFERROR(ROUND(INDEX($AF$55:$AF$542, MATCH(LARGE($AK$55:$AK$542,A56), $AK$55:$AK$542, 0)),2), "") -> 8.83 | G56: =IFERROR(INDEX($T$55:$T$542, MATCH(LARGE($AK$55:$AK$542,A56), $AK$55:$AK$542, 0)), "") -> 22 | H56: =IFERROR(INDEX($X$55:$X$542, MATCH(LARGE($AK$55:$AK$542,A56), $AK$55:$AK$542, 0)), "") -> The Wars of Light and Shadow | I56: =IFERROR(_xlfn.XLOOKUP(B56,$U$55:$U$542,$AH$55:$AH$542),"") -> The 30-year capstone to The Wars of Light and Shadow — a dense, lyrical epic-fantasy finale that peaks exactly where the series always has: ornate Prose (9.1), deep Worldbuilding (9.1–9.2), rich Theme (9.1–9.2), and a long-arc Ending (9.0) that reviewers say surpasses expectations. Closest analog is your own late-series peak (Stormed Fortress / Destiny's Conflict, ~8.7–8.8); it should sit at the very top of the series. Confidence caveat: Pacing (predicted 6.4) is the highest-risk score — billed as the 'densest WoLaS book yet', it could land as low as 5.5 for some readers. | J56: =IFERROR(_xlfn.XLOOKUP(B56,$U$55:$U$542,$AI$55:$AI$542),"") -> epic fantasy, war, magic, prose-heavy, sprawling, intricate, climactic | K56: =IF($B56="",FALSE,IFERROR(_xlfn.XLOOKUP($B56,Recommendations!$D:$D,Recommendations!$AJ:$AJ),FALSE)) -> FALSE | L56: =IF($B56="",FALSE,OR($K56=TRUE,$B56=BookTracker!$B$9)) -> FALSE | N56: {=IF(INDEX($P:$P,ROW()-1)="","",IF(OR(IFERROR(_xlfn.XLOOKUP(INDEX($P:$P,ROW()-1),Recommendations!$D:$D,Recommendations!$AJ:$AJ),FALSE)=TRUE,INDEX($P:$P,ROW()-1)=BookTracker!$B$9),"",ROW()-1))} | O56: The Dagger and the Coin | T56: =IFERROR(_xlfn.XLOOKUP(U56,Recommendations!$D:$D,Recommendations!$A:$A),"") -> 29 | U56: {=IFERROR(INDEX(Recommendations!$D:$D,SMALL($AL$2:$AL$488,ROW()-55)),"")} -> A Game of Thrones | V56: =IFERROR(_xlfn.XLOOKUP(U56,Recommendations!$D:$D,Recommendations!$F:$F),"") -> George R.R. Martin | W56: =IFERROR(_xlfn.XLOOKUP(U56,Recommendations!$D:$D,Recommendations!$E:$E),"") -> Epic Fantasy | X56: =IFERROR(_xlfn.XLOOKUP(U56,Recommendations!$D:$D,Recommendations!$G:$G),"") -> A Song of Ice and Fire | Y56: =IFERROR(_xlfn.XLOOKUP(U56,Recommendations!$D:$D,Recommendations!$H:$H),"") -> 298000 | Z56: =IF($U56="","",IFERROR(AVERAGE(INDEX(Recommendations!$K:$K,$AM56),INDEX(Recommendations!$I:$I,$AM56),INDEX(Recommendations!$J:$J,$AM56)),0)) -> 8.3366667 | AA56: =IF($U56="","",IFERROR(AVERAGE(INDEX(Recommendations!$X:$X,$AM56),INDEX(Recommendations!$Y:$Y,$AM56)),0)) -> 8.4 | AB56: =IF($U56="","",IFERROR(AVERAGE(INDEX(Recommendations!$P:$P,$AM56),INDEX(Recommendations!$O:$O,$AM56),INDEX(Recommendations!$R:$R,$AM56)),0)) -> 8.6333333 | AC56: =IF($U56="","",IFERROR(AVERAGE(INDEX(Recommendations!$AB:$AB,$AM56),INDEX(Recommendations!$AD:$AD,$AM56),INDEX(Recommendations!$T:$T,$AM56)),0)) -> 8.5333333 | AD56: =IF($U56="","",IFERROR(AVERAGE(INDEX(Recommendations!$I:$I,$AM56),INDEX(Recommendations!$L:$L,$AM56),INDEX(Recommendations!$J:$J,$AM56)),0)) -> 8.7033333 | AE56: =IF($U56="","",IFERROR(AVERAGE(INDEX(Recommendations!$O:$O,$AM56),INDEX(Recommendations!$Q:$Q,$AM56)),0)) -> 8.55 | AF56: {=IF($U56="","",IFERROR(IF(SUM($B$24:$B$29)=0,INDEX(Recommendations!$B:$B,$AM56),(Z56*$B$24+AA56*$B$25+AB56*$B$26+AC56*$B$27+AD56*$B$28+AE56*$B$29)/SUM($B$24:$B$29)),0))} -> 8.5288333 | AG56: =IFERROR(IF(ISNUMBER(AF56),IF(AF56=0,0,AF56+ROW()/10000000),0),0) -> 8.5288389 | AH56: =IFERROR(_xlfn.XLOOKUP(U56,Recommendations!$D:$D,Recommendations!$AK:$AK),"") -> The series opener that defined modern grimdark political fantasy — seven POVs and a willingness to break hero conventions that reset reader expectations (Ending 8.7), with Westeros rendered in extraordinary depth (Originality 9.4, Insights 9.2). Closest stylistic analogs in your library are Erikson and Abercrombie, though Martin's intricate plotting is more grounded in political realism than either. Confidence caveat: Prose (7.8) is highest-risk — reviewers consistently call Martin's writing 'competent/workmanlike' rather than stylistically distinguished, which could drag the predicted WA below 8.48. | AI56: =IFERROR(_xlfn.XLOOKUP(U56,Recommendations!$D:$D,Recommendations!$AL:$AL),"") -> epic fantasy, political, multi-POV, grimdark, scheming, medieval, morally-grey, immersive | AJ56: =IF($B$37="",TRUE,IFERROR(ISNUMBER(SEARCH($B$37,AI56))+ISNUMBER(SEARCH($B$37,U56))+ISNUMBER(SEARCH($B$37,W56))>0,FALSE)) -> TRUE | AK56: =IFERROR(IF(AND(AJ56=TRUE,_xlfn.XLOOKUP(U56,Recommendations!$D:$D,Recommendations!$AJ:$AJ,FALSE)<>TRUE,IF($B$33="Any",TRUE,W56=$B$33),IF($B$34="Any",TRUE,IF($B$34="Short (<150K)",Y56<150000,IF($B$34="Medium (150-300K)",(Y56>=150000)*(Y56<=300000),Y56>300000))),IF($B$35="Any",TRUE,IF($B$35="Standalone",X56="Standalone",X56<>"Standalone")),IF($B$36="Any",TRUE,ISNUMBER(SEARCH($B$36,V56)))),IF(ISNUMBER(AF56),IF(AF56=0,0,AF56+ROW()/10000000),0),-ROW()/10000000),0) -> 8.5288389 | AL56: {=IF(INDEX(Recommendations!$D:$D,ROW())="","",IF(INDEX(Recommendations!$AJ:$AJ,ROW())=TRUE,"",ROW()))} -> 56 | AM56: =IF($U56="","",IFERROR(MATCH($U56,Recommendations!$D:$D,0),"")) -> 2
A57: =17 -> 17 | B57: =IFERROR(INDEX($U$55:$U$542, MATCH(LARGE($AK$55:$AK$542,A57), $AK$55:$AK$542, 0)), "") -> The Great Ordeal | C57: =IFERROR(INDEX($V$55:$V$542, MATCH(LARGE($AK$55:$AK$542,A57), $AK$55:$AK$542, 0)), "") -> R. Scott Bakker | D57: =IFERROR(INDEX($W$55:$W$542, MATCH(LARGE($AK$55:$AK$542,A57), $AK$55:$AK$542, 0)), "") -> Epic Fantasy | E57: =IFERROR(INDEX($Y$55:$Y$542, MATCH(LARGE($AK$55:$AK$542,A57), $AK$55:$AK$542, 0)), "") -> 350000 | F57: =IFERROR(ROUND(INDEX($AF$55:$AF$542, MATCH(LARGE($AK$55:$AK$542,A57), $AK$55:$AK$542, 0)),2), "") -> 8.82 | G57: =IFERROR(INDEX($T$55:$T$542, MATCH(LARGE($AK$55:$AK$542,A57), $AK$55:$AK$542, 0)), "") -> 22 | H57: =IFERROR(INDEX($X$55:$X$542, MATCH(LARGE($AK$55:$AK$542,A57), $AK$55:$AK$542, 0)), "") -> The Second Apocalypse | I57: =IFERROR(_xlfn.XLOOKUP(B57,$U$55:$U$542,$AH$55:$AH$542),"") -> Penultimate volume where Bakker pays out the deep lore — several long-seeded mysteries reach series-high set pieces. Originally half of the finale, so it reads as less self-contained, and one major POV thread is the weakest of the series. Confidence caveat: Pacing (predicted 6.8) is highest-risk — portions drag and the split-book structure left structural holes; could land 5.5–7.5. | J57: =IFERROR(_xlfn.XLOOKUP(B57,$U$55:$U$542,$AI$55:$AI$542),"") -> dark fantasy, journey, metaphysical, grim, dense, foreboding, immersive | K57: =IF($B57="",FALSE,IFERROR(_xlfn.XLOOKUP($B57,Recommendations!$D:$D,Recommendations!$AJ:$AJ),FALSE)) -> FALSE | L57: =IF($B57="",FALSE,OR($K57=TRUE,$B57=BookTracker!$B$9)) -> FALSE | N57: {=IF(INDEX($P:$P,ROW()-1)="","",IF(OR(IFERROR(_xlfn.XLOOKUP(INDEX($P:$P,ROW()-1),Recommendations!$D:$D,Recommendations!$AJ:$AJ),FALSE)=TRUE,INDEX($P:$P,ROW()-1)=BookTracker!$B$9),"",ROW()-1))} | O57: The Dandelion Dynasty | T57: =IFERROR(_xlfn.XLOOKUP(U57,Recommendations!$D:$D,Recommendations!$A:$A),"") -> 31 | U57: {=IFERROR(INDEX(Recommendations!$D:$D,SMALL($AL$2:$AL$488,ROW()-55)),"")} -> A Clash of Kings | V57: =IFERROR(_xlfn.XLOOKUP(U57,Recommendations!$D:$D,Recommendations!$F:$F),"") -> George R.R. Martin | W57: =IFERROR(_xlfn.XLOOKUP(U57,Recommendations!$D:$D,Recommendations!$E:$E),"") -> Epic Fantasy | X57: =IFERROR(_xlfn.XLOOKUP(U57,Recommendations!$D:$D,Recommendations!$G:$G),"") -> A Song of Ice and Fire | Y57: =IFERROR(_xlfn.XLOOKUP(U57,Recommendations!$D:$D,Recommendations!$H:$H),"") -> 326000 | Z57: =IF($U57="","",IFERROR(AVERAGE(INDEX(Recommendations!$K:$K,$AM57),INDEX(Recommendations!$I:$I,$AM57),INDEX(Recommendations!$J:$J,$AM57)),0)) -> 8.4333333 | AA57: =IF($U57="","",IFERROR(AVERAGE(INDEX(Recommendations!$X:$X,$AM57),INDEX(Recommendations!$Y:$Y,$AM57)),0)) -> 8.45 | AB57: =IF($U57="","",IFERROR(AVERAGE(INDEX(Recommendations!$P:$P,$AM57),INDEX(Recommendations!$O:$O,$AM57),INDEX(Recommendations!$R:$R,$AM57)),0)) -> 8.5444444 | AC57: =IF($U57="","",IFERROR(AVERAGE(INDEX(Recommendations!$AB:$AB,$AM57),INDEX(Recommendations!$AD:$AD,$AM57),INDEX(Recommendations!$T:$T,$AM57)),0)) -> 8.5333333 | AD57: =IF($U57="","",IFERROR(AVERAGE(INDEX(Recommendations!$I:$I,$AM57),INDEX(Recommendations!$L:$L,$AM57),INDEX(Recommendations!$J:$J,$AM57)),0)) -> 8.4 | AE57: =IF($U57="","",IFERROR(AVERAGE(INDEX(Recommendations!$O:$O,$AM57),INDEX(Recommendations!$Q:$Q,$AM57)),0)) -> 8.5 | AF57: {=IF($U57="","",IFERROR(IF(SUM($B$24:$B$29)=0,INDEX(Recommendations!$B:$B,$AM57),(Z57*$B$24+AA57*$B$25+AB57*$B$26+AC57*$B$27+AD57*$B$28+AE57*$B$29)/SUM($B$24:$B$29)),0))} -> 8.5183333 | AG57: =IFERROR(IF(ISNUMBER(AF57),IF(AF57=0,0,AF57+ROW()/10000000),0),0) -> 8.518339 | AH57: =IFERROR(_xlfn.XLOOKUP(U57,Recommendations!$D:$D,Recommendations!$AK:$AK),"") -> The scope expands across all Seven Kingdoms as five kings contest the Iron Throne. The War of the Five Kings is GRRM at his most strategically complex — action and pacing both rise significantly from Book 1. Less intimate than Game of Thrones but broader in sweep. Confidence caveat: Ending (7.8) lands as deliberate non-closure rather than resolution. | AI57: =IFERROR(_xlfn.XLOOKUP(U57,Recommendations!$D:$D,Recommendations!$AL:$AL),"") -> epic fantasy, political, war, multi-POV, grimdark, betrayal, sprawling, tense | AJ57: =IF($B$37="",TRUE,IFERROR(ISNUMBER(SEARCH($B$37,AI57))+ISNUMBER(SEARCH($B$37,U57))+ISNUMBER(SEARCH($B$37,W57))>0,FALSE)) -> TRUE | AK57: =IFERROR(IF(AND(AJ57=TRUE,_xlfn.XLOOKUP(U57,Recommendations!$D:$D,Recommendations!$AJ:$AJ,FALSE)<>TRUE,IF($B$33="Any",TRUE,W57=$B$33),IF($B$34="Any",TRUE,IF($B$34="Short (<150K)",Y57<150000,IF($B$34="Medium (150-300K)",(Y57>=150000)*(Y57<=300000),Y57>300000))),IF($B$35="Any",TRUE,IF($B$35="Standalone",X57="Standalone",X57<>"Standalone")),IF($B$36="Any",TRUE,ISNUMBER(SEARCH($B$36,V57)))),IF(ISNUMBER(AF57),IF(AF57=0,0,AF57+ROW()/10000000),0),-ROW()/10000000),0) -> 8.518339 | AL57: {=IF(INDEX(Recommendations!$D:$D,ROW())="","",IF(INDEX(Recommendations!$AJ:$AJ,ROW())=TRUE,"",ROW()))} -> 57 | AM57: =IF($U57="","",IFERROR(MATCH($U57,Recommendations!$D:$D,0),"")) -> 3
A58: =18 -> 18 | B58: =IFERROR(INDEX($U$55:$U$542, MATCH(LARGE($AK$55:$AK$542,A58), $AK$55:$AK$542, 0)), "") -> City of Blades | C58: =IFERROR(INDEX($V$55:$V$542, MATCH(LARGE($AK$55:$AK$542,A58), $AK$55:$AK$542, 0)), "") -> Robert Jackson Bennett | D58: =IFERROR(INDEX($W$55:$W$542, MATCH(LARGE($AK$55:$AK$542,A58), $AK$55:$AK$542, 0)), "") -> Epic Fantasy | E58: =IFERROR(INDEX($Y$55:$Y$542, MATCH(LARGE($AK$55:$AK$542,A58), $AK$55:$AK$542, 0)), "") -> 165000 | F58: =IFERROR(ROUND(INDEX($AF$55:$AF$542, MATCH(LARGE($AK$55:$AK$542,A58), $AK$55:$AK$542, 0)),2), "") -> 8.81 | G58: =IFERROR(INDEX($T$55:$T$542, MATCH(LARGE($AK$55:$AK$542,A58), $AK$55:$AK$542, 0)), "") -> 16 | H58: =IFERROR(INDEX($X$55:$X$542, MATCH(LARGE($AK$55:$AK$542,A58), $AK$55:$AK$542, 0)), "") -> The Divine Cities | I58: =IFERROR(_xlfn.XLOOKUP(B58,$U$55:$U$542,$AH$55:$AH$542),"") -> The trilogy peak per consensus — Mulaghesh POV as a career soldier confronting what war owes the dead, in the tradition of Bakker's philosophical density crossed with the gut-punch of Toll the Hounds (9.72). Predicted Total Avg 8.73 → Rank ~14 of 116, with Theme (9.23) and Character (8.75) both hitting peaks; Mulaghesh is one of the most complete characters in modern fantasy. Confidence caveat: Multi-Dimensionality (8.0) is the structural limit — tight ensemble vs the sprawling casts that hit 9+ for you; Originality (8.5) dips as the world is no longer novel. | J58: =IFERROR(_xlfn.XLOOKUP(B58,$U$55:$U$542,$AI$55:$AI$542),"") -> silkpunk, finale, war, sweeping, resolution, generational, climactic | K58: =IF($B58="",FALSE,IFERROR(_xlfn.XLOOKUP($B58,Recommendations!$D:$D,Recommendations!$AJ:$AJ),FALSE)) -> FALSE | L58: =IF($B58="",FALSE,OR($K58=TRUE,$B58=BookTracker!$B$9)) -> FALSE | N58: {=IF(INDEX($P:$P,ROW()-1)="","",IF(OR(IFERROR(_xlfn.XLOOKUP(INDEX($P:$P,ROW()-1),Recommendations!$D:$D,Recommendations!$AJ:$AJ),FALSE)=TRUE,INDEX($P:$P,ROW()-1)=BookTracker!$B$9),"",ROW()-1))} | O58: The Demon Cycle | T58: =IFERROR(_xlfn.XLOOKUP(U58,Recommendations!$D:$D,Recommendations!$A:$A),"") -> 13 | U58: {=IFERROR(INDEX(Recommendations!$D:$D,SMALL($AL$2:$AL$488,ROW()-55)),"")} -> A Storm of Swords | V58: =IFERROR(_xlfn.XLOOKUP(U58,Recommendations!$D:$D,Recommendations!$F:$F),"") -> George R.R. Martin | W58: =IFERROR(_xlfn.XLOOKUP(U58,Recommendations!$D:$D,Recommendations!$E:$E),"") -> Epic Fantasy | X58: =IFERROR(_xlfn.XLOOKUP(U58,Recommendations!$D:$D,Recommendations!$G:$G),"") -> A Song of Ice and Fire | Y58: =IFERROR(_xlfn.XLOOKUP(U58,Recommendations!$D:$D,Recommendations!$H:$H),"") -> 424000 | Z58: =IF($U58="","",IFERROR(AVERAGE(INDEX(Recommendations!$K:$K,$AM58),INDEX(Recommendations!$I:$I,$AM58),INDEX(Recommendations!$J:$J,$AM58)),0)) -> 9.0566667 | AA58: =IF($U58="","",IFERROR(AVERAGE(INDEX(Recommendations!$X:$X,$AM58),INDEX(Recommendations!$Y:$Y,$AM58)),0)) -> 8.75 | AB58: =IF($U58="","",IFERROR(AVERAGE(INDEX(Recommendations!$P:$P,$AM58),INDEX(Recommendations!$O:$O,$AM58),INDEX(Recommendations!$R:$R,$AM58)),0)) -> 9.0111111 | AC58: =IF($U58="","",IFERROR(AVERAGE(INDEX(Recommendations!$AB:$AB,$AM58),INDEX(Recommendations!$AD:$AD,$AM58),INDEX(Recommendations!$T:$T,$AM58)),0)) -> 8.6666667 | AD58: =IF($U58="","",IFERROR(AVERAGE(INDEX(Recommendations!$I:$I,$AM58),INDEX(Recommendations!$L:$L,$AM58),INDEX(Recommendations!$J:$J,$AM58)),0)) -> 9.2566667 | AE58: =IF($U58="","",IFERROR(AVERAGE(INDEX(Recommendations!$O:$O,$AM58),INDEX(Recommendations!$Q:$Q,$AM58)),0)) -> 8.8 | AF58: {=IF($U58="","",IFERROR(IF(SUM($B$24:$B$29)=0,INDEX(Recommendations!$B:$B,$AM58),(Z58*$B$24+AA58*$B$25+AB58*$B$26+AC58*$B$27+AD58*$B$28+AE58*$B$29)/SUM($B$24:$B$29)),0))} -> 8.8618333 | AG58: =IFERROR(IF(ISNUMBER(AF58),IF(AF58=0,0,AF58+ROW()/10000000),0),0) -> 8.8618391 | AH58: =IFERROR(_xlfn.XLOOKUP(U58,Recommendations!$D:$D,Recommendations!$AK:$AK),"") -> The series peak — more shocking, momentum-shifting set pieces per page than any other fantasy novel in this list. Ending at 9.5 is the highest in the series; prose and worldbuilding also hit series highs. Nearly 200k words longer than Book 1 but not a page feels wasted. The definitive case for ASOIAF as high literary fantasy. | AI58: =IFERROR(_xlfn.XLOOKUP(U58,Recommendations!$D:$D,Recommendations!$AL:$AL),"") -> epic fantasy, political, brutal, multi-POV, shocking, war, morally-grey, gripping | AJ58: =IF($B$37="",TRUE,IFERROR(ISNUMBER(SEARCH($B$37,AI58))+ISNUMBER(SEARCH($B$37,U58))+ISNUMBER(SEARCH($B$37,W58))>0,FALSE)) -> TRUE | AK58: =IFERROR(IF(AND(AJ58=TRUE,_xlfn.XLOOKUP(U58,Recommendations!$D:$D,Recommendations!$AJ:$AJ,FALSE)<>TRUE,IF($B$33="Any",TRUE,W58=$B$33),IF($B$34="Any",TRUE,IF($B$34="Short (<150K)",Y58<150000,IF($B$34="Medium (150-300K)",(Y58>=150000)*(Y58<=300000),Y58>300000))),IF($B$35="Any",TRUE,IF($B$35="Standalone",X58="Standalone",X58<>"Standalone")),IF($B$36="Any",TRUE,ISNUMBER(SEARCH($B$36,V58)))),IF(ISNUMBER(AF58),IF(AF58=0,0,AF58+ROW()/10000000),0),-ROW()/10000000),0) -> 8.8618391 | AL58: {=IF(INDEX(Recommendations!$D:$D,ROW())="","",IF(INDEX(Recommendations!$AJ:$AJ,ROW())=TRUE,"",ROW()))} -> 58 | AM58: =IF($U58="","",IFERROR(MATCH($U58,Recommendations!$D:$D,0),"")) -> 4
A59: =19 -> 19 | B59: =IFERROR(INDEX($U$55:$U$542, MATCH(LARGE($AK$55:$AK$542,A59), $AK$55:$AK$542, 0)), "") -> Destiny's Conflict | C59: =IFERROR(INDEX($V$55:$V$542, MATCH(LARGE($AK$55:$AK$542,A59), $AK$55:$AK$542, 0)), "") -> Janny Wurts | D59: =IFERROR(INDEX($W$55:$W$542, MATCH(LARGE($AK$55:$AK$542,A59), $AK$55:$AK$542, 0)), "") -> Epic Fantasy | E59: =IFERROR(INDEX($Y$55:$Y$542, MATCH(LARGE($AK$55:$AK$542,A59), $AK$55:$AK$542, 0)), "") -> 189000 | F59: =IFERROR(ROUND(INDEX($AF$55:$AF$542, MATCH(LARGE($AK$55:$AK$542,A59), $AK$55:$AK$542, 0)),2), "") -> 8.8 | G59: =IFERROR(INDEX($T$55:$T$542, MATCH(LARGE($AK$55:$AK$542,A59), $AK$55:$AK$542, 0)), "") -> 23 | H59: =IFERROR(INDEX($X$55:$X$542, MATCH(LARGE($AK$55:$AK$542,A59), $AK$55:$AK$542, 0)), "") -> Wars of Light and Shadow | I59: =IFERROR(_xlfn.XLOOKUP(B59,$U$55:$U$542,$AH$55:$AH$542),"") -> Whirlwind action-and-revelation second half of Arc 4 — staggering reveals, wide sweep of events, emotionally raw. Shorter than most entries but dense. Strong arc conclusion. Confidence caveat: Thought-Provokingness (predicted 9.2) is highest-risk — series thematic peak; could land 8.6–9.5 depending on how revelations land. | J59: =IFERROR(_xlfn.XLOOKUP(B59,$U$55:$U$542,$AI$55:$AI$542),"") -> epic fantasy, siege, war, prose-heavy, climactic, intense, intricate | K59: =IF($B59="",FALSE,IFERROR(_xlfn.XLOOKUP($B59,Recommendations!$D:$D,Recommendations!$AJ:$AJ),FALSE)) -> FALSE | L59: =IF($B59="",FALSE,OR($K59=TRUE,$B59=BookTracker!$B$9)) -> FALSE | N59: {=IF(INDEX($P:$P,ROW()-1)="","",IF(OR(IFERROR(_xlfn.XLOOKUP(INDEX($P:$P,ROW()-1),Recommendations!$D:$D,Recommendations!$AJ:$AJ),FALSE)=TRUE,INDEX($P:$P,ROW()-1)=BookTracker!$B$9),"",ROW()-1))} | O59: The Divine Cities | T59: =IFERROR(_xlfn.XLOOKUP(U59,Recommendations!$D:$D,Recommendations!$A:$A),"") -> 45 | U59: {=IFERROR(INDEX(Recommendations!$D:$D,SMALL($AL$2:$AL$488,ROW()-55)),"")} -> A Feast for Crows | V59: =IFERROR(_xlfn.XLOOKUP(U59,Recommendations!$D:$D,Recommendations!$F:$F),"") -> George R.R. Martin | W59: =IFERROR(_xlfn.XLOOKUP(U59,Recommendations!$D:$D,Recommendations!$E:$E),"") -> Epic Fantasy | X59: =IFERROR(_xlfn.XLOOKUP(U59,Recommendations!$D:$D,Recommendations!$G:$G),"") -> A Song of Ice and Fire | Y59: =IFERROR(_xlfn.XLOOKUP(U59,Recommendations!$D:$D,Recommendations!$H:$H),"") -> 300000 | Z59: =IF($U59="","",IFERROR(AVERAGE(INDEX(Recommendations!$K:$K,$AM59),INDEX(Recommendations!$I:$I,$AM59),INDEX(Recommendations!$J:$J,$AM59)),0)) -> 6.7266667 | AA59: =IF($U59="","",IFERROR(AVERAGE(INDEX(Recommendations!$X:$X,$AM59),INDEX(Recommendations!$Y:$Y,$AM59)),0)) -> 8.95 | AB59: =IF($U59="","",IFERROR(AVERAGE(INDEX(Recommendations!$P:$P,$AM59),INDEX(Recommendations!$O:$O,$AM59),INDEX(Recommendations!$R:$R,$AM59)),0)) -> 8.5111111 | AC59: =IF($U59="","",IFERROR(AVERAGE(INDEX(Recommendations!$AB:$AB,$AM59),INDEX(Recommendations!$AD:$AD,$AM59),INDEX(Recommendations!$T:$T,$AM59)),0)) -> 8.5666667 | AD59: =IF($U59="","",IFERROR(AVERAGE(INDEX(Recommendations!$I:$I,$AM59),INDEX(Recommendations!$L:$L,$AM59),INDEX(Recommendations!$J:$J,$AM59)),0)) -> 7.2266667 | AE59: =IF($U59="","",IFERROR(AVERAGE(INDEX(Recommendations!$O:$O,$AM59),INDEX(Recommendations!$Q:$Q,$AM59)),0)) -> 8.7 | AF59: {=IF($U59="","",IFERROR(IF(SUM($B$24:$B$29)=0,INDEX(Recommendations!$B:$B,$AM59),(Z59*$B$24+AA59*$B$25+AB59*$B$26+AC59*$B$27+AD59*$B$28+AE59*$B$29)/SUM($B$24:$B$29)),0))} -> 8.3356667 | AG59: =IFERROR(IF(ISNUMBER(AF59),IF(AF59=0,0,AF59+ROW()/10000000),0),0) -> 8.3356726 | AH59: =IFERROR(_xlfn.XLOOKUP(U59,Recommendations!$D:$D,Recommendations!$AK:$AK),"") -> The deliberate, politics-first volume of the series — character study and aftermath over momentum, with the series' usual peak prose and POV depth. Closest shelf analog: the slower middle volumes of Wars of Light and Shadow. Re-predicted 2026-06: Pacing/Action lowered to match the broad reader consensus that this is the slow book; Pacing (6.8) is highest-risk — if its quieter arcs land for you, this could read a half-point high. Sources: cbr.com, worstgen forum ranking thread. | AI59: =IFERROR(_xlfn.XLOOKUP(U59,Recommendations!$D:$D,Recommendations!$AL:$AL),"") -> epic fantasy, political, slow, multi-POV, fragmented, intrigue, somber, transitional | AJ59: =IF($B$37="",TRUE,IFERROR(ISNUMBER(SEARCH($B$37,AI59))+ISNUMBER(SEARCH($B$37,U59))+ISNUMBER(SEARCH($B$37,W59))>0,FALSE)) -> TRUE | AK59: =IFERROR(IF(AND(AJ59=TRUE,_xlfn.XLOOKUP(U59,Recommendations!$D:$D,Recommendations!$AJ:$AJ,FALSE)<>TRUE,IF($B$33="Any",TRUE,W59=$B$33),IF($B$34="Any",TRUE,IF($B$34="Short (<150K)",Y59<150000,IF($B$34="Medium (150-300K)",(Y59>=150000)*(Y59<=300000),Y59>300000))),IF($B$35="Any",TRUE,IF($B$35="Standalone",X59="Standalone",X59<>"Standalone")),IF($B$36="Any",TRUE,ISNUMBER(SEARCH($B$36,V59)))),IF(ISNUMBER(AF59),IF(AF59=0,0,AF59+ROW()/10000000),0),-ROW()/10000000),0) -> 8.3356726 | AL59: {=IF(INDEX(Recommendations!$D:$D,ROW())="","",IF(INDEX(Recommendations!$AJ:$AJ,ROW())=TRUE,"",ROW()))} -> 59 | AM59: =IF($U59="","",IFERROR(MATCH($U59,Recommendations!$D:$D,0),"")) -> 5
A60: =20 -> 20 | B60: =IFERROR(INDEX($U$55:$U$542, MATCH(LARGE($AK$55:$AK$542,A60), $AK$55:$AK$542, 0)), "") -> Forge of Darkness | C60: =IFERROR(INDEX($V$55:$V$542, MATCH(LARGE($AK$55:$AK$542,A60), $AK$55:$AK$542, 0)), "") -> Steven Erikson | D60: =IFERROR(INDEX($W$55:$W$542, MATCH(LARGE($AK$55:$AK$542,A60), $AK$55:$AK$542, 0)), "") -> Epic Fantasy | E60: =IFERROR(INDEX($Y$55:$Y$542, MATCH(LARGE($AK$55:$AK$542,A60), $AK$55:$AK$542, 0)), "") -> 293000 | F60: =IFERROR(ROUND(INDEX($AF$55:$AF$542, MATCH(LARGE($AK$55:$AK$542,A60), $AK$55:$AK$542, 0)),2), "") -> 8.79 | G60: =IFERROR(INDEX($T$55:$T$542, MATCH(LARGE($AK$55:$AK$542,A60), $AK$55:$AK$542, 0)), "") -> 35 | H60: =IFERROR(INDEX($X$55:$X$542, MATCH(LARGE($AK$55:$AK$542,A60), $AK$55:$AK$542, 0)), "") -> Kharkanas | I60: =IFERROR(_xlfn.XLOOKUP(B60,$U$55:$U$542,$AH$55:$AH$542),"") -> Erikson's most literary work — a Tiste prequel meditating on the fall of Kharkanas through some of the most beautiful, philosophical prose in the genre. Closest analog: Toll the Hounds + Dust of Dreams — exceptional Prose (9.3) / Themes (9.4) / WB (9.4), weak Plot/Pacing/Ending. Confidence caveat: Ending (7.2) is highest-risk — Forge's cliffhanger split readers (could land 5.5–8.0); the floor on Pacing (6.8) is real. | J60: =IFERROR(_xlfn.XLOOKUP(B60,$U$55:$U$542,$AI$55:$AI$542),"") -> grimdark, political, war, dark, brutal, scheming, mythic, gritty | K60: =IF($B60="",FALSE,IFERROR(_xlfn.XLOOKUP($B60,Recommendations!$D:$D,Recommendations!$AJ:$AJ),FALSE)) -> FALSE | L60: =IF($B60="",FALSE,OR($K60=TRUE,$B60=BookTracker!$B$9)) -> FALSE | N60: {=IF(INDEX($P:$P,ROW()-1)="","",IF(OR(IFERROR(_xlfn.XLOOKUP(INDEX($P:$P,ROW()-1),Recommendations!$D:$D,Recommendations!$AJ:$AJ),FALSE)=TRUE,INDEX($P:$P,ROW()-1)=BookTracker!$B$9),"",ROW()-1))} | O60: The Dresden Files | T60: =IFERROR(_xlfn.XLOOKUP(U60,Recommendations!$D:$D,Recommendations!$A:$A),"") -> 38 | U60: {=IFERROR(INDEX(Recommendations!$D:$D,SMALL($AL$2:$AL$488,ROW()-55)),"")} -> A Dance with Dragons | V60: =IFERROR(_xlfn.XLOOKUP(U60,Recommendations!$D:$D,Recommendations!$F:$F),"") -> George R.R. Martin | W60: =IFERROR(_xlfn.XLOOKUP(U60,Recommendations!$D:$D,Recommendations!$E:$E),"") -> Epic Fantasy | X60: =IFERROR(_xlfn.XLOOKUP(U60,Recommendations!$D:$D,Recommendations!$G:$G),"") -> A Song of Ice and Fire | Y60: =IFERROR(_xlfn.XLOOKUP(U60,Recommendations!$D:$D,Recommendations!$H:$H),"") -> 422000 | Z60: =IF($U60="","",IFERROR(AVERAGE(INDEX(Recommendations!$K:$K,$AM60),INDEX(Recommendations!$I:$I,$AM60),INDEX(Recommendations!$J:$J,$AM60)),0)) -> 7.4433333 | AA60: =IF($U60="","",IFERROR(AVERAGE(INDEX(Recommendations!$X:$X,$AM60),INDEX(Recommendations!$Y:$Y,$AM60)),0)) -> 8.7 | AB60: =IF($U60="","",IFERROR(AVERAGE(INDEX(Recommendations!$P:$P,$AM60),INDEX(Recommendations!$O:$O,$AM60),INDEX(Recommendations!$R:$R,$AM60)),0)) -> 8.6444444 | AC60: =IF($U60="","",IFERROR(AVERAGE(INDEX(Recommendations!$AB:$AB,$AM60),INDEX(Recommendations!$AD:$AD,$AM60),INDEX(Recommendations!$T:$T,$AM60)),0)) -> 8.6 | AD60: =IF($U60="","",IFERROR(AVERAGE(INDEX(Recommendations!$I:$I,$AM60),INDEX(Recommendations!$L:$L,$AM60),INDEX(Recommendations!$J:$J,$AM60)),0)) -> 7.8766667 | AE60: =IF($U60="","",IFERROR(AVERAGE(INDEX(Recommendations!$O:$O,$AM60),INDEX(Recommendations!$Q:$Q,$AM60)),0)) -> 8.7 | AF60: {=IF($U60="","",IFERROR(IF(SUM($B$24:$B$29)=0,INDEX(Recommendations!$B:$B,$AM60),(Z60*$B$24+AA60*$B$25+AB60*$B$26+AC60*$B$27+AD60*$B$28+AE60*$B$29)/SUM($B$24:$B$29)),0))} -> 8.4615 | AG60: =IFERROR(IF(ISNUMBER(AF60),IF(AF60=0,0,AF60+ROW()/10000000),0),0) -> 8.461506 | AH60: =IFERROR(_xlfn.XLOOKUP(U60,Recommendations!$D:$D,Recommendations!$AK:$AK),"") -> Jon, Tyrion, and Dany POVs return after their absence in Feast for Crows. The Emotional Impact ceiling (9.4) and highest Character scores in the series reflect extraordinary depth of interiority. Plot momentum stalls in the middle (7.3 pacing), but Tyrion's chapters are the finest writing GRRM has done. Confidence caveat: Ending (8.8) is divisive — the cliffhangers feel either thrilling or infuriating depending on patience for the wait. | AI60: =IFERROR(_xlfn.XLOOKUP(U60,Recommendations!$D:$D,Recommendations!$AL:$AL),"") -> epic fantasy, political, sprawling, multi-POV, slow-burn, brooding, complex, atmospheric | AJ60: =IF($B$37="",TRUE,IFERROR(ISNUMBER(SEARCH($B$37,AI60))+ISNUMBER(SEARCH($B$37,U60))+ISNUMBER(SEARCH($B$37,W60))>0,FALSE)) -> TRUE | AK60: =IFERROR(IF(AND(AJ60=TRUE,_xlfn.XLOOKUP(U60,Recommendations!$D:$D,Recommendations!$AJ:$AJ,FALSE)<>TRUE,IF($B$33="Any",TRUE,W60=$B$33),IF($B$34="Any",TRUE,IF($B$34="Short (<150K)",Y60<150000,IF($B$34="Medium (150-300K)",(Y60>=150000)*(Y60<=300000),Y60>300000))),IF($B$35="Any",TRUE,IF($B$35="Standalone",X60="Standalone",X60<>"Standalone")),IF($B$36="Any",TRUE,ISNUMBER(SEARCH($B$36,V60)))),IF(ISNUMBER(AF60),IF(AF60=0,0,AF60+ROW()/10000000),0),-ROW()/10000000),0) -> 8.461506 | AL60: {=IF(INDEX(Recommendations!$D:$D,ROW())="","",IF(INDEX(Recommendations!$AJ:$AJ,ROW())=TRUE,"",ROW()))} -> 60 | AM60: =IF($U60="","",IFERROR(MATCH($U60,Recommendations!$D:$D,0),"")) -> 6
A61: =21 -> 21 | B61: =IFERROR(INDEX($U$55:$U$542, MATCH(LARGE($AK$55:$AK$542,A61), $AK$55:$AK$542, 0)), "") -> The Thousandfold Thought | C61: =IFERROR(INDEX($V$55:$V$542, MATCH(LARGE($AK$55:$AK$542,A61), $AK$55:$AK$542, 0)), "") -> R. Scott Bakker | D61: =IFERROR(INDEX($W$55:$W$542, MATCH(LARGE($AK$55:$AK$542,A61), $AK$55:$AK$542, 0)), "") -> Epic Fantasy | E61: =IFERROR(INDEX($Y$55:$Y$542, MATCH(LARGE($AK$55:$AK$542,A61), $AK$55:$AK$542, 0)), "") -> 230000 | F61: =IFERROR(ROUND(INDEX($AF$55:$AF$542, MATCH(LARGE($AK$55:$AK$542,A61), $AK$55:$AK$542, 0)),2), "") -> 8.77 | G61: =IFERROR(INDEX($T$55:$T$542, MATCH(LARGE($AK$55:$AK$542,A61), $AK$55:$AK$542, 0)), "") -> 24 | H61: =IFERROR(INDEX($X$55:$X$542, MATCH(LARGE($AK$55:$AK$542,A61), $AK$55:$AK$542, 0)), "") -> The Second Apocalypse | I61: =IFERROR(_xlfn.XLOOKUP(B61,$U$55:$U$542,$AH$55:$AH$542),"") -> Trilogy closer where the storming of Shimeh and Kellhus/Moënghus confrontation deliver, but the titular concept and many plot threads go unresolved by design (setup for Aspect-Emperor). Strong Depth and Theme, weaker Ending vs the build-up. Confidence caveat: Ending (predicted 7.4) is highest-risk — community is sharply split between 'best closing ever' and 'lacklustre/anticlimax'; could land 6.0–8.5. | J61: =IFERROR(_xlfn.XLOOKUP(B61,$U$55:$U$542,$AI$55:$AI$542),"") -> dark fantasy, philosophical, dense, war, grimdark, cerebral, bleak, unsettling | K61: =IF($B61="",FALSE,IFERROR(_xlfn.XLOOKUP($B61,Recommendations!$D:$D,Recommendations!$AJ:$AJ),FALSE)) -> FALSE | L61: =IF($B61="",FALSE,OR($K61=TRUE,$B61=BookTracker!$B$9)) -> FALSE | N61: {=IF(INDEX($P:$P,ROW()-1)="","",IF(OR(IFERROR(_xlfn.XLOOKUP(INDEX($P:$P,ROW()-1),Recommendations!$D:$D,Recommendations!$AJ:$AJ),FALSE)=TRUE,INDEX($P:$P,ROW()-1)=BookTracker!$B$9),"",ROW()-1))} | O61: The Empire Trilogy | T61: =IFERROR(_xlfn.XLOOKUP(U61,Recommendations!$D:$D,Recommendations!$A:$A),"") -> 51 | U61: {=IFERROR(INDEX(Recommendations!$D:$D,SMALL($AL$2:$AL$488,ROW()-55)),"")} -> The Daughters' War | V61: =IFERROR(_xlfn.XLOOKUP(U61,Recommendations!$D:$D,Recommendations!$F:$F),"") -> Christopher Buehlman | W61: =IFERROR(_xlfn.XLOOKUP(U61,Recommendations!$D:$D,Recommendations!$E:$E),"") -> Epic Fantasy | X61: =IFERROR(_xlfn.XLOOKUP(U61,Recommendations!$D:$D,Recommendations!$G:$G),"") -> Blacktongue | Y61: =IFERROR(_xlfn.XLOOKUP(U61,Recommendations!$D:$D,Recommendations!$H:$H),"") -> 140000 | Z61: =IF($U61="","",IFERROR(AVERAGE(INDEX(Recommendations!$K:$K,$AM61),INDEX(Recommendations!$I:$I,$AM61),INDEX(Recommendations!$J:$J,$AM61)),0)) -> 7.8066667 | AA61: =IF($U61="","",IFERROR(AVERAGE(INDEX(Recommendations!$X:$X,$AM61),INDEX(Recommendations!$Y:$Y,$AM61)),0)) -> 7.6 | AB61: =IF($U61="","",IFERROR(AVERAGE(INDEX(Recommendations!$P:$P,$AM61),INDEX(Recommendations!$O:$O,$AM61),INDEX(Recommendations!$R:$R,$AM61)),0)) -> 8.3111111 | AC61: =IF($U61="","",IFERROR(AVERAGE(INDEX(Recommendations!$AB:$AB,$AM61),INDEX(Recommendations!$AD:$AD,$AM61),INDEX(Recommendations!$T:$T,$AM61)),0)) -> 8.4666667 | AD61: =IF($U61="","",IFERROR(AVERAGE(INDEX(Recommendations!$I:$I,$AM61),INDEX(Recommendations!$L:$L,$AM61),INDEX(Recommendations!$J:$J,$AM61)),0)) -> 7.64 | AE61: =IF($U61="","",IFERROR(AVERAGE(INDEX(Recommendations!$O:$O,$AM61),INDEX(Recommendations!$Q:$Q,$AM61)),0)) -> 8.15 | AF61: {=IF($U61="","",IFERROR(IF(SUM($B$24:$B$29)=0,INDEX(Recommendations!$B:$B,$AM61),(Z61*$B$24+AA61*$B$25+AB61*$B$26+AC61*$B$27+AD61*$B$28+AE61*$B$29)/SUM($B$24:$B$29)),0))} -> 8.131 | AG61: =IFERROR(IF(ISNUMBER(AF61),IF(AF61=0,0,AF61+ROW()/10000000),0),0) -> 8.1310061 | AH61: =IFERROR(_xlfn.XLOOKUP(U61,Recommendations!$D:$D,Recommendations!$AK:$AK),"") -> A grimmer, war-focused prequel to The Blacktongue Thief — trades the opener's roguish voice for darker military fantasy, with Buehlman's prose (predicted strongest dimension) intact. Analog: your Abercrombie grimdark tier crossed with the Thief's craft. Confidence caveat: Entertainment (predicted 8.0) is highest-risk — a bleaker tone may cost the breezy charm that lifts the first book, range 7.0–8.3. | AI61: =IFERROR(_xlfn.XLOOKUP(U61,Recommendations!$D:$D,Recommendations!$AL:$AL),"") -> heist, dark humor, sharp prose, road journey, roguish, secondary world, voice-driven | AJ61: =IF($B$37="",TRUE,IFERROR(ISNUMBER(SEARCH($B$37,AI61))+ISNUMBER(SEARCH($B$37,U61))+ISNUMBER(SEARCH($B$37,W61))>0,FALSE)) -> TRUE | AK61: =IFERROR(IF(AND(AJ61=TRUE,_xlfn.XLOOKUP(U61,Recommendations!$D:$D,Recommendations!$AJ:$AJ,FALSE)<>TRUE,IF($B$33="Any",TRUE,W61=$B$33),IF($B$34="Any",TRUE,IF($B$34="Short (<150K)",Y61<150000,IF($B$34="Medium (150-300K)",(Y61>=150000)*(Y61<=300000),Y61>300000))),IF($B$35="Any",TRUE,IF($B$35="Standalone",X61="Standalone",X61<>"Standalone")),IF($B$36="Any",TRUE,ISNUMBER(SEARCH($B$36,V61)))),IF(ISNUMBER(AF61),IF(AF61=0,0,AF61+ROW()/10000000),0),-ROW()/10000000),0) -> 8.1310061 | AL61: {=IF(INDEX(Recommendations!$D:$D,ROW())="","",IF(INDEX(Recommendations!$AJ:$AJ,ROW())=TRUE,"",ROW()))} -> 61 | AM61: =IF($U61="","",IFERROR(MATCH($U61,Recommendations!$D:$D,0),"")) -> 7
A62: =22 -> 22 | B62: =IFERROR(INDEX($U$55:$U$542, MATCH(LARGE($AK$55:$AK$542,A62), $AK$55:$AK$542, 0)), "") -> Peril's Gate | C62: =IFERROR(INDEX($V$55:$V$542, MATCH(LARGE($AK$55:$AK$542,A62), $AK$55:$AK$542, 0)), "") -> Janny Wurts | D62: =IFERROR(INDEX($W$55:$W$542, MATCH(LARGE($AK$55:$AK$542,A62), $AK$55:$AK$542, 0)), "") -> Epic Fantasy | E62: =IFERROR(INDEX($Y$55:$Y$542, MATCH(LARGE($AK$55:$AK$542,A62), $AK$55:$AK$542, 0)), "") -> 292000 | F62: =IFERROR(ROUND(INDEX($AF$55:$AF$542, MATCH(LARGE($AK$55:$AK$542,A62), $AK$55:$AK$542, 0)),2), "") -> 8.77 | G62: =IFERROR(INDEX($T$55:$T$542, MATCH(LARGE($AK$55:$AK$542,A62), $AK$55:$AK$542, 0)), "") -> 24 | H62: =IFERROR(INDEX($X$55:$X$542, MATCH(LARGE($AK$55:$AK$542,A62), $AK$55:$AK$542, 0)), "") -> Wars of Light and Shadow | I62: =IFERROR(_xlfn.XLOOKUP(B62,$U$55:$U$542,$AH$55:$AH$542),"") -> Series tipping point and its most kinetic novel — one extended chase through hostile terrain after five books of investment. Reviewers cite the chase sequence as among the most dramatic in modern fantasy. Closest analog: relentless back half of Assassin's Fate or Erikson's Memories of Ice. Confidence caveat: Pacing (predicted 6.5) is highest-risk — genuinely the fastest the series moves; could land 6.0–7.2. | J62: =IFERROR(_xlfn.XLOOKUP(B62,$U$55:$U$542,$AI$55:$AI$542),"") -> epic fantasy, trial, intrigue, prose-heavy, slow-burn, sprawling, dense | K62: =IF($B62="",FALSE,IFERROR(_xlfn.XLOOKUP($B62,Recommendations!$D:$D,Recommendations!$AJ:$AJ),FALSE)) -> FALSE | L62: =IF($B62="",FALSE,OR($K62=TRUE,$B62=BookTracker!$B$9)) -> FALSE | N62: {=IF(INDEX($P:$P,ROW()-1)="","",IF(OR(IFERROR(_xlfn.XLOOKUP(INDEX($P:$P,ROW()-1),Recommendations!$D:$D,Recommendations!$AJ:$AJ),FALSE)=TRUE,INDEX($P:$P,ROW()-1)=BookTracker!$B$9),"",ROW()-1))} | O62: The Expanse | T62: =IFERROR(_xlfn.XLOOKUP(U62,Recommendations!$D:$D,Recommendations!$A:$A),"") -> 110 | U62: {=IFERROR(INDEX(Recommendations!$D:$D,SMALL($AL$2:$AL$488,ROW()-55)),"")} -> Talon of the Silver Hawk | V62: =IFERROR(_xlfn.XLOOKUP(U62,Recommendations!$D:$D,Recommendations!$F:$F),"") -> Raymond E. Feist | W62: =IFERROR(_xlfn.XLOOKUP(U62,Recommendations!$D:$D,Recommendations!$E:$E),"") -> Epic Fantasy | X62: =IFERROR(_xlfn.XLOOKUP(U62,Recommendations!$D:$D,Recommendations!$G:$G),"") -> Conclave of Shadows | Y62: =IFERROR(_xlfn.XLOOKUP(U62,Recommendations!$D:$D,Recommendations!$H:$H),"") -> 130000 | Z62: =IF($U62="","",IFERROR(AVERAGE(INDEX(Recommendations!$K:$K,$AM62),INDEX(Recommendations!$I:$I,$AM62),INDEX(Recommendations!$J:$J,$AM62)),0)) -> 6.9066667 | AA62: =IF($U62="","",IFERROR(AVERAGE(INDEX(Recommendations!$X:$X,$AM62),INDEX(Recommendations!$Y:$Y,$AM62)),0)) -> 5.45 | AB62: =IF($U62="","",IFERROR(AVERAGE(INDEX(Recommendations!$P:$P,$AM62),INDEX(Recommendations!$O:$O,$AM62),INDEX(Recommendations!$R:$R,$AM62)),0)) -> 6.0888889 | AC62: =IF($U62="","",IFERROR(AVERAGE(INDEX(Recommendations!$AB:$AB,$AM62),INDEX(Recommendations!$AD:$AD,$AM62),INDEX(Recommendations!$T:$T,$AM62)),0)) -> 5.9 | AD62: =IF($U62="","",IFERROR(AVERAGE(INDEX(Recommendations!$I:$I,$AM62),INDEX(Recommendations!$L:$L,$AM62),INDEX(Recommendations!$J:$J,$AM62)),0)) -> 6.7733333 | AE62: =IF($U62="","",IFERROR(AVERAGE(INDEX(Recommendations!$O:$O,$AM62),INDEX(Recommendations!$Q:$Q,$AM62)),0)) -> 6.25 | AF62: {=IF($U62="","",IFERROR(IF(SUM($B$24:$B$29)=0,INDEX(Recommendations!$B:$B,$AM62),(Z62*$B$24+AA62*$B$25+AB62*$B$26+AC62*$B$27+AD62*$B$28+AE62*$B$29)/SUM($B$24:$B$29)),0))} -> 6.071 | AG62: =IFERROR(IF(ISNUMBER(AF62),IF(AF62=0,0,AF62+ROW()/10000000),0),0) -> 6.0710062 | AH62: =IFERROR(_xlfn.XLOOKUP(U62,Recommendations!$D:$D,Recommendations!$AK:$AK),"") -> Conclave of Shadows opener — a leaner coming-of-age revenge arc following Talon, more YA-feeling than the sprawling Serpentwar. Predicted below the Serpentwar band. Confidence caveat: Theme (predicted ~5.3) is lowest — the straightforward revenge plot offers little for your Theme weighting, range 4.8-6.0. | AI62: =IFERROR(_xlfn.XLOOKUP(U62,Recommendations!$D:$D,Recommendations!$AL:$AL),"") -> epic-fantasy, war, aftermath, military, good-vs-evil, conclusion, comfort-read, adventure | AJ62: =IF($B$37="",TRUE,IFERROR(ISNUMBER(SEARCH($B$37,AI62))+ISNUMBER(SEARCH($B$37,U62))+ISNUMBER(SEARCH($B$37,W62))>0,FALSE)) -> TRUE | AK62: =IFERROR(IF(AND(AJ62=TRUE,_xlfn.XLOOKUP(U62,Recommendations!$D:$D,Recommendations!$AJ:$AJ,FALSE)<>TRUE,IF($B$33="Any",TRUE,W62=$B$33),IF($B$34="Any",TRUE,IF($B$34="Short (<150K)",Y62<150000,IF($B$34="Medium (150-300K)",(Y62>=150000)*(Y62<=300000),Y62>300000))),IF($B$35="Any",TRUE,IF($B$35="Standalone",X62="Standalone",X62<>"Standalone")),IF($B$36="Any",TRUE,ISNUMBER(SEARCH($B$36,V62)))),IF(ISNUMBER(AF62),IF(AF62=0,0,AF62+ROW()/10000000),0),-ROW()/10000000),0) -> 6.0710062 | AL62: {=IF(INDEX(Recommendations!$D:$D,ROW())="","",IF(INDEX(Recommendations!$AJ:$AJ,ROW())=TRUE,"",ROW()))} -> 62 | AM62: =IF($U62="","",IFERROR(MATCH($U62,Recommendations!$D:$D,0),"")) -> 8
A63: =23 -> 23 | B63: =IFERROR(INDEX($U$55:$U$542, MATCH(LARGE($AK$55:$AK$542,A63), $AK$55:$AK$542, 0)), "") -> Dune | C63: =IFERROR(INDEX($V$55:$V$542, MATCH(LARGE($AK$55:$AK$542,A63), $AK$55:$AK$542, 0)), "") -> Frank Herbert | D63: =IFERROR(INDEX($W$55:$W$542, MATCH(LARGE($AK$55:$AK$542,A63), $AK$55:$AK$542, 0)), "") -> Science Fiction (Soft) | E63: =IFERROR(INDEX($Y$55:$Y$542, MATCH(LARGE($AK$55:$AK$542,A63), $AK$55:$AK$542, 0)), "") -> 188000 | F63: =IFERROR(ROUND(INDEX($AF$55:$AF$542, MATCH(LARGE($AK$55:$AK$542,A63), $AK$55:$AK$542, 0)),2), "") -> 8.77 | G63: =IFERROR(INDEX($T$55:$T$542, MATCH(LARGE($AK$55:$AK$542,A63), $AK$55:$AK$542, 0)), "") -> 29 | H63: =IFERROR(INDEX($X$55:$X$542, MATCH(LARGE($AK$55:$AK$542,A63), $AK$55:$AK$542, 0)), "") -> Dune | I63: =IFERROR(_xlfn.XLOOKUP(B63,$U$55:$U$542,$AH$55:$AH$542),"") -> Foundational philosophical SF — ecology, religion, prescience, power. Strongest dimensions: Worldbuilding (9.5, possibly the genre's deepest) and Theme (9.0). Closest analog: SF-Card-A cluster (Speaker for the Dead 9.30) for philosophical-SF-masterpiece structure. Confidence caveat: Pacing (predicted 7.5) is highest-risk — the famously glacial first 200 pages could push it down to 6.5–8.0; EmoImpact (8.2) also risky given the cerebral, distanced tone. | J63: =IFERROR(_xlfn.XLOOKUP(B63,$U$55:$U$542,$AI$55:$AI$542),"") -> space-opera, AI, far-future, galactic, inventive, propulsive, cerebral, expansive | K63: =IF($B63="",FALSE,IFERROR(_xlfn.XLOOKUP($B63,Recommendations!$D:$D,Recommendations!$AJ:$AJ),FALSE)) -> FALSE | L63: =IF($B63="",FALSE,OR($K63=TRUE,$B63=BookTracker!$B$9)) -> FALSE | N63: {=IF(INDEX($P:$P,ROW()-1)="","",IF(OR(IFERROR(_xlfn.XLOOKUP(INDEX($P:$P,ROW()-1),Recommendations!$D:$D,Recommendations!$AJ:$AJ),FALSE)=TRUE,INDEX($P:$P,ROW()-1)=BookTracker!$B$9),"",ROW()-1))} | O63: The Faithful and the Fallen | T63: =IFERROR(_xlfn.XLOOKUP(U63,Recommendations!$D:$D,Recommendations!$A:$A),"") -> 110 | U63: {=IFERROR(INDEX(Recommendations!$D:$D,SMALL($AL$2:$AL$488,ROW()-55)),"")} -> King of Foxes | V63: =IFERROR(_xlfn.XLOOKUP(U63,Recommendations!$D:$D,Recommendations!$F:$F),"") -> Raymond E. Feist | W63: =IFERROR(_xlfn.XLOOKUP(U63,Recommendations!$D:$D,Recommendations!$E:$E),"") -> Epic Fantasy | X63: =IFERROR(_xlfn.XLOOKUP(U63,Recommendations!$D:$D,Recommendations!$G:$G),"") -> Conclave of Shadows | Y63: =IFERROR(_xlfn.XLOOKUP(U63,Recommendations!$D:$D,Recommendations!$H:$H),"") -> 132000 | Z63: =IF($U63="","",IFERROR(AVERAGE(INDEX(Recommendations!$K:$K,$AM63),INDEX(Recommendations!$I:$I,$AM63),INDEX(Recommendations!$J:$J,$AM63)),0)) -> 6.9666667 | AA63: =IF($U63="","",IFERROR(AVERAGE(INDEX(Recommendations!$X:$X,$AM63),INDEX(Recommendations!$Y:$Y,$AM63)),0)) -> 5.6 | AB63: =IF($U63="","",IFERROR(AVERAGE(INDEX(Recommendations!$P:$P,$AM63),INDEX(Recommendations!$O:$O,$AM63),INDEX(Recommendations!$R:$R,$AM63)),0)) -> 6.1888889 | AC63: =IF($U63="","",IFERROR(AVERAGE(INDEX(Recommendations!$AB:$AB,$AM63),INDEX(Recommendations!$AD:$AD,$AM63),INDEX(Recommendations!$T:$T,$AM63)),0)) -> 5.9666667 | AD63: =IF($U63="","",IFERROR(AVERAGE(INDEX(Recommendations!$I:$I,$AM63),INDEX(Recommendations!$L:$L,$AM63),INDEX(Recommendations!$J:$J,$AM63)),0)) -> 6.8666667 | AE63: =IF($U63="","",IFERROR(AVERAGE(INDEX(Recommendations!$O:$O,$AM63),INDEX(Recommendations!$Q:$Q,$AM63)),0)) -> 6.35 | AF63: {=IF($U63="","",IFERROR(IF(SUM($B$24:$B$29)=0,INDEX(Recommendations!$B:$B,$AM63),(Z63*$B$24+AA63*$B$25+AB63*$B$26+AC63*$B$27+AD63*$B$28+AE63*$B$29)/SUM($B$24:$B$29)),0))} -> 6.155 | AG63: =IFERROR(IF(ISNUMBER(AF63),IF(AF63=0,0,AF63+ROW()/10000000),0),0) -> 6.1550063 | AH63: =IFERROR(_xlfn.XLOOKUP(U63,Recommendations!$D:$D,Recommendations!$AK:$AK),"") -> The strongest Conclave entry — court intrigue and espionage as Talon infiltrates an enemy noble's service. Tighter and more cunning than the bookends. Confidence caveat: Character depth (predicted 6.2) is the swing factor — spy-craft plotting may engage you more than predicted, could reach 6.8. | AI63: =IFERROR(_xlfn.XLOOKUP(U63,Recommendations!$D:$D,Recommendations!$AL:$AL),"") -> epic-fantasy, coming-of-age, revenge, adventure, training, comfort-read, YA-adjacent, quest | AJ63: =IF($B$37="",TRUE,IFERROR(ISNUMBER(SEARCH($B$37,AI63))+ISNUMBER(SEARCH($B$37,U63))+ISNUMBER(SEARCH($B$37,W63))>0,FALSE)) -> TRUE | AK63: =IFERROR(IF(AND(AJ63=TRUE,_xlfn.XLOOKUP(U63,Recommendations!$D:$D,Recommendations!$AJ:$AJ,FALSE)<>TRUE,IF($B$33="Any",TRUE,W63=$B$33),IF($B$34="Any",TRUE,IF($B$34="Short (<150K)",Y63<150000,IF($B$34="Medium (150-300K)",(Y63>=150000)*(Y63<=300000),Y63>300000))),IF($B$35="Any",TRUE,IF($B$35="Standalone",X63="Standalone",X63<>"Standalone")),IF($B$36="Any",TRUE,ISNUMBER(SEARCH($B$36,V63)))),IF(ISNUMBER(AF63),IF(AF63=0,0,AF63+ROW()/10000000),0),-ROW()/10000000),0) -> 6.1550063 | AL63: {=IF(INDEX(Recommendations!$D:$D,ROW())="","",IF(INDEX(Recommendations!$AJ:$AJ,ROW())=TRUE,"",ROW()))} -> 63 | AM63: =IF($U63="","",IFERROR(MATCH($U63,Recommendations!$D:$D,0),"")) -> 9
A64: =24 -> 24 | B64: =IFERROR(INDEX($U$55:$U$542, MATCH(LARGE($AK$55:$AK$542,A64), $AK$55:$AK$542, 0)), "") -> Under Heaven | C64: =IFERROR(INDEX($V$55:$V$542, MATCH(LARGE($AK$55:$AK$542,A64), $AK$55:$AK$542, 0)), "") -> Guy Gavriel Kay | D64: =IFERROR(INDEX($W$55:$W$542, MATCH(LARGE($AK$55:$AK$542,A64), $AK$55:$AK$542, 0)), "") -> Literary Fantasy | E64: =IFERROR(INDEX($Y$55:$Y$542, MATCH(LARGE($AK$55:$AK$542,A64), $AK$55:$AK$542, 0)), "") -> 215000 | F64: =IFERROR(ROUND(INDEX($AF$55:$AF$542, MATCH(LARGE($AK$55:$AK$542,A64), $AK$55:$AK$542, 0)),2), "") -> 8.76 | G64: =IFERROR(INDEX($T$55:$T$542, MATCH(LARGE($AK$55:$AK$542,A64), $AK$55:$AK$542, 0)), "") -> 24 | H64: =IFERROR(INDEX($X$55:$X$542, MATCH(LARGE($AK$55:$AK$542,A64), $AK$55:$AK$542, 0)), "") -> Standalone | I64: =IFERROR(_xlfn.XLOOKUP(B64,$U$55:$U$542,$AH$55:$AH$542),"") -> Kay's Tang-Dynasty-inspired late-career masterpiece — widely cited as 'his most assured book since Lions of Al-Rassan' with 'gem-like' construction and conversations that rival Tigana's eavesdropping scene. Closest analog: Lions of Al-Rassan (WA 8.95); Under Heaven sits just below, dragged by a near-universally-flagged 'slightly abrupt' ending and low Action (contemplative court-intrigue, not battle). Confidence caveat: Ending (predicted 8.2) is highest-risk — every major review flags the rushed finale; could land 7.0–8.8. | J64: =IFERROR(_xlfn.XLOOKUP(B64,$U$55:$U$542,$AI$55:$AI$542),"") -> action, cosmere, chase, survival, fast-paced, dystopian, sci-fantasy | K64: =IF($B64="",FALSE,IFERROR(_xlfn.XLOOKUP($B64,Recommendations!$D:$D,Recommendations!$AJ:$AJ),FALSE)) -> FALSE | L64: =IF($B64="",FALSE,OR($K64=TRUE,$B64=BookTracker!$B$9)) -> FALSE | N64: {=IF(INDEX($P:$P,ROW()-1)="","",IF(OR(IFERROR(_xlfn.XLOOKUP(INDEX($P:$P,ROW()-1),Recommendations!$D:$D,Recommendations!$AJ:$AJ),FALSE)=TRUE,INDEX($P:$P,ROW()-1)=BookTracker!$B$9),"",ROW()-1))} | O64: The Final Architecture | T64: =IFERROR(_xlfn.XLOOKUP(U64,Recommendations!$D:$D,Recommendations!$A:$A),"") -> 113 | U64: {=IFERROR(INDEX(Recommendations!$D:$D,SMALL($AL$2:$AL$488,ROW()-55)),"")} -> Exile's Return | V64: =IFERROR(_xlfn.XLOOKUP(U64,Recommendations!$D:$D,Recommendations!$F:$F),"") -> Raymond E. Feist | W64: =IFERROR(_xlfn.XLOOKUP(U64,Recommendations!$D:$D,Recommendations!$E:$E),"") -> Epic Fantasy | X64: =IFERROR(_xlfn.XLOOKUP(U64,Recommendations!$D:$D,Recommendations!$G:$G),"") -> Conclave of Shadows | Y64: =IFERROR(_xlfn.XLOOKUP(U64,Recommendations!$D:$D,Recommendations!$H:$H),"") -> 128000 | Z64: =IF($U64="","",IFERROR(AVERAGE(INDEX(Recommendations!$K:$K,$AM64),INDEX(Recommendations!$I:$I,$AM64),INDEX(Recommendations!$J:$J,$AM64)),0)) -> 6.3733333 | AA64: =IF($U64="","",IFERROR(AVERAGE(INDEX(Recommendations!$X:$X,$AM64),INDEX(Recommendations!$Y:$Y,$AM64)),0)) -> 5.6 | AB64: =IF($U64="","",IFERROR(AVERAGE(INDEX(Recommendations!$P:$P,$AM64),INDEX(Recommendations!$O:$O,$AM64),INDEX(Recommendations!$R:$R,$AM64)),0)) -> 5.9444444 | AC64: =IF($U64="","",IFERROR(AVERAGE(INDEX(Recommendations!$AB:$AB,$AM64),INDEX(Recommendations!$AD:$AD,$AM64),INDEX(Recommendations!$T:$T,$AM64)),0)) -> 5.8333333 | AD64: =IF($U64="","",IFERROR(AVERAGE(INDEX(Recommendations!$I:$I,$AM64),INDEX(Recommendations!$L:$L,$AM64),INDEX(Recommendations!$J:$J,$AM64)),0)) -> 6.3066667 | AE64: =IF($U64="","",IFERROR(AVERAGE(INDEX(Recommendations!$O:$O,$AM64),INDEX(Recommendations!$Q:$Q,$AM64)),0)) -> 6.15 | AF64: {=IF($U64="","",IFERROR(IF(SUM($B$24:$B$29)=0,INDEX(Recommendations!$B:$B,$AM64),(Z64*$B$24+AA64*$B$25+AB64*$B$26+AC64*$B$27+AD64*$B$28+AE64*$B$29)/SUM($B$24:$B$29)),0))} -> 5.941 | AG64: =IFERROR(IF(ISNUMBER(AF64),IF(AF64=0,0,AF64+ROW()/10000000),0),0) -> 5.9410064 | AH64: =IFERROR(_xlfn.XLOOKUP(U64,Recommendations!$D:$D,Recommendations!$AK:$AK),"") -> Conclave finale told partly from the antagonist's view — an experiment that divides readers and predicts as the weakest of these seven. Wraps Talon's arc. Confidence caveat: Plot (predicted 6.3) is the risk — the villain-POV structure may feel uneven, range 5.5-6.8. | AI64: =IFERROR(_xlfn.XLOOKUP(U64,Recommendations!$D:$D,Recommendations!$AL:$AL),"") -> epic-fantasy, espionage, court-intrigue, revenge, infiltration, adventure, comfort-read, cunning | AJ64: =IF($B$37="",TRUE,IFERROR(ISNUMBER(SEARCH($B$37,AI64))+ISNUMBER(SEARCH($B$37,U64))+ISNUMBER(SEARCH($B$37,W64))>0,FALSE)) -> TRUE | AK64: =IFERROR(IF(AND(AJ64=TRUE,_xlfn.XLOOKUP(U64,Recommendations!$D:$D,Recommendations!$AJ:$AJ,FALSE)<>TRUE,IF($B$33="Any",TRUE,W64=$B$33),IF($B$34="Any",TRUE,IF($B$34="Short (<150K)",Y64<150000,IF($B$34="Medium (150-300K)",(Y64>=150000)*(Y64<=300000),Y64>300000))),IF($B$35="Any",TRUE,IF($B$35="Standalone",X64="Standalone",X64<>"Standalone")),IF($B$36="Any",TRUE,ISNUMBER(SEARCH($B$36,V64)))),IF(ISNUMBER(AF64),IF(AF64=0,0,AF64+ROW()/10000000),0),-ROW()/10000000),0) -> 5.9410064 | AL64: {=IF(INDEX(Recommendations!$D:$D,ROW())="","",IF(INDEX(Recommendations!$AJ:$AJ,ROW())=TRUE,"",ROW()))} -> 64 | AM64: =IF($U64="","",IFERROR(MATCH($U64,Recommendations!$D:$D,0),"")) -> 10
A65: =25 -> 25 | B65: =IFERROR(INDEX($U$55:$U$542, MATCH(LARGE($AK$55:$AK$542,A65), $AK$55:$AK$542, 0)), "") -> Hogfather | C65: =IFERROR(INDEX($V$55:$V$542, MATCH(LARGE($AK$55:$AK$542,A65), $AK$55:$AK$542, 0)), "") -> Terry Pratchett | D65: =IFERROR(INDEX($W$55:$W$542, MATCH(LARGE($AK$55:$AK$542,A65), $AK$55:$AK$542, 0)), "") -> Literary Fantasy | E65: =IFERROR(INDEX($Y$55:$Y$542, MATCH(LARGE($AK$55:$AK$542,A65), $AK$55:$AK$542, 0)), "") -> 110000 | F65: =IFERROR(ROUND(INDEX($AF$55:$AF$542, MATCH(LARGE($AK$55:$AK$542,A65), $AK$55:$AK$542, 0)),2), "") -> 8.75 | G65: =IFERROR(INDEX($T$55:$T$542, MATCH(LARGE($AK$55:$AK$542,A65), $AK$55:$AK$542, 0)), "") -> 20 | H65: =IFERROR(INDEX($X$55:$X$542, MATCH(LARGE($AK$55:$AK$542,A65), $AK$55:$AK$542, 0)), "") -> Discworld: Death | I65: =IFERROR(_xlfn.XLOOKUP(B65,$U$55:$U$542,$AH$55:$AH$542),"") -> Pratchett's philosophical magnum opus — belief, myth, and the necessary fictions that make us human. Closest analog: The Neverending Story for thematic ambition (humanity-needs-stories) and Between Two Fires for the high-stakes-with-villain structure; Teatime is one of Pratchett's great antagonists. Confidence caveat: Ending (predicted 9.2) is highest-risk — the 'you need to believe in things that aren't true' speech is either a 10 or a 7 depending on taste, could land 8.0–9.7. | J65: =IFERROR(_xlfn.XLOOKUP(B65,$U$55:$U$542,$AI$55:$AI$542),"") -> comic fantasy, mortality, poignant, witty, heartfelt, whimsical, bittersweet | K65: =IF($B65="",FALSE,IFERROR(_xlfn.XLOOKUP($B65,Recommendations!$D:$D,Recommendations!$AJ:$AJ),FALSE)) -> FALSE | L65: =IF($B65="",FALSE,OR($K65=TRUE,$B65=BookTracker!$B$9)) -> FALSE | N65: {=IF(INDEX($P:$P,ROW()-1)="","",IF(OR(IFERROR(_xlfn.XLOOKUP(INDEX($P:$P,ROW()-1),Recommendations!$D:$D,Recommendations!$AJ:$AJ),FALSE)=TRUE,INDEX($P:$P,ROW()-1)=BookTracker!$B$9),"",ROW()-1))} | O65: The Forever War | T65: =IFERROR(_xlfn.XLOOKUP(U65,Recommendations!$D:$D,Recommendations!$A:$A),"") -> 103 | U65: {=IFERROR(INDEX(Recommendations!$D:$D,SMALL($AL$2:$AL$488,ROW()-55)),"")} -> Legend | V65: =IFERROR(_xlfn.XLOOKUP(U65,Recommendations!$D:$D,Recommendations!$F:$F),"") -> David Gemmell | W65: =IFERROR(_xlfn.XLOOKUP(U65,Recommendations!$D:$D,Recommendations!$E:$E),"") -> Epic Fantasy | X65: =IFERROR(_xlfn.XLOOKUP(U65,Recommendations!$D:$D,Recommendations!$G:$G),"") -> Drenai Saga | Y65: =IFERROR(_xlfn.XLOOKUP(U65,Recommendations!$D:$D,Recommendations!$H:$H),"") -> 110000 | Z65: =IF($U65="","",IFERROR(AVERAGE(INDEX(Recommendations!$K:$K,$AM65),INDEX(Recommendations!$I:$I,$AM65),INDEX(Recommendations!$J:$J,$AM65)),0)) -> 8.0866667 | AA65: =IF($U65="","",IFERROR(AVERAGE(INDEX(Recommendations!$X:$X,$AM65),INDEX(Recommendations!$Y:$Y,$AM65)),0)) -> 5.75 | AB65: =IF($U65="","",IFERROR(AVERAGE(INDEX(Recommendations!$P:$P,$AM65),INDEX(Recommendations!$O:$O,$AM65),INDEX(Recommendations!$R:$R,$AM65)),0)) -> 6.6111111 | AC65: =IF($U65="","",IFERROR(AVERAGE(INDEX(Recommendations!$AB:$AB,$AM65),INDEX(Recommendations!$AD:$AD,$AM65),INDEX(Recommendations!$T:$T,$AM65)),0)) -> 5.6666667 | AD65: =IF($U65="","",IFERROR(AVERAGE(INDEX(Recommendations!$I:$I,$AM65),INDEX(Recommendations!$L:$L,$AM65),INDEX(Recommendations!$J:$J,$AM65)),0)) -> 7.9866667 | AE65: =IF($U65="","",IFERROR(AVERAGE(INDEX(Recommendations!$O:$O,$AM65),INDEX(Recommendations!$Q:$Q,$AM65)),0)) -> 5.9 | AF65: {=IF($U65="","",IFERROR(IF(SUM($B$24:$B$29)=0,INDEX(Recommendations!$B:$B,$AM65),(Z65*$B$24+AA65*$B$25+AB65*$B$26+AC65*$B$27+AD65*$B$28+AE65*$B$29)/SUM($B$24:$B$29)),0))} -> 6.4246667 | AG65: =IFERROR(IF(ISNUMBER(AF65),IF(AF65=0,0,AF65+ROW()/10000000),0),0) -> 6.4246732 | AH65: =IFERROR(_xlfn.XLOOKUP(U65,Recommendations!$D:$D,Recommendations!$AK:$AK),"") -> Founding text of heroic fantasy — a doomed last stand at the fortress of Dros Delnoch, anchored by aging axeman Druss. Predicted highs: Action (8.8), Pacing (8.6), Ending (8.5); weakest on Prose, Multi-Dimensionality, and Originality (archetypal characters, plain prose). Closest analog on your shelf: tonally between Williams (Memory/Sorrow) and the propulsive-but-simple end of Erikson — shorter, leaner, less ornate. Confidence caveat: Emotional Impact (7.5) and Ending (8.5) are highest-risk — Gemmell's emotional directness could read as earned or sentimental depending on taste, landing anywhere from 6.5 to 9.0. | AI65: =IFERROR(_xlfn.XLOOKUP(U65,Recommendations!$D:$D,Recommendations!$AL:$AL),"") -> heroic fantasy, siege, war, stoic, aging-hero, gritty, fast-paced, bittersweet | AJ65: =IF($B$37="",TRUE,IFERROR(ISNUMBER(SEARCH($B$37,AI65))+ISNUMBER(SEARCH($B$37,U65))+ISNUMBER(SEARCH($B$37,W65))>0,FALSE)) -> TRUE | AK65: =IFERROR(IF(AND(AJ65=TRUE,_xlfn.XLOOKUP(U65,Recommendations!$D:$D,Recommendations!$AJ:$AJ,FALSE)<>TRUE,IF($B$33="Any",TRUE,W65=$B$33),IF($B$34="Any",TRUE,IF($B$34="Short (<150K)",Y65<150000,IF($B$34="Medium (150-300K)",(Y65>=150000)*(Y65<=300000),Y65>300000))),IF($B$35="Any",TRUE,IF($B$35="Standalone",X65="Standalone",X65<>"Standalone")),IF($B$36="Any",TRUE,ISNUMBER(SEARCH($B$36,V65)))),IF(ISNUMBER(AF65),IF(AF65=0,0,AF65+ROW()/10000000),0),-ROW()/10000000),0) -> 6.4246732 | AL65: {=IF(INDEX(Recommendations!$D:$D,ROW())="","",IF(INDEX(Recommendations!$AJ:$AJ,ROW())=TRUE,"",ROW()))} -> 65 | AM65: =IF($U65="","",IFERROR(MATCH($U65,Recommendations!$D:$D,0),"")) -> 11
A66: =26 -> 26 | B66: =IFERROR(INDEX($U$55:$U$542, MATCH(LARGE($AK$55:$AK$542,A66), $AK$55:$AK$542, 0)), "") -> Assassin's Fate | C66: =IFERROR(INDEX($V$55:$V$542, MATCH(LARGE($AK$55:$AK$542,A66), $AK$55:$AK$542, 0)), "") -> Robin Hobb | D66: =IFERROR(INDEX($W$55:$W$542, MATCH(LARGE($AK$55:$AK$542,A66), $AK$55:$AK$542, 0)), "") -> Epic Fantasy | E66: =IFERROR(INDEX($Y$55:$Y$542, MATCH(LARGE($AK$55:$AK$542,A66), $AK$55:$AK$542, 0)), "") -> 370000 | F66: =IFERROR(ROUND(INDEX($AF$55:$AF$542, MATCH(LARGE($AK$55:$AK$542,A66), $AK$55:$AK$542, 0)),2), "") -> 8.74 | G66: =IFERROR(INDEX($T$55:$T$542, MATCH(LARGE($AK$55:$AK$542,A66), $AK$55:$AK$542, 0)), "") -> 19 | H66: =IFERROR(INDEX($X$55:$X$542, MATCH(LARGE($AK$55:$AK$542,A66), $AK$55:$AK$542, 0)), "") -> Realm of the Elderlings | I66: =IFERROR(_xlfn.XLOOKUP(B66,$U$55:$U$542,$AH$55:$AH$542),"") -> Hobb's career capstone — Assassin's Fate is widely cited as one of the greatest endings in epic fantasy. Ending (9.4) and Emotional Impact (9.6) are the highest scores anywhere in the prediction set; the closing 200 pages with Fitz, the Fool, and Bee land an arc 16 books in the making. Worldbuilding integration (8.9) reaches Erikson-tier as every thread from Liveship and Rain Wild converges. Confidence caveat: Pacing (7.3) reflects the long approach to the Clerres assault; if 9.4 Ending feels too high, that's where to adjust — the prediction assumes you've earned the emotional capital through the prior 15 volumes. | J66: =IFERROR(_xlfn.XLOOKUP(B66,$U$55:$U$542,$AI$55:$AI$542),"") -> quiet, domestic, melancholic, slow-burn, fatherhood, foreboding, character-driven | K66: =IF($B66="",FALSE,IFERROR(_xlfn.XLOOKUP($B66,Recommendations!$D:$D,Recommendations!$AJ:$AJ),FALSE)) -> FALSE | L66: =IF($B66="",FALSE,OR($K66=TRUE,$B66=BookTracker!$B$9)) -> FALSE | N66: {=IF(INDEX($P:$P,ROW()-1)="","",IF(OR(IFERROR(_xlfn.XLOOKUP(INDEX($P:$P,ROW()-1),Recommendations!$D:$D,Recommendations!$AJ:$AJ),FALSE)=TRUE,INDEX($P:$P,ROW()-1)=BookTracker!$B$9),"",ROW()-1))} | O66: The Forsyte Saga | T66: =IFERROR(_xlfn.XLOOKUP(U66,Recommendations!$D:$D,Recommendations!$A:$A),"") -> 109 | U66: {=IFERROR(INDEX(Recommendations!$D:$D,SMALL($AL$2:$AL$488,ROW()-55)),"")} -> The King Beyond the Gate | V66: =IFERROR(_xlfn.XLOOKUP(U66,Recommendations!$D:$D,Recommendations!$F:$F),"") -> David Gemmell | W66: =IFERROR(_xlfn.XLOOKUP(U66,Recommendations!$D:$D,Recommendations!$E:$E),"") -> Epic Fantasy | X66: =IFERROR(_xlfn.XLOOKUP(U66,Recommendations!$D:$D,Recommendations!$G:$G),"") -> Drenai Saga | Y66: =IFERROR(_xlfn.XLOOKUP(U66,Recommendations!$D:$D,Recommendations!$H:$H),"") -> 120000 | Z66: =IF($U66="","",IFERROR(AVERAGE(INDEX(Recommendations!$K:$K,$AM66),INDEX(Recommendations!$I:$I,$AM66),INDEX(Recommendations!$J:$J,$AM66)),0)) -> 7.0966667 | AA66: =IF($U66="","",IFERROR(AVERAGE(INDEX(Recommendations!$X:$X,$AM66),INDEX(Recommendations!$Y:$Y,$AM66)),0)) -> 6.15 | AB66: =IF($U66="","",IFERROR(AVERAGE(INDEX(Recommendations!$P:$P,$AM66),INDEX(Recommendations!$O:$O,$AM66),INDEX(Recommendations!$R:$R,$AM66)),0)) -> 5.9333333 | AC66: =IF($U66="","",IFERROR(AVERAGE(INDEX(Recommendations!$AB:$AB,$AM66),INDEX(Recommendations!$AD:$AD,$AM66),INDEX(Recommendations!$T:$T,$AM66)),0)) -> 6.0333333 | AD66: =IF($U66="","",IFERROR(AVERAGE(INDEX(Recommendations!$I:$I,$AM66),INDEX(Recommendations!$L:$L,$AM66),INDEX(Recommendations!$J:$J,$AM66)),0)) -> 6.8633333 | AE66: =IF($U66="","",IFERROR(AVERAGE(INDEX(Recommendations!$O:$O,$AM66),INDEX(Recommendations!$Q:$Q,$AM66)),0)) -> 6 | AF66: {=IF($U66="","",IFERROR(IF(SUM($B$24:$B$29)=0,INDEX(Recommendations!$B:$B,$AM66),(Z66*$B$24+AA66*$B$25+AB66*$B$26+AC66*$B$27+AD66*$B$28+AE66*$B$29)/SUM($B$24:$B$29)),0))} -> 6.2545 | AG66: =IFERROR(IF(ISNUMBER(AF66),IF(AF66=0,0,AF66+ROW()/10000000),0),0) -> 6.2545066 | AH66: =IFERROR(_xlfn.XLOOKUP(U66,Recommendations!$D:$D,Recommendations!$AK:$AK),"") -> Drenai #2, set 100 years after Legend — Tenaka Khan's revolt against a decadent empire. Reads as Legend redux with tighter scope; Goodreads 3.99 vs Legend's 4.31. Predicted Total Avg 6.21 → Rank ~95, sitting below Legend's anchor (6.46) with no real character or theme lift. Confidence caveat: Originality (5.8) is the floor — this is the book where Gemmell's repeat-the-formula problem shows most clearly. Skip if you only want the canonical Drenai entries. | AI66: =IFERROR(_xlfn.XLOOKUP(U66,Recommendations!$D:$D,Recommendations!$AL:$AL),"") -> heroic fantasy, rebellion, tyranny, gritty, fast-paced, dark, action, redemption | AJ66: =IF($B$37="",TRUE,IFERROR(ISNUMBER(SEARCH($B$37,AI66))+ISNUMBER(SEARCH($B$37,U66))+ISNUMBER(SEARCH($B$37,W66))>0,FALSE)) -> TRUE | AK66: =IFERROR(IF(AND(AJ66=TRUE,_xlfn.XLOOKUP(U66,Recommendations!$D:$D,Recommendations!$AJ:$AJ,FALSE)<>TRUE,IF($B$33="Any",TRUE,W66=$B$33),IF($B$34="Any",TRUE,IF($B$34="Short (<150K)",Y66<150000,IF($B$34="Medium (150-300K)",(Y66>=150000)*(Y66<=300000),Y66>300000))),IF($B$35="Any",TRUE,IF($B$35="Standalone",X66="Standalone",X66<>"Standalone")),IF($B$36="Any",TRUE,ISNUMBER(SEARCH($B$36,V66)))),IF(ISNUMBER(AF66),IF(AF66=0,0,AF66+ROW()/10000000),0),-ROW()/10000000),0) -> 6.2545066 | AL66: {=IF(INDEX(Recommendations!$D:$D,ROW())="","",IF(INDEX(Recommendations!$AJ:$AJ,ROW())=TRUE,"",ROW()))} -> 66 | AM66: =IF($U66="","",IFERROR(MATCH($U66,Recommendations!$D:$D,0),"")) -> 12
A67: =27 -> 27 | B67: =IFERROR(INDEX($U$55:$U$542, MATCH(LARGE($AK$55:$AK$542,A67), $AK$55:$AK$542, 0)), "") -> Traitor's Knot | C67: =IFERROR(INDEX($V$55:$V$542, MATCH(LARGE($AK$55:$AK$542,A67), $AK$55:$AK$542, 0)), "") -> Janny Wurts | D67: =IFERROR(INDEX($W$55:$W$542, MATCH(LARGE($AK$55:$AK$542,A67), $AK$55:$AK$542, 0)), "") -> Epic Fantasy | E67: =IFERROR(INDEX($Y$55:$Y$542, MATCH(LARGE($AK$55:$AK$542,A67), $AK$55:$AK$542, 0)), "") -> 212000 | F67: =IFERROR(ROUND(INDEX($AF$55:$AF$542, MATCH(LARGE($AK$55:$AK$542,A67), $AK$55:$AK$542, 0)),2), "") -> 8.73 | G67: =IFERROR(INDEX($T$55:$T$542, MATCH(LARGE($AK$55:$AK$542,A67), $AK$55:$AK$542, 0)), "") -> 28 | H67: =IFERROR(INDEX($X$55:$X$542, MATCH(LARGE($AK$55:$AK$542,A67), $AK$55:$AK$542, 0)), "") -> Wars of Light and Shadow | I67: =IFERROR(_xlfn.XLOOKUP(B67,$U$55:$U$542,$AH$55:$AH$542),"") -> Penultimate arc entry that deepens moral complexity and positions the siege finale — Arithon masters the curse remnants, Lysaer's false religion fractures. Slightly slower than Peril's Gate but the richest in thematic density of the series. Confidence caveat: Entertainment (predicted 7.4) is highest-risk — setup-heavy sections could push lower (6.8) for plot-first readers. | J67: =IFERROR(_xlfn.XLOOKUP(B67,$U$55:$U$542,$AI$55:$AI$542),"") -> epic fantasy, intrigue, persecution, prose-heavy, sprawling, slow-burn, dense | K67: =IF($B67="",FALSE,IFERROR(_xlfn.XLOOKUP($B67,Recommendations!$D:$D,Recommendations!$AJ:$AJ),FALSE)) -> FALSE | L67: =IF($B67="",FALSE,OR($K67=TRUE,$B67=BookTracker!$B$9)) -> FALSE | N67: {=IF(INDEX($P:$P,ROW()-1)="","",IF(OR(IFERROR(_xlfn.XLOOKUP(INDEX($P:$P,ROW()-1),Recommendations!$D:$D,Recommendations!$AJ:$AJ),FALSE)=TRUE,INDEX($P:$P,ROW()-1)=BookTracker!$B$9),"",ROW()-1))} | O67: The Founders Trilogy | T67: =IFERROR(_xlfn.XLOOKUP(U67,Recommendations!$D:$D,Recommendations!$A:$A),"") -> 95 | U67: {=IFERROR(INDEX(Recommendations!$D:$D,SMALL($AL$2:$AL$488,ROW()-55)),"")} -> Waylander | V67: =IFERROR(_xlfn.XLOOKUP(U67,Recommendations!$D:$D,Recommendations!$F:$F),"") -> David Gemmell | W67: =IFERROR(_xlfn.XLOOKUP(U67,Recommendations!$D:$D,Recommendations!$E:$E),"") -> Epic Fantasy | X67: =IFERROR(_xlfn.XLOOKUP(U67,Recommendations!$D:$D,Recommendations!$G:$G),"") -> Drenai Saga | Y67: =IFERROR(_xlfn.XLOOKUP(U67,Recommendations!$D:$D,Recommendations!$H:$H),"") -> 105000 | Z67: =IF($U67="","",IFERROR(AVERAGE(INDEX(Recommendations!$K:$K,$AM67),INDEX(Recommendations!$I:$I,$AM67),INDEX(Recommendations!$J:$J,$AM67)),0)) -> 7.5866667 | AA67: =IF($U67="","",IFERROR(AVERAGE(INDEX(Recommendations!$X:$X,$AM67),INDEX(Recommendations!$Y:$Y,$AM67)),0)) -> 6.9 | AB67: =IF($U67="","",IFERROR(AVERAGE(INDEX(Recommendations!$P:$P,$AM67),INDEX(Recommendations!$O:$O,$AM67),INDEX(Recommendations!$R:$R,$AM67)),0)) -> 7.0444444 | AC67: =IF($U67="","",IFERROR(AVERAGE(INDEX(Recommendations!$AB:$AB,$AM67),INDEX(Recommendations!$AD:$AD,$AM67),INDEX(Recommendations!$T:$T,$AM67)),0)) -> 6.2666667 | AD67: =IF($U67="","",IFERROR(AVERAGE(INDEX(Recommendations!$I:$I,$AM67),INDEX(Recommendations!$L:$L,$AM67),INDEX(Recommendations!$J:$J,$AM67)),0)) -> 7.4866667 | AE67: =IF($U67="","",IFERROR(AVERAGE(INDEX(Recommendations!$O:$O,$AM67),INDEX(Recommendations!$Q:$Q,$AM67)),0)) -> 6.9 | AF67: {=IF($U67="","",IFERROR(IF(SUM($B$24:$B$29)=0,INDEX(Recommendations!$B:$B,$AM67),(Z67*$B$24+AA67*$B$25+AB67*$B$26+AC67*$B$27+AD67*$B$28+AE67*$B$29)/SUM($B$24:$B$29)),0))} -> 6.7996667 | AG67: =IFERROR(IF(ISNUMBER(AF67),IF(AF67=0,0,AF67+ROW()/10000000),0),0) -> 6.7996734 | AH67: =IFERROR(_xlfn.XLOOKUP(U67,Recommendations!$D:$D,Recommendations!$AK:$AK),"") -> The fan-favorite second peak — assassin antihero on a redemption arc, considered Gemmell's deepest protagonist. Goodreads 4.16. Predicted Total Avg 6.71 → Rank ~75, the highest of the entire Drenai saga (above Legend itself at 6.46) on Character (6.78) and Theme (6.87) lifts that the rest of the series doesn't match. Confidence caveat: Prose (5.8) remains the structural floor for all Gemmell — this is the highest-confidence pick of the saga and the one to read first if you only sample one beyond Legend. | AI67: =IFERROR(_xlfn.XLOOKUP(U67,Recommendations!$D:$D,Recommendations!$AL:$AL),"") -> heroic fantasy, antihero, assassin, redemption, gritty, fast-paced, brooding, violent | AJ67: =IF($B$37="",TRUE,IFERROR(ISNUMBER(SEARCH($B$37,AI67))+ISNUMBER(SEARCH($B$37,U67))+ISNUMBER(SEARCH($B$37,W67))>0,FALSE)) -> TRUE | AK67: =IFERROR(IF(AND(AJ67=TRUE,_xlfn.XLOOKUP(U67,Recommendations!$D:$D,Recommendations!$AJ:$AJ,FALSE)<>TRUE,IF($B$33="Any",TRUE,W67=$B$33),IF($B$34="Any",TRUE,IF($B$34="Short (<150K)",Y67<150000,IF($B$34="Medium (150-300K)",(Y67>=150000)*(Y67<=300000),Y67>300000))),IF($B$35="Any",TRUE,IF($B$35="Standalone",X67="Standalone",X67<>"Standalone")),IF($B$36="Any",TRUE,ISNUMBER(SEARCH($B$36,V67)))),IF(ISNUMBER(AF67),IF(AF67=0,0,AF67+ROW()/10000000),0),-ROW()/10000000),0) -> 6.7996734 | AL67: {=IF(INDEX(Recommendations!$D:$D,ROW())="","",IF(INDEX(Recommendations!$AJ:$AJ,ROW())=TRUE,"",ROW()))} -> 67 | AM67: =IF($U67="","",IFERROR(MATCH($U67,Recommendations!$D:$D,0),"")) -> 13
A68: =28 -> 28 | B68: =IFERROR(INDEX($U$55:$U$542, MATCH(LARGE($AK$55:$AK$542,A68), $AK$55:$AK$542, 0)), "") -> Beloved | C68: =IFERROR(INDEX($V$55:$V$542, MATCH(LARGE($AK$55:$AK$542,A68), $AK$55:$AK$542, 0)), "") -> Toni Morrison | D68: =IFERROR(INDEX($W$55:$W$542, MATCH(LARGE($AK$55:$AK$542,A68), $AK$55:$AK$542, 0)), "") -> Literary Fiction | E68: =IFERROR(INDEX($Y$55:$Y$542, MATCH(LARGE($AK$55:$AK$542,A68), $AK$55:$AK$542, 0)), "") -> 100000 | F68: =IFERROR(ROUND(INDEX($AF$55:$AF$542, MATCH(LARGE($AK$55:$AK$542,A68), $AK$55:$AK$542, 0)),2), "") -> 8.73 | G68: =IFERROR(INDEX($T$55:$T$542, MATCH(LARGE($AK$55:$AK$542,A68), $AK$55:$AK$542, 0)), "") -> 22 | H68: =IFERROR(INDEX($X$55:$X$542, MATCH(LARGE($AK$55:$AK$542,A68), $AK$55:$AK$542, 0)), "") -> Standalone | I68: =IFERROR(_xlfn.XLOOKUP(B68,$U$55:$U$542,$AH$55:$AH$542),"") -> Morrison's ghost-haunted reckoning with slavery — the only book in this batch I'm pricing Emotional Impact at 9.5. Predicted Total ceiling of the LitFic block. Closest analogs on your shelf: nothing matches the prose+devastation combination. Confidence caveat: the non-linear structure can be disorienting on first read — if the recursion sharpens the emotional climax, total ~8.7; if it muddies it, ~8.4. | J68: =IFERROR(_xlfn.XLOOKUP(B68,$U$55:$U$542,$AI$55:$AI$542),"") -> literary, classic, revenge, justice, adventure, sweeping, propulsive, satisfying | K68: =IF($B68="",FALSE,IFERROR(_xlfn.XLOOKUP($B68,Recommendations!$D:$D,Recommendations!$AJ:$AJ),FALSE)) -> FALSE | L68: =IF($B68="",FALSE,OR($K68=TRUE,$B68=BookTracker!$B$9)) -> FALSE | N68: {=IF(INDEX($P:$P,ROW()-1)="","",IF(OR(IFERROR(_xlfn.XLOOKUP(INDEX($P:$P,ROW()-1),Recommendations!$D:$D,Recommendations!$AJ:$AJ),FALSE)=TRUE,INDEX($P:$P,ROW()-1)=BookTracker!$B$9),"",ROW()-1))} | O68: The Henry Saga | T68: =IFERROR(_xlfn.XLOOKUP(U68,Recommendations!$D:$D,Recommendations!$A:$A),"") -> 109 | U68: {=IFERROR(INDEX(Recommendations!$D:$D,SMALL($AL$2:$AL$488,ROW()-55)),"")} -> Quest for Lost Heroes | V68: =IFERROR(_xlfn.XLOOKUP(U68,Recommendations!$D:$D,Recommendations!$F:$F),"") -> David Gemmell | W68: =IFERROR(_xlfn.XLOOKUP(U68,Recommendations!$D:$D,Recommendations!$E:$E),"") -> Epic Fantasy | X68: =IFERROR(_xlfn.XLOOKUP(U68,Recommendations!$D:$D,Recommendations!$G:$G),"") -> Drenai Saga | Y68: =IFERROR(_xlfn.XLOOKUP(U68,Recommendations!$D:$D,Recommendations!$H:$H),"") -> 105000 | Z68: =IF($U68="","",IFERROR(AVERAGE(INDEX(Recommendations!$K:$K,$AM68),INDEX(Recommendations!$I:$I,$AM68),INDEX(Recommendations!$J:$J,$AM68)),0)) -> 7.13 | AA68: =IF($U68="","",IFERROR(AVERAGE(INDEX(Recommendations!$X:$X,$AM68),INDEX(Recommendations!$Y:$Y,$AM68)),0)) -> 5.9 | AB68: =IF($U68="","",IFERROR(AVERAGE(INDEX(Recommendations!$P:$P,$AM68),INDEX(Recommendations!$O:$O,$AM68),INDEX(Recommendations!$R:$R,$AM68)),0)) -> 6.0777778 | AC68: =IF($U68="","",IFERROR(AVERAGE(INDEX(Recommendations!$AB:$AB,$AM68),INDEX(Recommendations!$AD:$AD,$AM68),INDEX(Recommendations!$T:$T,$AM68)),0)) -> 5.8666667 | AD68: =IF($U68="","",IFERROR(AVERAGE(INDEX(Recommendations!$I:$I,$AM68),INDEX(Recommendations!$L:$L,$AM68),INDEX(Recommendations!$J:$J,$AM68)),0)) -> 6.9633333 | AE68: =IF($U68="","",IFERROR(AVERAGE(INDEX(Recommendations!$O:$O,$AM68),INDEX(Recommendations!$Q:$Q,$AM68)),0)) -> 6.05 | AF68: {=IF($U68="","",IFERROR(IF(SUM($B$24:$B$29)=0,INDEX(Recommendations!$B:$B,$AM68),(Z68*$B$24+AA68*$B$25+AB68*$B$26+AC68*$B$27+AD68*$B$28+AE68*$B$29)/SUM($B$24:$B$29)),0))} -> 6.2161667 | AG68: =IFERROR(IF(ISNUMBER(AF68),IF(AF68=0,0,AF68+ROW()/10000000),0),0) -> 6.2161735 | AH68: =IFERROR(_xlfn.XLOOKUP(U68,Recommendations!$D:$D,Recommendations!$AK:$AK),"") -> Light ensemble heroic quest, reads like a D&D party adventure. Goodreads 4.04. Predicted Total Avg 6.20 → Rank ~95, tied with King Beyond the Gate as the saga's bottom tier. Multi-Dim gets a slight ensemble lift (6.2) but Theme (5.87) is the floor — this is the most disposable Drenai entry, no thematic ambition beyond the quest structure. Skip unless completionist. | AI68: =IFERROR(_xlfn.XLOOKUP(U68,Recommendations!$D:$D,Recommendations!$AL:$AL),"") -> heroic fantasy, quest, companionship, adventure, gritty, fast-paced, hopeful, action | AJ68: =IF($B$37="",TRUE,IFERROR(ISNUMBER(SEARCH($B$37,AI68))+ISNUMBER(SEARCH($B$37,U68))+ISNUMBER(SEARCH($B$37,W68))>0,FALSE)) -> TRUE | AK68: =IFERROR(IF(AND(AJ68=TRUE,_xlfn.XLOOKUP(U68,Recommendations!$D:$D,Recommendations!$AJ:$AJ,FALSE)<>TRUE,IF($B$33="Any",TRUE,W68=$B$33),IF($B$34="Any",TRUE,IF($B$34="Short (<150K)",Y68<150000,IF($B$34="Medium (150-300K)",(Y68>=150000)*(Y68<=300000),Y68>300000))),IF($B$35="Any",TRUE,IF($B$35="Standalone",X68="Standalone",X68<>"Standalone")),IF($B$36="Any",TRUE,ISNUMBER(SEARCH($B$36,V68)))),IF(ISNUMBER(AF68),IF(AF68=0,0,AF68+ROW()/10000000),0),-ROW()/10000000),0) -> 6.2161735 | AL68: {=IF(INDEX(Recommendations!$D:$D,ROW())="","",IF(INDEX(Recommendations!$AJ:$AJ,ROW())=TRUE,"",ROW()))} -> 68 | AM68: =IF($U68="","",IFERROR(MATCH($U68,Recommendations!$D:$D,0),"")) -> 14
A69: =29 -> 29 | B69: =IFERROR(INDEX($U$55:$U$542, MATCH(LARGE($AK$55:$AK$542,A69), $AK$55:$AK$542, 0)), "") -> Lolita | C69: =IFERROR(INDEX($V$55:$V$542, MATCH(LARGE($AK$55:$AK$542,A69), $AK$55:$AK$542, 0)), "") -> Vladimir Nabokov | D69: =IFERROR(INDEX($W$55:$W$542, MATCH(LARGE($AK$55:$AK$542,A69), $AK$55:$AK$542, 0)), "") -> Literary Fiction | E69: =IFERROR(INDEX($Y$55:$Y$542, MATCH(LARGE($AK$55:$AK$542,A69), $AK$55:$AK$542, 0)), "") -> 112000 | F69: =IFERROR(ROUND(INDEX($AF$55:$AF$542, MATCH(LARGE($AK$55:$AK$542,A69), $AK$55:$AK$542, 0)),2), "") -> 8.71 | G69: =IFERROR(INDEX($T$55:$T$542, MATCH(LARGE($AK$55:$AK$542,A69), $AK$55:$AK$542, 0)), "") -> 28 | H69: =IFERROR(INDEX($X$55:$X$542, MATCH(LARGE($AK$55:$AK$542,A69), $AK$55:$AK$542, 0)), "") -> Standalone | I69: =IFERROR(_xlfn.XLOOKUP(B69,$U$55:$U$542,$AH$55:$AH$542),"") -> Predator-narrator's confession written as if to dazzle the jury — the Prose/Phraseology/Narration triple-9.5 ceiling. Predicted highest in the LitFic block. No direct analog on your shelf — Lolita is its own category. Confidence caveat: Motivations (9.5) is a confident call — Humbert is one of the most fully motivated narrators in fiction; the real downside is moral discomfort tanking Entertainment, which I priced at 8.0. Total likely ~8.5–8.7. | J69: =IFERROR(_xlfn.XLOOKUP(B69,$U$55:$U$542,$AI$55:$AI$542),"") -> literary, historical, haunting, memory, trauma, lyrical, profound, harrowing | K69: =IF($B69="",FALSE,IFERROR(_xlfn.XLOOKUP($B69,Recommendations!$D:$D,Recommendations!$AJ:$AJ),FALSE)) -> FALSE | L69: =IF($B69="",FALSE,OR($K69=TRUE,$B69=BookTracker!$B$9)) -> FALSE | N69: {=IF(INDEX($P:$P,ROW()-1)="","",IF(OR(IFERROR(_xlfn.XLOOKUP(INDEX($P:$P,ROW()-1),Recommendations!$D:$D,Recommendations!$AJ:$AJ),FALSE)=TRUE,INDEX($P:$P,ROW()-1)=BookTracker!$B$9),"",ROW()-1))} | O69: The Kingkiller Chronicle | T69: =IFERROR(_xlfn.XLOOKUP(U69,Recommendations!$D:$D,Recommendations!$A:$A),"") -> 97 | U69: {=IFERROR(INDEX(Recommendations!$D:$D,SMALL($AL$2:$AL$488,ROW()-55)),"")} -> Waylander II: In the Realm of the Wolf | V69: =IFERROR(_xlfn.XLOOKUP(U69,Recommendations!$D:$D,Recommendations!$F:$F),"") -> David Gemmell | W69: =IFERROR(_xlfn.XLOOKUP(U69,Recommendations!$D:$D,Recommendations!$E:$E),"") -> Epic Fantasy | X69: =IFERROR(_xlfn.XLOOKUP(U69,Recommendations!$D:$D,Recommendations!$G:$G),"") -> Drenai Saga | Y69: =IFERROR(_xlfn.XLOOKUP(U69,Recommendations!$D:$D,Recommendations!$H:$H),"") -> 115000 | Z69: =IF($U69="","",IFERROR(AVERAGE(INDEX(Recommendations!$K:$K,$AM69),INDEX(Recommendations!$I:$I,$AM69),INDEX(Recommendations!$J:$J,$AM69)),0)) -> 7.2833333 | AA69: =IF($U69="","",IFERROR(AVERAGE(INDEX(Recommendations!$X:$X,$AM69),INDEX(Recommendations!$Y:$Y,$AM69)),0)) -> 6.9 | AB69: =IF($U69="","",IFERROR(AVERAGE(INDEX(Recommendations!$P:$P,$AM69),INDEX(Recommendations!$O:$O,$AM69),INDEX(Recommendations!$R:$R,$AM69)),0)) -> 7.0444444 | AC69: =IF($U69="","",IFERROR(AVERAGE(INDEX(Recommendations!$AB:$AB,$AM69),INDEX(Recommendations!$AD:$AD,$AM69),INDEX(Recommendations!$T:$T,$AM69)),0)) -> 6.1 | AD69: =IF($U69="","",IFERROR(AVERAGE(INDEX(Recommendations!$I:$I,$AM69),INDEX(Recommendations!$L:$L,$AM69),INDEX(Recommendations!$J:$J,$AM69)),0)) -> 7.2833333 | AE69: =IF($U69="","",IFERROR(AVERAGE(INDEX(Recommendations!$O:$O,$AM69),INDEX(Recommendations!$Q:$Q,$AM69)),0)) -> 6.9 | AF69: {=IF($U69="","",IFERROR(IF(SUM($B$24:$B$29)=0,INDEX(Recommendations!$B:$B,$AM69),(Z69*$B$24+AA69*$B$25+AB69*$B$26+AC69*$B$27+AD69*$B$28+AE69*$B$29)/SUM($B$24:$B$29)),0))} -> 6.7408333 | AG69: =IFERROR(IF(ISNUMBER(AF69),IF(AF69=0,0,AF69+ROW()/10000000),0),0) -> 6.7408402 | AH69: =IFERROR(_xlfn.XLOOKUP(U69,Recommendations!$D:$D,Recommendations!$AK:$AK),"") -> Waylander 20 years later, raising a daughter — fatherhood themes layered over the assassin's continuing redemption. Goodreads 4.21. Predicted Total Avg 6.66 → Rank ~75, sitting just under Waylander itself on Char/Theme parity but with slightly weaker Story momentum. Confidence caveat: Ending (7.5) is the standout — Gemmell consistently lands his finales, and Waylander II is one of the best examples. Read after Waylander. | AI69: =IFERROR(_xlfn.XLOOKUP(U69,Recommendations!$D:$D,Recommendations!$AL:$AL),"") -> heroic fantasy, assassin, hunted, gritty, fast-paced, dark, redemption, action | AJ69: =IF($B$37="",TRUE,IFERROR(ISNUMBER(SEARCH($B$37,AI69))+ISNUMBER(SEARCH($B$37,U69))+ISNUMBER(SEARCH($B$37,W69))>0,FALSE)) -> TRUE | AK69: =IFERROR(IF(AND(AJ69=TRUE,_xlfn.XLOOKUP(U69,Recommendations!$D:$D,Recommendations!$AJ:$AJ,FALSE)<>TRUE,IF($B$33="Any",TRUE,W69=$B$33),IF($B$34="Any",TRUE,IF($B$34="Short (<150K)",Y69<150000,IF($B$34="Medium (150-300K)",(Y69>=150000)*(Y69<=300000),Y69>300000))),IF($B$35="Any",TRUE,IF($B$35="Standalone",X69="Standalone",X69<>"Standalone")),IF($B$36="Any",TRUE,ISNUMBER(SEARCH($B$36,V69)))),IF(ISNUMBER(AF69),IF(AF69=0,0,AF69+ROW()/10000000),0),-ROW()/10000000),0) -> 6.7408402 | AL69: {=IF(INDEX(Recommendations!$D:$D,ROW())="","",IF(INDEX(Recommendations!$AJ:$AJ,ROW())=TRUE,"",ROW()))} -> 69 | AM69: =IF($U69="","",IFERROR(MATCH($U69,Recommendations!$D:$D,0),"")) -> 15
A70: =30 -> 30 | B70: =IFERROR(INDEX($U$55:$U$542, MATCH(LARGE($AK$55:$AK$542,A70), $AK$55:$AK$542, 0)), "") -> All the Light We Cannot See | C70: =IFERROR(INDEX($V$55:$V$542, MATCH(LARGE($AK$55:$AK$542,A70), $AK$55:$AK$542, 0)), "") -> Anthony Doerr | D70: =IFERROR(INDEX($W$55:$W$542, MATCH(LARGE($AK$55:$AK$542,A70), $AK$55:$AK$542, 0)), "") -> Historical Fiction | E70: =IFERROR(INDEX($Y$55:$Y$542, MATCH(LARGE($AK$55:$AK$542,A70), $AK$55:$AK$542, 0)), "") -> 180000 | F70: =IFERROR(ROUND(INDEX($AF$55:$AF$542, MATCH(LARGE($AK$55:$AK$542,A70), $AK$55:$AK$542, 0)),2), "") -> 8.71 | G70: =IFERROR(INDEX($T$55:$T$542, MATCH(LARGE($AK$55:$AK$542,A70), $AK$55:$AK$542, 0)), "") -> 24 | H70: =IFERROR(INDEX($X$55:$X$542, MATCH(LARGE($AK$55:$AK$542,A70), $AK$55:$AK$542, 0)), "") -> Standalone | I70: =IFERROR(_xlfn.XLOOKUP(B70,$U$55:$U$542,$AH$55:$AH$542),"") -> Doerr's Pulitzer-winning WWII novel — blind Marie-Laure and German radio prodigy Werner converge in occupied Saint-Malo through a luminous dual-timeline structure. Aesthetics (9.10) is the highest in HistFic section — Doerr's prose is genuinely lyrical and shelf-grade. Theme 8.70 / Char 9.00 round it out. Analog: LF-Masters cluster (8.61) for literary craft tier. Predicted WA 8.59 → Rank ~22. Confidence caveat: Emotional Impact (9.0) is highest-risk — the convergent finale either lands devastating or feels overly engineered; 7.5-9.5 plausible. | J70: =IFERROR(_xlfn.XLOOKUP(B70,$U$55:$U$542,$AI$55:$AI$542),"") -> existential, philosophical, introspective, alienation, bleak, cerebral, slow | K70: =IF($B70="",FALSE,IFERROR(_xlfn.XLOOKUP($B70,Recommendations!$D:$D,Recommendations!$AJ:$AJ),FALSE)) -> FALSE | L70: =IF($B70="",FALSE,OR($K70=TRUE,$B70=BookTracker!$B$9)) -> FALSE | N70: {=IF(INDEX($P:$P,ROW()-1)="","",IF(OR(IFERROR(_xlfn.XLOOKUP(INDEX($P:$P,ROW()-1),Recommendations!$D:$D,Recommendations!$AJ:$AJ),FALSE)=TRUE,INDEX($P:$P,ROW()-1)=BookTracker!$B$9),"",ROW()-1))} | O70: The Licanius Trilogy | T70: =IFERROR(_xlfn.XLOOKUP(U70,Recommendations!$D:$D,Recommendations!$A:$A),"") -> 104 | U70: {=IFERROR(INDEX(Recommendations!$D:$D,SMALL($AL$2:$AL$488,ROW()-55)),"")} -> The First Chronicles of Druss the Legend | V70: =IFERROR(_xlfn.XLOOKUP(U70,Recommendations!$D:$D,Recommendations!$F:$F),"") -> David Gemmell | W70: =IFERROR(_xlfn.XLOOKUP(U70,Recommendations!$D:$D,Recommendations!$E:$E),"") -> Epic Fantasy | X70: =IFERROR(_xlfn.XLOOKUP(U70,Recommendations!$D:$D,Recommendations!$G:$G),"") -> Drenai Saga | Y70: =IFERROR(_xlfn.XLOOKUP(U70,Recommendations!$D:$D,Recommendations!$H:$H),"") -> 115000 | Z70: =IF($U70="","",IFERROR(AVERAGE(INDEX(Recommendations!$K:$K,$AM70),INDEX(Recommendations!$I:$I,$AM70),INDEX(Recommendations!$J:$J,$AM70)),0)) -> 7.45 | AA70: =IF($U70="","",IFERROR(AVERAGE(INDEX(Recommendations!$X:$X,$AM70),INDEX(Recommendations!$Y:$Y,$AM70)),0)) -> 6.4 | AB70: =IF($U70="","",IFERROR(AVERAGE(INDEX(Recommendations!$P:$P,$AM70),INDEX(Recommendations!$O:$O,$AM70),INDEX(Recommendations!$R:$R,$AM70)),0)) -> 6.5777778 | AC70: =IF($U70="","",IFERROR(AVERAGE(INDEX(Recommendations!$AB:$AB,$AM70),INDEX(Recommendations!$AD:$AD,$AM70),INDEX(Recommendations!$T:$T,$AM70)),0)) -> 6.0333333 | AD70: =IF($U70="","",IFERROR(AVERAGE(INDEX(Recommendations!$I:$I,$AM70),INDEX(Recommendations!$L:$L,$AM70),INDEX(Recommendations!$J:$J,$AM70)),0)) -> 7.1833333 | AE70: =IF($U70="","",IFERROR(AVERAGE(INDEX(Recommendations!$O:$O,$AM70),INDEX(Recommendations!$Q:$Q,$AM70)),0)) -> 6.55 | AF70: {=IF($U70="","",IFERROR(IF(SUM($B$24:$B$29)=0,INDEX(Recommendations!$B:$B,$AM70),(Z70*$B$24+AA70*$B$25+AB70*$B$26+AC70*$B$27+AD70*$B$28+AE70*$B$29)/SUM($B$24:$B$29)),0))} -> 6.5075 | AG70: =IFERROR(IF(ISNUMBER(AF70),IF(AF70=0,0,AF70+ROW()/10000000),0),0) -> 6.507507 | AH70: =IFERROR(_xlfn.XLOOKUP(U70,Recommendations!$D:$D,Recommendations!$AK:$AK),"") -> Druss origin prequel to Legend — mountain villager to Captain of the Axe. Goodreads 4.13. Predicted Total Avg 6.44 → Rank ~80, essentially Legend-equivalent on Total Avg with Story (7.32) doing the work via Action (7.8) peak. Closest analog among your low cluster: Eye of the World (~7.0) for the propulsive bildungsroman structure, though Gemmell stays leaner. Confidence caveat: Multi-Dim (5.8) is the floor — single-POV adventure, no ensemble payoff. | AI70: =IFERROR(_xlfn.XLOOKUP(U70,Recommendations!$D:$D,Recommendations!$AL:$AL),"") -> heroic fantasy, origin, adventure, episodic, gritty, fast-paced, legendary, action | AJ70: =IF($B$37="",TRUE,IFERROR(ISNUMBER(SEARCH($B$37,AI70))+ISNUMBER(SEARCH($B$37,U70))+ISNUMBER(SEARCH($B$37,W70))>0,FALSE)) -> TRUE | AK70: =IFERROR(IF(AND(AJ70=TRUE,_xlfn.XLOOKUP(U70,Recommendations!$D:$D,Recommendations!$AJ:$AJ,FALSE)<>TRUE,IF($B$33="Any",TRUE,W70=$B$33),IF($B$34="Any",TRUE,IF($B$34="Short (<150K)",Y70<150000,IF($B$34="Medium (150-300K)",(Y70>=150000)*(Y70<=300000),Y70>300000))),IF($B$35="Any",TRUE,IF($B$35="Standalone",X70="Standalone",X70<>"Standalone")),IF($B$36="Any",TRUE,ISNUMBER(SEARCH($B$36,V70)))),IF(ISNUMBER(AF70),IF(AF70=0,0,AF70+ROW()/10000000),0),-ROW()/10000000),0) -> 6.507507 | AL70: {=IF(INDEX(Recommendations!$D:$D,ROW())="","",IF(INDEX(Recommendations!$AJ:$AJ,ROW())=TRUE,"",ROW()))} -> 70 | AM70: =IF($U70="","",IFERROR(MATCH($U70,Recommendations!$D:$D,0),"")) -> 16
A71: =31 -> 31 | B71: =IFERROR(INDEX($U$55:$U$542, MATCH(LARGE($AK$55:$AK$542,A71), $AK$55:$AK$542, 0)), "") -> Tigana | C71: =IFERROR(INDEX($V$55:$V$542, MATCH(LARGE($AK$55:$AK$542,A71), $AK$55:$AK$542, 0)), "") -> Guy Gavriel Kay | D71: =IFERROR(INDEX($W$55:$W$542, MATCH(LARGE($AK$55:$AK$542,A71), $AK$55:$AK$542, 0)), "") -> Epic Fantasy | E71: =IFERROR(INDEX($Y$55:$Y$542, MATCH(LARGE($AK$55:$AK$542,A71), $AK$55:$AK$542, 0)), "") -> 290000 | F71: =IFERROR(ROUND(INDEX($AF$55:$AF$542, MATCH(LARGE($AK$55:$AK$542,A71), $AK$55:$AK$542, 0)),2), "") -> 8.7 | G71: =IFERROR(INDEX($T$55:$T$542, MATCH(LARGE($AK$55:$AK$542,A71), $AK$55:$AK$542, 0)), "") -> 22 | H71: =IFERROR(INDEX($X$55:$X$542, MATCH(LARGE($AK$55:$AK$542,A71), $AK$55:$AK$542, 0)), "") -> Standalone | I71: =IFERROR(_xlfn.XLOOKUP(B71,$U$55:$U$542,$AH$55:$AH$542),"") -> Standalone literary epic fantasy about a conquered nation whose name has been magically erased from memory — widely cited as one of the most emotionally devastating fantasies ever written. Strongest predicted dimensions are Prose, Emotional Impact, and Ending, with GGK at peak craft. Closest analog: A Song for Arbonne's lyricism (Lit Fantasy is already strong for you) repurposed into a tighter, sadder, single-volume epic. Confidence caveat: Action (predicted 6.6) is highest-risk — Tigana is contemplative and political with minimal battle sequences, so this could land 5.0–7.5 depending on tolerance for slow-burn pacing. | J71: =IFERROR(_xlfn.XLOOKUP(B71,$U$55:$U$542,$AI$55:$AI$542),"") -> quest, rescue, melancholic, emotional, magic, foreboding, slow-burn | K71: =IF($B71="",FALSE,IFERROR(_xlfn.XLOOKUP($B71,Recommendations!$D:$D,Recommendations!$AJ:$AJ),FALSE)) -> FALSE | L71: =IF($B71="",FALSE,OR($K71=TRUE,$B71=BookTracker!$B$9)) -> FALSE | N71: {=IF(INDEX($P:$P,ROW()-1)="","",IF(OR(IFERROR(_xlfn.XLOOKUP(INDEX($P:$P,ROW()-1),Recommendations!$D:$D,Recommendations!$AJ:$AJ),FALSE)=TRUE,INDEX($P:$P,ROW()-1)=BookTracker!$B$9),"",ROW()-1))} | O71: The Locked Tomb | T71: =IFERROR(_xlfn.XLOOKUP(U71,Recommendations!$D:$D,Recommendations!$A:$A),"") -> 104 | U71: {=IFERROR(INDEX(Recommendations!$D:$D,SMALL($AL$2:$AL$488,ROW()-55)),"")} -> Winter Warriors | V71: =IFERROR(_xlfn.XLOOKUP(U71,Recommendations!$D:$D,Recommendations!$F:$F),"") -> David Gemmell | W71: =IFERROR(_xlfn.XLOOKUP(U71,Recommendations!$D:$D,Recommendations!$E:$E),"") -> Epic Fantasy | X71: =IFERROR(_xlfn.XLOOKUP(U71,Recommendations!$D:$D,Recommendations!$G:$G),"") -> Drenai Saga | Y71: =IFERROR(_xlfn.XLOOKUP(U71,Recommendations!$D:$D,Recommendations!$H:$H),"") -> 100000 | Z71: =IF($U71="","",IFERROR(AVERAGE(INDEX(Recommendations!$K:$K,$AM71),INDEX(Recommendations!$I:$I,$AM71),INDEX(Recommendations!$J:$J,$AM71)),0)) -> 7.0166667 | AA71: =IF($U71="","",IFERROR(AVERAGE(INDEX(Recommendations!$X:$X,$AM71),INDEX(Recommendations!$Y:$Y,$AM71)),0)) -> 6.65 | AB71: =IF($U71="","",IFERROR(AVERAGE(INDEX(Recommendations!$P:$P,$AM71),INDEX(Recommendations!$O:$O,$AM71),INDEX(Recommendations!$R:$R,$AM71)),0)) -> 6.6333333 | AC71: =IF($U71="","",IFERROR(AVERAGE(INDEX(Recommendations!$AB:$AB,$AM71),INDEX(Recommendations!$AD:$AD,$AM71),INDEX(Recommendations!$T:$T,$AM71)),0)) -> 5.9666667 | AD71: =IF($U71="","",IFERROR(AVERAGE(INDEX(Recommendations!$I:$I,$AM71),INDEX(Recommendations!$L:$L,$AM71),INDEX(Recommendations!$J:$J,$AM71)),0)) -> 7.0166667 | AE71: =IF($U71="","",IFERROR(AVERAGE(INDEX(Recommendations!$O:$O,$AM71),INDEX(Recommendations!$Q:$Q,$AM71)),0)) -> 6.4 | AF71: {=IF($U71="","",IFERROR(IF(SUM($B$24:$B$29)=0,INDEX(Recommendations!$B:$B,$AM71),(Z71*$B$24+AA71*$B$25+AB71*$B$26+AC71*$B$27+AD71*$B$28+AE71*$B$29)/SUM($B$24:$B$29)),0))} -> 6.4741667 | AG71: =IFERROR(IF(ISNUMBER(AF71),IF(AF71=0,0,AF71+ROW()/10000000),0),0) -> 6.4741738 | AH71: =IFERROR(_xlfn.XLOOKUP(U71,Recommendations!$D:$D,Recommendations!$AK:$AK),"") -> Aging veterans on a final mission — mortality theme is pure Gemmell wheelhouse and Theme (6.70) is the second-highest of any Drenai book (only the Waylander trilogy beats it). Goodreads 4.07. Predicted Total Avg 6.43 → Rank ~80. EmoImpact (7.0) and Ending (7.3) carry the read. Confidence caveat: Action (7.3) is restrained vs Druss-centric books — this is the contemplative end-of-life entry, sits closest to your Tigana/Kay mood without the prose. | AI71: =IFERROR(_xlfn.XLOOKUP(U71,Recommendations!$D:$D,Recommendations!$AL:$AL),"") -> heroic fantasy, war, survival, aging-hero, gritty, bleak, action, camaraderie | AJ71: =IF($B$37="",TRUE,IFERROR(ISNUMBER(SEARCH($B$37,AI71))+ISNUMBER(SEARCH($B$37,U71))+ISNUMBER(SEARCH($B$37,W71))>0,FALSE)) -> TRUE | AK71: =IFERROR(IF(AND(AJ71=TRUE,_xlfn.XLOOKUP(U71,Recommendations!$D:$D,Recommendations!$AJ:$AJ,FALSE)<>TRUE,IF($B$33="Any",TRUE,W71=$B$33),IF($B$34="Any",TRUE,IF($B$34="Short (<150K)",Y71<150000,IF($B$34="Medium (150-300K)",(Y71>=150000)*(Y71<=300000),Y71>300000))),IF($B$35="Any",TRUE,IF($B$35="Standalone",X71="Standalone",X71<>"Standalone")),IF($B$36="Any",TRUE,ISNUMBER(SEARCH($B$36,V71)))),IF(ISNUMBER(AF71),IF(AF71=0,0,AF71+ROW()/10000000),0),-ROW()/10000000),0) -> 6.4741738 | AL71: {=IF(INDEX(Recommendations!$D:$D,ROW())="","",IF(INDEX(Recommendations!$AJ:$AJ,ROW())=TRUE,"",ROW()))} -> 71 | AM71: =IF($U71="","",IFERROR(MATCH($U71,Recommendations!$D:$D,0),"")) -> 17
